Workbook
Name SegmentaciónDeDatos_CANAL: #N/A
Name SegmentaciónDeDatos_DESTINO: #N/A
Name SegmentaciónDeDatos_DESTINO1: #N/A
Name SegmentaciónDeDatos_DESTINO2: #N/A
Name SegmentaciónDeDatos_DESTINO3: #N/A
Name SegmentaciónDeDatos_Edad1: #N/A
Name SegmentaciónDeDatos_GRUPO1: #N/A
Name SegmentaciónDeDatos_INVENTARIO: #N/A
Name SegmentaciónDeDatos_TIPO: #N/A
Name SegmentaciónDeDatos_TIPO_2: #N/A
Name SegmentaciónDeDatos_TIPO_DE_HUEVO: #N/A
Name SegmentaciónDeDatos_TIPO_DE_HUEVO1: #N/A
Name SegmentaciónDeDatos_TIPO_DE_HUEVO2: #N/A
Name SegmentaciónDeDatos_TIPO_HUEVO: #N/A
Name SegmentaciónDeDatos_tipo1: #N/A
Name SegmentaciónDeDatos_ZONA1: #N/A

Sheet Detalle1
A1: Detalles para Cantidades - CANAL: 0
A3: articulo | B3: descripcion_articulo | C3: id_unidad | D3: cantidad | E3: por_dsto | F3: ind_iva_venta | G3: iva_ventas | H3: por_iva | I3: precio_unitario | J3: codigo_linea | K3: descripcion_linea | L3: costo_promedio | M3: fecha | N3: codigo_plu | O3: descripcion | P3: cod_barras1 | Q3: id_bodega | R3: num_piezas | S3: id_item_bodega | T3: DESTINO | U3: GRUPO | V3: TIPO DE HUEVO | W3: TIPO DE HUEVO 2 | X3: ZONA | Y3: P | Z3: MAY | AA3: GRUPO 2 | AB3: CANAL
A4: 112207 | B4: HUEVO XL X 15 PET | C4: UN | D4: 360 | F4: S | G4: IV82 | J4: HU | K4: HUEVO COMERCIAL | L4: 599.68 | M4: 46210 | O4: BODEGA KIKES | P4: 112207 | Q4: KI | R4: 0 | T4: LANZA | U4: PLANTA CLASIFICACION | V4: XL | W4: EMPACADOS | X4: - | Y4: SANTANDER | Z4: 0 | AA4: BODEGA | AB4: 0

Sheet RESUMEN
N7: EDADES CEDIS MAYOR A 5 DIAS | U7: EDADES PLANTAS MAYOR A 4 DÍAS
AE8: TIPO DE HUEVO 2 | AF8: VERDE
N9: Edad | O9: (Varios elementos) | U9: Edad | V9: (Varios elementos)
AC10: TIPO DE HUEVO 2 | AD10: VERDE | AE10: Prom Actual
B11: Etiquetas de fila | C11: CANTIDADES | E11: cantidad | F11: Etiquetas de columna | N11: Suma de CANTIDAD | O11: tipo | U11: Suma de CANTIDAD | V11: tipo | AE11: 760492.5
B12: VEHICULOS | C12: 2489681 | E12: Etiquetas de fila | F12: VERDE | G12: SEGUNDA | H12: HUEVO SIN CLASIFICAR | I12: GRIS SUELTO | J12: ETIQUETA | K12: EMPACADOS | L12: Total general | N12: DESTINO | O12: VERDE | P12: EMPACADOS | Q12: Total general | U12: DESTINO | V12: VERDE | W12: GRIS SUELTO | X12: SEGUNDA | Y12: Total general | AC12: Etiquetas de fila | AD12: CANTIDAD. | AE12: DIAS DE INVENTARIO | AJ12: INVENTARIO POR PLANTA
B13: BODEGA | C13: 8194931 | E13: BODEGA | F13: 3488265 | G13: 26180 | I13: 2549331 | J13: 5647 | K13: 2125508 | L13: 8194931 | N13: TAT BARRANQUILLA | O13: 206275 | P13: 9360 | Q13: 215635 | U13: ALKA1 | W13: 13370 | Y13: 13370 | AC13: VEHICULOS | AD13: 743277 | AE13: =AD13/$AE$11 -> 0.9773627 | AJ13: TIPO | AK13: LANZA | AL13: BELLAVISTA | AM13: ALKA 1 | AN13: ALKA 2 | AO13: PALMAS | AP13: BQ | AQ13: MONTERIA | AR13: CALI | AS13: BODEGA KIGT | AT13: TOTAL
B14: TRANSITO | C14: 4854662 | E14: HUEVO SIN CLASIFICAR | H14: 2746557 | L14: 2746557 | N14: TAT BOGOTA MONTEVIDEO | O14: 117120 | P14: 51955 | Q14: 169075 | U14: ALKA2 | V14: 48669 | Y14: 48669 | AC14: BODEGA | AD14: 1371925 | AE14: =AD14/$AE$11 -> 1.8039954 | AJ14: AAA | AK14: 4530 | AL14: 0 | AM14: 10275 | AN14: 0 | AO14: 45069 | AP14: 0 | AQ14: 0 | AR14: 0 | AS14: 0 | AT14: 59874
B15: PLANTA CLASIFICACION | C15: 4431580 | E15: PLANTA CLASIFICACION | F15: 1398924 | G15: 593943 | I15: 2012773 | K15: 425940 | L15: 4431580 | N15: TAT BOGOTA SIBERIA | O15: 54720 | P15: 1560 | Q15: 56280 | U15: BELLAVISTA | W15: 18532 | X15: 1846 | Y15: 20378 | AC15: TRANSITO | AD15: 792024 | AE15: =AD15/$AE$11 -> 1.0414619 | AJ15: AA | AK15: 30030 | AL15: 0 | AM15: 15450 | AN15: 0 | AO15: 35109 | AP15: 0 | AQ15: 0 | AR15: 0 | AS15: 0 | AT15: 80589
B16: HUEVO SIN CLASIFICAR | C16: 2746557 | E16: TRANSITO | F16: 1895244 | I16: 2460260 | J16: 12000 | K16: 487158 | L16: 4854662 | N16: TAT CALI | O16: 67556 | P16: 2595 | Q16: 70151 | U16: PALMAS | W16: 12788 | Y16: 12788 | AC16: PLANTA CLASIFICACION | AD16: 463103 | AE16: =AD16/$AE$11 -> 0.60895144 | AJ16: A | AK16: 16080 | AL16: 0 | AM16: 9723 | AN16: 0 | AO16: 18346 | AP16: 0 | AQ16: 0 | AR16: 0 | AS16: 0 | AT16: 44149
B17: Total general | C17: 22717411 | E17: VEHICULOS | F17: 2230735 | J17: 21425 | K17: 237521 | L17: 2489681 | N17: TAT CARTAGENA | P17: 34488 | Q17: 34488 | U17: Total general | V17: 48669 | W17: 44690 | X17: 1846 | Y17: 95205 | AC17: Total general | AD17: 3370329 | AE17: =SUM(AE13:AE16) -> 4.4317715 | AJ17: B | AK17: 2580 | AL17: 0 | AM17: 492 | AN17: 0 | AO17: 6548 | AP17: 0 | AQ17: 0 | AR17: 0 | AS17: 0 | AT17: 9620
E18: Total general | F18: 9013168 | G18: 620123 | H18: 2746557 | I18: 7022364 | J18: 39072 | K18: 3276127 | L18: 22717411 | N18: TAT MEDELLIN | O18: 215580 | P18: 5940 | Q18: 221520 | AJ18: C | AK18: 25680 | AL18: 99398 | AM18: 9212 | AN18: 9810 | AO18: 29832 | AP18: 0 | AQ18: 0 | AR18: 0 | AS18: 0 | AT18: 173932
N19: TAT PASTO | O19: 19623 | P19: 10590 | Q19: 30213 | AJ19: SEGUNDA | AK19: 8100 | AL19: 23895 | AM19: 0 | AN19: 0 | AO19: 0 | AP19: 0 | AQ19: 0 | AR19: 0 | AS19: 0 | AT19: 31995
N20: TAT VALLEDUPAR | O20: 70726 | Q20: 70726 | AJ20: TOTAL | AK20: 87000 | AL20: 123293 | AM20: 45152 | AN20: 9810 | AO20: 134904 | AP20: 0 | AQ20: 0 | AR20: 0 | AS20: 0 | AT20: 400159
N21: TAT VILLAVICENCIO | O21: 13754 | Q21: 13754 | U21: PLANTAS | V21: CAP TOTAL | W21: CAP CON EQUIPO | X21: TOTAL PLANTA | Y21: % | AC21: CEDIS | AD21: CAP MAXIMA | AE21: TOTAL CEDI | AF21: %
N22: TAT BUCARAMANGA | P22: 14004 | Q22: 14004 | U22: ALKA1 | V22: 4134960 | W22: 3199960 | X22: =SUMIF(inv!T$1:T$1164,RESUMEN!U22,inv!D$1:D$1164) -> 852724 | Y22: =X22/W22 -> 0.26647958 | AC22: TAT PEREIRA | AD22: 226000 | AE22: =SUMIFS(inv!D$1:D$1164,inv!T$1:T$1164,RESUMEN!AC22,inv!U$1:U$1164,"<>VEHICULOS") -> 30427 | AF22: =AE22/AD22 -> 0.13463274
N23: TAT CUCUTA | O23: 57350 | P23: 1920 | Q23: 59270 | U23: ALKA2 | V23: 1247760 | W23: 907760 | X23: =SUMIF(inv!T$1:T$1164,RESUMEN!U23,inv!D$1:D$1164) -> 749062 | Y23: =X23/W23 -> 0.82517626 | AC23: TAT VALLEDUPAR | AD23: 450000 | AE23: =SUMIFS(inv!D$1:D$1164,inv!T$1:T$1164,RESUMEN!AC23,inv!U$1:U$1164,"<>VEHICULOS") -> 175663 | AF23: =AE23/AD23 -> 0.39036222
N24: TAT MONTERIA | O24: 124807 | P24: 1710 | Q24: 126517 | U24: PALMAS | V24: 2085120 | W24: 1575120 | X24: =SUMIF(inv!T$1:T$1164,RESUMEN!U24,inv!D$1:D$1164) -> 1062135 | Y24: =X24/W24 -> 0.67432005 | AC24: TAT BUCARAMANGA | AD24: 200000 | AE24: =SUMIFS(inv!D$1:D$1164,inv!T$1:T$1164,RESUMEN!AC24,inv!U$1:U$1164,"<>VEHICULOS") -> 224814 | AF24: =AE24/AD24 -> 1.12407
N25: TAT SANTA MARTA | P25: 2457 | Q25: 2457 | U25: BELLAVISTA | V25: 3200000 | W25: 2100000 | X25: =SUMIF(inv!T$1:T$1164,RESUMEN!U25,inv!D$1:D$1164) -> 430976 | Y25: =X25/W25 -> 0.20522667 | AC25: TAT BOGOTA MONTEVIDEO | AD25: 1486000 | AE25: =SUMIFS(inv!D$1:D$1164,inv!T$1:T$1164,RESUMEN!AC25,inv!U$1:U$1164,"<>VEHICULOS") -> 910912 | AF25: =AE25/AD25 -> 0.61299596
N26: Total general | O26: 947511 | P26: 136579 | Q26: 1084090 | U26: LANZA | V26: 2500000 | W26: 2500000 | X26: =SUMIF(inv!T$1:T$1164,RESUMEN!U26,inv!D$1:D$1164) -> 1976014 | Y26: =X26/W26 -> 0.7904056 | AC26: TAT BOGOTA SIBERIA | AD26: 835800 | AE26: =SUMIFS(inv!D$1:D$1164,inv!T$1:T$1164,RESUMEN!AC26,inv!U$1:U$1164,"<>VEHICULOS") -> 132806 | AF26: =AE26/AD26 -> 0.15889687
AC27: TAT CE BOGOTA | AD27: 713000 | AE27: =SUMIFS(inv!D$1:D$1164,inv!T$1:T$1164,RESUMEN!AC27,inv!U$1:U$1164,"<>VEHICULOS") -> 1474546 | AF27: =AE27/AD27 -> 2.068087
AC28: TAT MONTERIA | AD28: 359040 | AE28: =SUMIFS(inv!D$1:D$1164,inv!T$1:T$1164,RESUMEN!AC28,inv!U$1:U$1164,"<>VEHICULOS") -> 286186 | AF28: =AE28/AD28 -> 0.79708668
AC29: TAT CARTAGENA | AD29: 864000 | AE29: =SUMIFS(inv!D$1:D$1164,inv!T$1:T$1164,RESUMEN!AC29,inv!U$1:U$1164,"<>VEHICULOS") -> 1236253 | AF29: =AE29/AD29 -> 1.4308484
AC30: TAT CALI | AD30: 910440 | AE30: =SUMIFS(inv!D$1:D$1164,inv!T$1:T$1164,RESUMEN!AC30,inv!U$1:U$1164,"<>VEHICULOS") -> 566851 | AF30: =AE30/AD30 -> 0.62261214
AC31: TAT MEDELLIN | AD31: 950400 | AE31: =SUMIFS(inv!D$1:D$1164,inv!T$1:T$1164,RESUMEN!AC31,inv!U$1:U$1164,"<>VEHICULOS") -> 887995 | AF31: =AE31/AD31 -> 0.93433817
AC32: TAT PASTO | AD32: 900000 | AE32: =SUMIFS(inv!D$1:D$1164,inv!T$1:T$1164,RESUMEN!AC32,inv!U$1:U$1164,"<>VEHICULOS") -> 536155 | AF32: =AE32/AD32 -> 0.59572778
B33: Etiquetas de fila | C33: Inventario | D33: Venta Mes | E33: Días de Venta | F33: Venta/Día | G33: Días de Inv | H33: Ventas Prom | I33: Días de Inv | J33: Días Ideales | K33: Inv Ideal | L33: Inv-ideal | AC33: TAT SANTA MARTA | AD33: 450000 | AE33: =SUMIFS(inv!D$1:D$1164,inv!T$1:T$1164,RESUMEN!AC33,inv!U$1:U$1164,"<>VEHICULOS") -> 237649 | AF33: =AE33/AD33 -> 0.52810889
B34: TAT | C34: 9896112 | D34: 58260250 | E34: 25 | F34: =D34/E34 -> 2330410 | G34: =C34/F34 -> 4.2465111 | H34: =SUMIFS('VENTAS CANAL'!$O:$O,'VENTAS CANAL'!$N:$N,RESUMEN!B34) -> 1622445.7 | I34: =IFERROR((C34/H34),0) -> 6.0995029 | J34: 5 | K34: =H34*J34 -> 8112228.3 | L34: =+GETPIVOTDATA("cantidad",$B$33,"CANAL","TAT")-K34 -> 1783883.7 | AC34: TAT POPAYAN | AD34: 460000 | AE34: =SUMIFS(inv!D$1:D$1164,inv!T$1:T$1164,RESUMEN!AC34,inv!U$1:U$1164,"<>VEHICULOS") -> 463597 | AF34: =AE34/AD34 -> 1.0078196
B35: HD | C35: 8074772 | D35: 62000000 | E35: 28 | F35: =D35/E35 -> 2214285.7 | G35: =C35/F35 -> 3.6466712 | H35: =SUMIFS('VENTAS CANAL'!$O:$O,'VENTAS CANAL'!$N:$N,RESUMEN!B35) -> 2359374 | I35: =IFERROR((C35/H35),0) -> 3.4224214 | J35: 3.5 | K35: =H35*J35 -> 8257809 | L35: =+GETPIVOTDATA("cantidad",$B$33,"CANAL","HD")-K35 -> -183037 | AC35: TAT CUCUTA | AD35: 600000 | AE35: =SUMIFS(inv!D$1:D$1164,inv!T$1:T$1164,RESUMEN!AC35,inv!U$1:U$1164,"<>VEHICULOS") -> 254772 | AF35: =AE35/AD35 -> 0.42462
B36: AU/FS/GS | C36: 896242 | D36: 20650000 | E36: 25 | F36: =D36/E36 -> 826000 | G36: =C36/F36 -> 1.0850387 | H36: =SUMIFS('VENTAS CANAL'!$O:$O,'VENTAS CANAL'!$N:$N,RESUMEN!B36) -> 499374.67 | I36: =IFERROR((C36/H36),0) -> 1.7947286 | J36: 3 | K36: =H36*J36 -> 1498124 | L36: =+GETPIVOTDATA("cantidad",$B$33,"CANAL","AU/FS/GS")-K36 -> -601882 | AC36: TAT CE BARRANQUILLA | AD36: 2534400 | AE36: =SUMIFS(inv!D$1:D$1164,inv!T$1:T$1164,RESUMEN!AC36,inv!U$1:U$1164,"<>VEHICULOS") -> 2514933 | AF36: =AE36/AD36 -> 0.99231889
B37: MAY | C37: 483605 | D37: 7436798.7 | E37: 25 | F37: =D37/E37 -> 297471.95 | G37: =C37/F37 -> 1.6257163 | H37: =SUMIFS('VENTAS CANAL'!$O:$O,'VENTAS CANAL'!$N:$N,RESUMEN!B37) -> 63258 | I37: =IFERROR((C37/H37),0) -> 7.6449619 | J37: 3 | K37: =H37*J37 -> 189774 | L37: =+GETPIVOTDATA("cantidad",$B$33,"CANAL","MAY")-K37 -> 293831 | AC37: TAT CE MONTERIA | AD37: 673200 | AE37: =SUMIFS(inv!D$1:D$1164,inv!T$1:T$1164,RESUMEN!AC37,inv!U$1:U$1164,"<>VEHICULOS") -> 868584 | AF37: =AE37/AD37 -> 1.2902317
B38: SEGUNDA | C38: 620123 | D38: 6342000 | E38: 25 | F38: =D38/E38 -> 253680 | G38: =C38/F38 -> 2.4445088 | H38: =SUMIFS('VENTAS CANAL'!$O:$O,'VENTAS CANAL'!$N:$N,RESUMEN!B38) -> 252615 | I38: =IFERROR((C38/H38),0) -> 2.4548146 | J38: 3 | K38: =H38*J38 -> 757845 | L38: =+GETPIVOTDATA("cantidad",$B$33,"CANAL","SEGUNDA")-K38 -> -137722 | AC38: TAT BARRANQUILLA | AD38: 950400 | AE38: =SUMIFS(inv!D$1:D$1164,inv!T$1:T$1164,RESUMEN!AC38,inv!U$1:U$1164,"<>VEHICULOS") -> 792770 | AF38: =AE38/AD38 -> 0.83414352
B39: SIN CL | C39: 2746557 | D39: 45589609 | E39: 30 | F39: =D39/E39 -> 1519653.6 | G39: =C39/F39 -> 1.8073573 | H39: =F39 -> 1519653.6 | I39: =IFERROR((C39/H39),0) -> 1.8073573 | J39: 1.5 | K39: =H39*J39 -> 2279480.4 | L39: =+GETPIVOTDATA("cantidad",$B$33,"CANAL","SIN CL")-K39 -> 467076.56 | AC39: TAT SINCELEJO | AD39: 400000 | AE39: =SUMIFS(inv!D$1:D$1164,inv!T$1:T$1164,RESUMEN!AC39,inv!U$1:U$1164,"<>VEHICULOS") -> 37518 | AF39: =AE39/AD39 -> 0.093795
B40: Total general | C40: 22717411 | F40: =+SUM(F34:F38) -> 5921847.7 | G40: =C40/F40 -> 3.8362032 | H40: =+SUM(H34:H38) -> 4797067.3 | K40: =SUM(K34:K39) -> 21095261 | L40: =+SUM(L34:L39) -> 1622150.2 | AC40: TAT VILLAVICENCIO | AD40: 110000 | AE40: =SUMIFS(inv!D$1:D$1164,inv!T$1:T$1164,RESUMEN!AC40,inv!U$1:U$1164,"<>VEHICULOS") -> 82874 | AF40: =AE40/AD40 -> 0.7534

Sheet EDADES
A1: VOLVER
D6: DESTINO | E6: Edad | F6: Item | G6: Referencia | H6: Suma de CANTIDAD2
D7: ALKA1 | E7: 8 | F7: 75201 | G7: HUEVO AAA X 30 CARTON GRIS LZ | H7: 4224
D8: ALKA1 | E8: 7 | F8: 75201 | G8: HUEVO AAA X 30 CARTON GRIS LZ | H8: 3206
D9: ALKA1 | E9: 6 | F9: 75201 | G9: HUEVO AAA X 30 CARTON GRIS LZ | H9: 5940
D10: ALKA1 | E10: 4 | F10: 75201 | G10: HUEVO AAA X 30 CARTON GRIS LZ | H10: 8038
D11: ALKA1 | E11: 4 | F11: 75301 | G11: HUEVO AA X 30 CARTON GRIS LZ | H11: 90
D12: ALKA1 | E12: 4 | F12: 75401 | G12: HUEVO A X 30 CARTON GRIS LZ | H12: 76
D13: ALKA1 | E13: 4 | F13: 75501 | G13: HUEVO B X 30 CARTON GRIS LZ | H13: 172
D14: ALKA1 | E14: 4 | F14: 79110 | G14: HUEVO ROTO - ZF | H14: 3300
D15: ALKA1 | E15: 4 | F15: 2110402 | G15: HUEVO M X 30 CARTON VERDE CANASTA | H15: 120
D16: ALKA1 | E16: 4 | F16: 2110202 | G16: HUEVO XL X 30 CARTON VERDE CANASTA | H16: 31317
D17: ALKA1 | E17: 3 | F17: 10601 | G17: HUEVO CX30 CARTON GRIS | H17: 98
D18: ALKA1 | E18: 3 | F18: 73001 | G18: HUEVO PICADO ROJO | H18: 18109
... D46: ALKA1 | E46: 1 | F46: 2410401 | G46: HUEVO CE X 30 CARTON GRIS CANASTA | H46: 302316
D47: Total ALKA1 | H47: 852724
D48: ALKA2 | E48: 6 | F48: 2110202 | G48: HUEVO XL X 30 CARTON VERDE CANASTA | H48: 25200
D49: ALKA2 | E49: 5 | F49: 2110202 | G49: HUEVO XL X 30 CARTON VERDE CANASTA | H49: 22509
D50: ALKA2 | E50: 5 | F50: 2010102 | G50: HUEVO YUMBO X20 CARTON VERDE CANASTA | H50: 960
D51: ALKA2 | E51: 4 | F51: 2110202 | G51: HUEVO XL X 30 CARTON VERDE CANASTA | H51: 44455
D52: ALKA2 | E52: 4 | F52: 2010102 | G52: HUEVO YUMBO X20 CARTON VERDE CANASTA | H52: 1352
D53: ALKA2 | E53: 3 | F53: 10601 | G53: HUEVO CX30 CARTON GRIS | H53: 1747
D54: ALKA2 | E54: 3 | F54: 73001 | G54: HUEVO PICADO ROJO | H54: 10577
D55: ALKA2 | E55: 3 | F55: 2110402 | G55: HUEVO M X 30 CARTON VERDE CANASTA | H55: 3257
D56: ALKA2 | E56: 3 | F56: 2110202 | G56: HUEVO XL X 30 CARTON VERDE CANASTA | H56: 29929
D57: ALKA2 | E57: 3 | F57: 2010102 | G57: HUEVO YUMBO X20 CARTON VERDE CANASTA | H57: 1014
D58: ALKA2 | E58: 2 | F58: 10601 | G58: HUEVO CX30 CARTON GRIS | H58: 3684
D59: ALKA2 | E59: 2 | F59: 72003 | G59: HUEVO SUCIO ZF MARCADO | H59: 3240
... D73: ALKA2 | E73: 1 | F73: 2410401 | G73: HUEVO CE X 30 CARTON GRIS CANASTA | H73: 180747
D74: Total ALKA2 | H74: 748353
D75: BELLAVISTA | E75: 6 | F75: 79101 | G75: HUEVO ROTO | H75: 1046
D76: BELLAVISTA | E76: 5 | F76: 10601 | G76: HUEVO CX30 CARTON GRIS | H76: 18532
D77: BELLAVISTA | E77: 5 | F77: 79101 | G77: HUEVO ROTO | H77: 800
D78: BELLAVISTA | E78: 4 | F78: 10501 | G78: HUEVO B X30 CARTON GRIS | H78: 19844
D79: BELLAVISTA | E79: 4 | F79: 10601 | G79: HUEVO CX30 CARTON GRIS | H79: 27498
D80: BELLAVISTA | E80: 4 | F80: 79101 | G80: HUEVO ROTO | H80: 1253
D81: BELLAVISTA | E81: 4 | F81: 79111 | G81: HUEVO ROTO ZF- SANTANDER | H81: 5235
D82: BELLAVISTA | E82: 4 | F82: 2010501 | G82: HUEVO B X30 CARTON GRIS CANASTA | H82: 3918
D83: BELLAVISTA | E83: 3 | F83: 10501 | G83: HUEVO B X30 CARTON GRIS | H83: 18444
D84: BELLAVISTA | E84: 3 | F84: 10601 | G84: HUEVO CX30 CARTON GRIS | H84: 28691
D85: BELLAVISTA | E85: 3 | F85: 79101 | G85: HUEVO ROTO | H85: 1467
D86: BELLAVISTA | E86: 3 | F86: 79111 | G86: HUEVO ROTO ZF- SANTANDER | H86: 6057
... D108: BELLAVISTA | E108: 1 | F108: 2410401 | G108: HUEVO CE X 30 CARTON GRIS CANASTA | H108: 31991
D109: Total BELLAVISTA | H109: 431077
D110: LANZA | E110: 4 | F110: 79111 | G110: HUEVO ROTO ZF- SANTANDER | H110: 2400
D111: LANZA | E111: 4 | F111: 13459 | G111: HUEVO A X 300 BANDEJA GRIS ALAT CAJA AMARRADO | H111: 15600
D112: LANZA | E112: 4 | F112: 110303 | G112: HUEVO L X30 CARTON VERDE AMARRADO | H112: 8100
D113: LANZA | E113: 3 | F113: 75201 | G113: HUEVO AAA X 30 CARTON GRIS LZ | H113: 4530
D114: LANZA | E114: 3 | F114: 75301 | G114: HUEVO AA X 30 CARTON GRIS LZ | H114: 30030
D115: LANZA | E115: 3 | F115: 75401 | G115: HUEVO A X 30 CARTON GRIS LZ | H115: 16080
D116: LANZA | E116: 3 | F116: 75501 | G116: HUEVO B X 30 CARTON GRIS LZ | H116: 2580
D117: LANZA | E117: 3 | F117: 79111 | G117: HUEVO ROTO ZF- SANTANDER | H117: 3300
D118: LANZA | E118: 3 | F118: 152384 | G118: HUEVO L X 15 PAGUE 14 PET CAJA X 300. | H118: 5100
D119: LANZA | E119: 3 | F119: 2010102 | G119: HUEVO YUMBO X20 CARTON VERDE CANASTA | H119: 4814
D120: LANZA | E120: 3 | F120: 114379 | G120: HUEVO L X 30 PET CAJA X 300 PV. | H120: 1800
D121: LANZA | E121: 3 | F121: 272002 | G121: HUEVO SUCIO ZF SIN MARCA X 30 BANDEJA GRIS CANASTA | H121: 1392
... D142: LANZA | E142: 2 | F142: 272008 | G142: HUEVO SUCIO BASE LAVADO ZF X 30 BANDEJA GRIS CANASTA | H142: 45740
D143: Total LANZA | H143: 1096954
D144: PALMAS | E144: 5 | F144: 75201 | G144: HUEVO AAA X 30 CARTON GRIS LZ | H144: 12788
D145: PALMAS | E145: 4 | F145: 75201 | G145: HUEVO AAA X 30 CARTON GRIS LZ | H145: 17070
D146: PALMAS | E146: 3 | F146: 10601 | G146: HUEVO CX30 CARTON GRIS | H146: 7950
D147: PALMAS | E147: 3 | F147: 72003 | G147: HUEVO SUCIO ZF MARCADO | H147: 24211
D148: PALMAS | E148: 3 | F148: 73001 | G148: HUEVO PICADO ROJO | H148: 41675
D149: PALMAS | E149: 3 | F149: 75201 | G149: HUEVO AAA X 30 CARTON GRIS LZ | H149: 12407
D150: PALMAS | E150: 3 | F150: 75301 | G150: HUEVO AA X 30 CARTON GRIS LZ | H150: 13095
D151: PALMAS | E151: 3 | F151: 75401 | G151: HUEVO A X 30 CARTON GRIS LZ | H151: 4486
D152: PALMAS | E152: 3 | F152: 75501 | G152: HUEVO B X 30 CARTON GRIS LZ | H152: 2388
D153: PALMAS | E153: 3 | F153: 2110202 | G153: HUEVO XL X 30 CARTON VERDE CANASTA | H153: 19440
D154: PALMAS | E154: 2 | F154: 10601 | G154: HUEVO CX30 CARTON GRIS | H154: 11250
D155: PALMAS | E155: 2 | F155: 72003 | G155: HUEVO SUCIO ZF MARCADO | H155: 16570
... D173: PALMAS | E173: 1 | F173: 2410401 | G173: HUEVO CE X 30 CARTON GRIS CANASTA | H173: 168876
D174: Total PALMAS | H174: 1062183
D175: TAT BOGOTA MONTEVIDEO | E175: 8 | F175: 2110402 | G175: HUEVO M X 30 CARTON VERDE CANASTA | H175: 10560
D176: TAT BOGOTA MONTEVIDEO | E176: 6 | F176: 112268 | G176: HUEVO XL X 15 PET CAJA X 300 | H176: 10095
D177: TAT BOGOTA MONTEVIDEO | E177: 6 | F177: 112379 | G177: HUEVO L X 30 PET CAJA X 300 | H177: 27600
D178: TAT BOGOTA MONTEVIDEO | E178: 6 | F178: 152384 | G178: HUEVO L X 15 PAGUE 14 PET CAJA X 300. | H178: 6000
D179: TAT BOGOTA MONTEVIDEO | E179: 6 | F179: 2110302 | G179: HUEVO L X 30 CARTON VERDE CANASTA | H179: 6960
D180: TAT BOGOTA MONTEVIDEO | E180: 6 | F180: 2110402 | G180: HUEVO M X 30 CARTON VERDE CANASTA | H180: 21120
D181: TAT BOGOTA MONTEVIDEO | E181: 6 | F181: 2110202 | G181: HUEVO XL X 30 CARTON VERDE CANASTA | H181: 78480
D182: TAT BOGOTA MONTEVIDEO | E182: 6 | F182: 2152388 | G182: HUEVO L X 15 PAGUE 14 PET EN CANASTA. | H182: 1080
D183: TAT BOGOTA MONTEVIDEO | E183: 6 | F183: 2112207 | G183: HUEVO XL X 15 PET CANASTA | H183: 2080
D184: TAT BOGOTA MONTEVIDEO | E184: 6 | F184: 112271 | G184: HUEVO XL X 15 PET CAJA X 300 - TAT | H184: 5100
D185: TAT BOGOTA MONTEVIDEO | E185: 5 | F185: 112268 | G185: HUEVO XL X 15 PET CAJA X 300 | H185: 21000
D186: TAT BOGOTA MONTEVIDEO | E186: 5 | F186: 112379 | G186: HUEVO L X 30 PET CAJA X 300 | H186: 54000
... D197: TAT BOGOTA MONTEVIDEO | E197: 3 | F197: 2110302 | G197: HUEVO L X 30 CARTON VERDE CANASTA | H197: 40320
D198: Total TAT BOGOTA MONTEVIDEO | H198: 636467
D199: TAT BOGOTA SIBERIA | E199: 6 | F199: 2110202 | G199: HUEVO XL X 30 CARTON VERDE CANASTA | H199: 54720
D200: TAT BOGOTA SIBERIA | E200: 6 | F200: 2152388 | G200: HUEVO L X 15 PAGUE 14 PET EN CANASTA. | H200: 1200
D201: TAT BOGOTA SIBERIA | E201: 6 | F201: 2112207 | G201: HUEVO XL X 15 PET CANASTA | H201: 360
D202: TAT BOGOTA SIBERIA | E202: 4 | F202: 2110402 | G202: HUEVO M X 30 CARTON VERDE CANASTA | H202: 2370
D203: TAT BOGOTA SIBERIA | E203: 4 | F203: 2110317 | G203: HUEVO L X 30 CARTON VERDE AMARRADO SIN ETIQUETA | H203: 180
D204: TAT BOGOTA SIBERIA | E204: 4 | F204: 2110217 | G204: HUEVO XL X 30 CARTON VERDE AMARRADO SIN ETIQUETA CANASTA | H204: 20267
D205: TAT BOGOTA SIBERIA | E205: 3 | F205: 152384 | G205: HUEVO L X 15 PAGUE 14 PET CAJA X 300. | H205: 5700
D206: TAT BOGOTA SIBERIA | E206: 3 | F206: 2110302 | G206: HUEVO L X 30 CARTON VERDE CANASTA | H206: 36475
D207: TAT BOGOTA SIBERIA | E207: 3 | F207: 2010102 | G207: HUEVO YUMBO X20 CARTON VERDE CANASTA | H207: 820
D208: TAT BOGOTA SIBERIA | E208: 3 | F208: 112271 | G208: HUEVO XL X 15 PET CAJA X 300 - TAT | H208: 5700
D209: Total TAT BOGOTA SIBERIA | H209: 127792
D210: TAT BUCARAMANGA | E210: 7 | F210: 2114268 | G210: HUEVO XL X 15 PET CANASTA X 180 PV | H210: 1770
D211: TAT BUCARAMANGA | E211: 7 | F211: 2114357 | G211: HUEVO L X 12 PET CANASTA X 144 PV | H211: 144
D212: TAT BUCARAMANGA | E212: 7 | F212: 2114379 | G212: HUEVO L X 30 PET CANASTA X 180 PV | H212: 2430
...

Sheet GESTION EDADES
C3: GESTION DE DESECHO / ZF | L3: EDADES ALTAS EN PLANTAS Y CENTRO EMPAQUES | T3: EDADES ALTAS EN CEDIS
C4: CEDI | D4: (Varios elementos)
C5: Gestion desecho/zf | D5: Aplica | L5: Edad Alta | M5: No aplica | T5: Cedis | U5: No aplica
C7: DESTINO | D7: Edad | E7: Item | F7: Referencia | G7: CANTIDAD. | L7: DESTINO | M7: Edad | N7: Item | O7: Referencia | P7: Suma de CANTIDAD | T7: DESTINO | U7: Edad | V7: Item | W7: Referencia | X7: Suma de CANTIDAD
C8: ALKA1 | D8: 8 | E8: 75201 | F8: HUEVO AAA X 30 CARTON GRIS LZ | G8: 4224 | L8: ALKA1 | M8: 8 | N8: 75201 | O8: HUEVO AAA X 30 CARTON GRIS LZ | P8: 4224 | T8: ALKA1 | U8: 1 | V8: 10601 | W8: HUEVO CX30 CARTON GRIS | X8: 4344
C9: ALKA1 | D9: 7 | E9: 75201 | F9: HUEVO AAA X 30 CARTON GRIS LZ | G9: 3206 | L9: ALKA1 | M9: 7 | N9: 75201 | O9: HUEVO AAA X 30 CARTON GRIS LZ | P9: 3206 | T9: ALKA1 | U9: 1 | V9: 72002 | W9: HUEVO SUCIO ZF | X9: 3210
C10: ALKA1 | D10: 6 | E10: 75201 | F10: HUEVO AAA X 30 CARTON GRIS LZ | G10: 5940 | L10: ALKA1 | M10: 6 | N10: 75201 | O10: HUEVO AAA X 30 CARTON GRIS LZ | P10: 5940 | T10: ALKA1 | U10: 1 | V10: 73001 | W10: HUEVO PICADO ROJO | X10: 20910
C11: Total ALKA1 | G11: 13370 | L11: ALKA1 | M11: 4 | N11: 75201 | O11: HUEVO AAA X 30 CARTON GRIS LZ | P11: 8038 | T11: ALKA1 | U11: 1 | V11: 75201 | W11: HUEVO AAA X 30 CARTON GRIS LZ | X11: 570
C12: ALKA2 | D12: 2 | E12: 72003 | F12: HUEVO SUCIO ZF MARCADO | G12: 3240 | L12: ALKA1 | M12: 4 | N12: 75301 | O12: HUEVO AA X 30 CARTON GRIS LZ | P12: 90 | T12: ALKA1 | U12: 1 | V12: 75301 | W12: HUEVO AA X 30 CARTON GRIS LZ | X12: 4080
C13: Total ALKA2 | G13: 3240 | L13: ALKA1 | M13: 4 | N13: 75401 | O13: HUEVO A X 30 CARTON GRIS LZ | P13: 76 | T13: ALKA1 | U13: 1 | V13: 75401 | W13: HUEVO A X 30 CARTON GRIS LZ | X13: 3360
C14: BELLAVISTA | D14: 4 | E14: 79111 | F14: HUEVO ROTO ZF- SANTANDER | G14: 5235 | L14: ALKA1 | M14: 4 | N14: 75501 | O14: HUEVO B X 30 CARTON GRIS LZ | P14: 172 | T14: ALKA1 | U14: 1 | V14: 75501 | W14: HUEVO B X 30 CARTON GRIS LZ | X14: 260
C15: BELLAVISTA | D15: 3 | E15: 79111 | F15: HUEVO ROTO ZF- SANTANDER | G15: 6057 | L15: ALKA1 | M15: 4 | N15: 79110 | O15: HUEVO ROTO - ZF | P15: 3300 | T15: ALKA1 | U15: 1 | V15: 79110 | W15: HUEVO ROTO - ZF | X15: 7800
C16: BELLAVISTA | D16: 2 | E16: 79111 | F16: HUEVO ROTO ZF- SANTANDER | G16: 5403 | L16: ALKA1 | M16: 4 | N16: 2110202 | O16: HUEVO XL X 30 CARTON VERDE CANASTA | P16: 31317 | T16: ALKA1 | U16: 1 | V16: 112268 | W16: HUEVO XL X 15 PET CAJA X 300 | X16: 39000
C17: BELLAVISTA | D17: 2 | E17: 271901 | F17: HUEVO MAL MARCADO CANASTA | G17: 170 | L17: ALKA1 | M17: 4 | N17: 2110402 | O17: HUEVO M X 30 CARTON VERDE CANASTA | P17: 120 | T17: ALKA1 | U17: 1 | V17: 2010102 | W17: HUEVO YUMBO X20 CARTON VERDE CANASTA | X17: 2471
C18: BELLAVISTA | D18: 2 | E18: 273003 | F18: HUEVO PICADO ZF MARCADO X 30 BANDEJAS GRIS CANASTA | G18: 1615 | L18: ALKA1 | M18: 3 | N18: 10601 | O18: HUEVO CX30 CARTON GRIS | P18: 98 | T18: ALKA1 | U18: 1 | V18: 2010301 | W18: HUEVO AA X30 CARTON GRIS CANASTA | X18: 182400
C19: BELLAVISTA | D19: 1 | E19: 72003 | F19: HUEVO SUCIO ZF MARCADO | G19: 238 | L19: ALKA1 | M19: 3 | N19: 73001 | O19: HUEVO PICADO ROJO | P19: 18109 | T19: ALKA1 | U19: 1 | V19: 2010501 | W19: HUEVO B X30 CARTON GRIS CANASTA | X19: 1989
C20: BELLAVISTA | D20: 1 | E20: 79111 | F20: HUEVO ROTO ZF- SANTANDER | G20: 7200 | L20: ALKA1 | M20: 3 | N20: 79110 | O20: HUEVO ROTO - ZF | P20: 10500 | T20: ALKA1 | U20: 1 | V20: 2110202 | W20: HUEVO XL X 30 CARTON VERDE CANASTA | X20: 25740
C21: BELLAVISTA | D21: 1 | E21: 271901 | F21: HUEVO MAL MARCADO CANASTA | G21: 175 | L21: ALKA1 | M21: 3 | N21: 2010102 | O21: HUEVO YUMBO X20 CARTON VERDE CANASTA | P21: 40 | T21: ALKA1 | U21: 1 | V21: 2110302 | W21: HUEVO L X 30 CARTON VERDE CANASTA | X21: 23256
C22: BELLAVISTA | D22: 1 | E22: 273003 | F22: HUEVO PICADO ZF MARCADO X 30 BANDEJAS GRIS CANASTA | G22: 685 | L22: ALKA1 | M22: 3 | N22: 2110202 | O22: HUEVO XL X 30 CARTON VERDE CANASTA | P22: 17160 | T22: ALKA1 | U22: 1 | V22: 2410401 | W22: HUEVO CE X 30 CARTON GRIS CANASTA | X22: 302316
C23: Total BELLAVISTA | G23: 26778 | L23: ALKA1 | M23: 2 | N23: 10601 | O23: HUEVO CX30 CARTON GRIS | P23: 4770 | T23: ALKA1 | U23: 2 | V23: 10601 | W23: HUEVO CX30 CARTON GRIS | X23: 4770
C24: LANZA | D24: 4 | E24: 79111 | F24: HUEVO ROTO ZF- SANTANDER | G24: 2400 | L24: ALKA1 | M24: 2 | N24: 73001 | O24: HUEVO PICADO ROJO | P24: 23404 | T24: ALKA1 | U24: 2 | V24: 73001 | W24: HUEVO PICADO ROJO | X24: 23404
C25: LANZA | D25: 3 | E25: 79111 | F25: HUEVO ROTO ZF- SANTANDER | G25: 3300 | L25: ALKA1 | M25: 2 | N25: 75201 | O25: HUEVO AAA X 30 CARTON GRIS LZ | P25: 1667 | T25: ALKA1 | U25: 2 | V25: 75201 | W25: HUEVO AAA X 30 CARTON GRIS LZ | X25: 1667
C26: LANZA | D26: 2 | E26: 79111 | F26: HUEVO ROTO ZF- SANTANDER | G26: 2400 | L26: ALKA1 | M26: 2 | N26: 75301 | O26: HUEVO AA X 30 CARTON GRIS LZ | P26: 11280 | T26: ALKA1 | U26: 2 | V26: 75301 | W26: HUEVO AA X 30 CARTON GRIS LZ | X26: 11280
C27: LANZA | D27: 2 | E27: 272003 | F27: HUEVO SUCIO ZF MARCADO X 30 BANDEJA GRIS CANASTA | G27: 6690 | L27: ALKA1 | M27: 2 | N27: 75401 | O27: HUEVO A X 30 CARTON GRIS LZ | P27: 6287 | T27: ALKA1 | U27: 2 | V27: 75401 | W27: HUEVO A X 30 CARTON GRIS LZ | X27: 6287
C28: LANZA | D28: 2 | E28: 273003 | F28: HUEVO PICADO ZF MARCADO X 30 BANDEJAS GRIS CANASTA | G28: 3630 | L28: ALKA1 | M28: 2 | N28: 75501 | O28: HUEVO B X 30 CARTON GRIS LZ | P28: 60 | T28: ALKA1 | U28: 2 | V28: 75501 | W28: HUEVO B X 30 CARTON GRIS LZ | X28: 60
C29: Total LANZA | G29: 18420 | L29: ALKA1 | M29: 2 | N29: 79110 | O29: HUEVO ROTO - ZF | P29: 10200 | T29: ALKA1 | U29: 2 | V29: 79110 | W29: HUEVO ROTO - ZF | X29: 10200
C30: PALMAS | D30: 3 | E30: 72003 | F30: HUEVO SUCIO ZF MARCADO | G30: 24211 | L30: ALKA1 | M30: 2 | N30: 2010102 | O30: HUEVO YUMBO X20 CARTON VERDE CANASTA | P30: 2748 | T30: ALKA1 | U30: 2 | V30: 2010102 | W30: HUEVO YUMBO X20 CARTON VERDE CANASTA | X30: 2748
C31: PALMAS | D31: 2 | E31: 72003 | F31: HUEVO SUCIO ZF MARCADO | G31: 16570 | L31: ALKA1 | M31: 2 | N31: 2010301 | O31: HUEVO AA X30 CARTON GRIS CANASTA | P31: 42393 | T31: ALKA1 | U31: 2 | V31: 2010301 | W31: HUEVO AA X30 CARTON GRIS CANASTA | X31: 42393
C32: PALMAS | D32: 1 | E32: 72003 | F32: HUEVO SUCIO ZF MARCADO | G32: 15126 | L32: ALKA1 | M32: 2 | N32: 2110202 | O32: HUEVO XL X 30 CARTON VERDE CANASTA | P32: 25819 | T32: ALKA1 | U32: 2 | V32: 2110202 | W32: HUEVO XL X 30 CARTON VERDE CANASTA | X32: 25819
C33: Total PALMAS | G33: 55907 | L33: ALKA1 | M33: 1 | N33: 10601 | O33: HUEVO CX30 CARTON GRIS | P33: 4344 | T33: ALKA1 | U33: 3 | V33: 10601 | W33: HUEVO CX30 CARTON GRIS | X33: 98
C34: TAT CE BARRANQUILLA | D34: 7 | E34: 72001 | F34: HUEVO SUCIO DE JAULA | G34: 939 | L34: ALKA1 | M34: 1 | N34: 72002 | O34: HUEVO SUCIO ZF | P34: 3210 | T34: ALKA1 | U34: 3 | V34: 73001 | W34: HUEVO PICADO ROJO | X34: 18109
C35: Total TAT CE BARRANQUILLA | G35: 939 | L35: ALKA1 | M35: 1 | N35: 73001 | O35: HUEVO PICADO ROJO | P35: 20910 | T35: ALKA1 | U35: 3 | V35: 79110 | W35: HUEVO ROTO - ZF | X35: 10500
C36: Total general | G36: 118654 | L36: ALKA1 | M36: 1 | N36: 75201 | O36: HUEVO AAA X 30 CARTON GRIS LZ | P36: 570 | T36: ALKA1 | U36: 3 | V36: 2010102 | W36: HUEVO YUMBO X20 CARTON VERDE CANASTA | X36: 40
L37: ALKA1 | M37: 1 | N37: 75301 | O37: HUEVO AA X 30 CARTON GRIS LZ | P37: 4080 | T37: ALKA1 | U37: 3 | V37: 2110202 | W37: HUEVO XL X 30 CARTON VERDE CANASTA | X37: 17160
L38: ALKA1 | M38: 1 | N38: 75401 | O38: HUEVO A X 30 CARTON GRIS LZ | P38: 3360 | T38: ALKA1 | U38: 4 | V38: 75201 | W38: HUEVO AAA X 30 CARTON GRIS LZ | X38: 8038
L39: ALKA1 | M39: 1 | N39: 75501 | O39: HUEVO B X 30 CARTON GRIS LZ | P39: 260 | T39: ALKA1 | U39: 4 | V39: 75301 | W39: HUEVO AA X 30 CARTON GRIS LZ | X39: 90
L40: ALKA1 | M40: 1 | N40: 79110 | O40: HUEVO ROTO - ZF | P40: 7800 | T40: ALKA1 | U40: 4 | V40: 75401 | W40: HUEVO A X 30 CARTON GRIS LZ | X40: 76
L41: ALKA1 | M41: 1 | N41: 112268 | O41: HUEVO XL X 15 PET CAJA X 300 | P41: 39000 | T41: ALKA1 | U41: 4 | V41: 75501 | W41: HUEVO B X 30 CARTON GRIS LZ | X41: 172
L42: ALKA1 | M42: 1 | N42: 2010102 | O42: HUEVO YUMBO X20 CARTON VERDE CANASTA | P42: 2471 | T42: ALKA1 | U42: 4 | V42: 79110 | W42: HUEVO ROTO - ZF | X42: 3300
L43: ALKA1 | M43: 1 | N43: 2010301 | O43: HUEVO AA X30 CARTON GRIS CANASTA | P43: 182400 | T43: ALKA1 | U43: 4 | V43: 2110202 | W43: HUEVO XL X 30 CARTON VERDE CANASTA | X43: 31317
L44: ALKA1 | M44: 1 | N44: 2010501 | O44: HUEVO B X30 CARTON GRIS CANASTA | P44: 1989 | T44: ALKA1 | U44: 4 | V44: 2110402 | W44: HUEVO M X 30 CARTON VERDE CANASTA | X44: 120
L45: ALKA1 | M45: 1 | N45: 2110202 | O45: HUEVO XL X 30 CARTON VERDE CANASTA | P45: 25740 | T45: ALKA1 | U45: 6 | V45: 75201 | W45: HUEVO AAA X 30 CARTON GRIS LZ | X45: 5940
L46: ALKA1 | M46: 1 | N46: 2110302 | O46: HUEVO L X 30 CARTON VERDE CANASTA | P46: 23256 | T46: ALKA1 | U46: 7 | V46: 75201 | W46: HUEVO AAA X 30 CARTON GRIS LZ | X46: 3206
L47: ALKA1 | M47: 1 | N47: 2410401 | O47: HUEVO CE X 30 CARTON GRIS CANASTA | P47: 302316 | T47: ALKA1 | U47: 8 | V47: 75201 | W47: HUEVO AAA X 30 CARTON GRIS LZ | X47: 4224
L48: Total ALKA1 | P48: 852724 | T48: Total ALKA1 | X48: 852724
L49: ALKA2 | M49: 5 | N49: 2010102 | O49: HUEVO YUMBO X20 CARTON VERDE CANASTA | P49: 960 | T49: ALKA2 | U49: 1 | V49: 10601 | W49: HUEVO CX30 CARTON GRIS | X49: 4379
L50: ALKA2 | M50: 5 | N50: 2110202 | O50: HUEVO XL X 30 CARTON VERDE CANASTA | P50: 22509 | T50: ALKA2 | U50: 1 | V50: 72001 | W50: HUEVO SUCIO DE JAULA | X50: 9144
L51: ALKA2 | M51: 4 | N51: 2010102 | O51: HUEVO YUMBO X20 CARTON VERDE CANASTA | P51: 1352 | T51: ALKA2 | U51: 1 | V51: 73001 | W51: HUEVO PICADO ROJO | X51: 13500
L52: ALKA2 | M52: 4 | N52: 2110202 | O52: HUEVO XL X 30 CARTON VERDE CANASTA | P52: 44455 | T52: ALKA2 | U52: 1 | V52: 79110 | W52: HUEVO ROTO - ZF | X52: 3600
L53: ALKA2 | M53: 3 | N53: 10601 | O53: HUEVO CX30 CARTON GRIS | P53: 1747 | T53: ALKA2 | U53: 1 | V53: 112268 | W53: HUEVO XL X 15 PET CAJA X 300 | X53: 45000
L54: ALKA2 | M54: 3 | N54: 73001 | O54: HUEVO PICADO ROJO | P54: 10577 | T54: ALKA2 | U54: 1 | V54: 2010102 | W54: HUEVO YUMBO X20 CARTON VERDE CANASTA | X54: 1352
L55: ALKA2 | M55: 3 | N55: 2010102 | O55: HUEVO YUMBO X20 CARTON VERDE CANASTA | P55: 1014 | T55: ALKA2 | U55: 1 | V55: 2010301 | W55: HUEVO AA X30 CARTON GRIS CANASTA | X55: 263538
L56: ALKA2 | M56: 3 | N56: 2110202 | O56: HUEVO XL X 30 CARTON VERDE CANASTA | P56: 29929 | T56: ALKA2 | U56: 1 | V56: 2010501 | W56: HUEVO B X30 CARTON GRIS CANASTA | X56: 362
L57: ALKA2 | M57: 3 | N57: 2110402 | O57: HUEVO M X 30 CARTON VERDE CANASTA | P57: 3257 | T57: ALKA2 | U57: 1 | V57: 2110202 | W57: HUEVO XL X 30 CARTON VERDE CANASTA | X57: 18526
L58: ALKA2 | M58: 2 | N58: 10601 | O58: HUEVO CX30 CARTON GRIS | P58: 3684 | T58: ALKA2 | U58: 1 | V58: 2110302 | W58: HUEVO L X 30 CARTON VERDE CANASTA | X58: 5976
L59: ALKA2 | M59: 2 | N59: 72003 | O59: HUEVO SUCIO ZF MARCADO | P59: 3240 | T59: ALKA2 | U59: 1 | V59: 2410401 | W59: HUEVO CE X 30 CARTON GRIS CANASTA | X59: 180747
L60: ALKA2 | M60: 2 | N60: 73001 | O60: HUEVO PICADO ROJO | P60: 15492 | T60: ALKA2 | U60: 2 | V60: 10601 | W60: HUEVO CX30 CARTON GRIS | X60: 3684
... L73: ALKA2 | M73: 1 | N73: 2410401 | O73: HUEVO CE X 30 CARTON GRIS CANASTA | P73: 180747 | T73: ALKA2 | U73: 5 | V73: 2110202 | W73: HUEVO XL X 30 CARTON VERDE CANASTA | X73: 22509
L74: Total ALKA2 | P74: 723153 | T74: ALKA2 | U74: 6 | V74: 2110202 | W74: HUEVO XL X 30 CARTON VERDE CANASTA | X74: 25200
L75: BELLAVISTA | M75: 6 | N75: 79101 | O75: HUEVO ROTO | P75: 1046 | T75: Total ALKA2 | X75: 748353
L76: BELLAVISTA | M76: 5 | N76: 10601 | O76: HUEVO CX30 CARTON GRIS | P76: 18532 | T76: BELLAVISTA | U76: 1 | V76: 10601 | W76: HUEVO CX30 CARTON GRIS | X76: 25544
L77: BELLAVISTA | M77: 5 | N77: 79101 | O77: HUEVO ROTO | P77: 800 | T77: BELLAVISTA | U77: 1 | V77: 72001 | W77: HUEVO SUCIO DE JAULA | X77: 1714
L78: BELLAVISTA | M78: 4 | N78: 10501 | O78: HUEVO B X30 CARTON GRIS | P78: 19844 | T78: BELLAVISTA | U78: 1 | V78: 72003 | W78: HUEVO SUCIO ZF MARCADO | X78: 238
L79: BELLAVISTA | M79: 4 | N79: 10601 | O79: HUEVO CX30 CARTON GRIS | P79: 27498 | T79: BELLAVISTA | U79: 1 | V79: 79101 | W79: HUEVO ROTO | X79: 2968
L80: BELLAVISTA | M80: 4 | N80: 79101 | O80: HUEVO ROTO | P80: 1253 | T80: BELLAVISTA | U80: 1 | V80: 79111 | W80: HUEVO ROTO ZF- SANTANDER | X80: 7200
L81: BELLAVISTA | M81: 4 | N81: 79111 | O81: HUEVO ROTO ZF- SANTANDER | P81: 5235 | T81: BELLAVISTA | U81: 1 | V81: 271901 | W81: HUEVO MAL MARCADO CANASTA | X81: 175
L82: BELLAVISTA | M82: 4 | N82: 2010501 | O82: HUEVO B X30 CARTON GRIS CANASTA | P82: 3918 | T82: BELLAVISTA | U82: 1 | V82: 273003 | W82: HUEVO PICADO ZF MARCADO X 30 BANDEJAS GRIS CANASTA | X82: 685
L83: BELLAVISTA | M83: 3 | N83: 10501 | O83: HUEVO B X30 CARTON GRIS | P83: 18444 | T83: BELLAVISTA | U83: 1 | V83: 2010102 | W83: HUEVO YUMBO X20 CARTON VERDE CANASTA | X83: 2819
L84: BELLAVISTA | M84: 3 | N84: 10601 | O84: HUEVO CX30 CARTON GRIS | P84: 28691 | T84: BELLAVISTA | U84: 1 | V84: 2010501 | W84: HUEVO B X30 CARTON GRIS CANASTA | X84: 41376
L85: BELLAVISTA | M85: 3 | N85: 79101 | O85: HUEVO ROTO | P85: 1467 | T85: BELLAVISTA | U85: 1 | V85: 2110202 | W85: HUEVO XL X 30 CARTON VERDE CANASTA | X85: 3671
L86: BELLAVISTA | M86: 3 | N86: 79111 | O86: HUEVO ROTO ZF- SANTANDER | P86: 6057 | T86: BELLAVISTA | U86: 1 | V86: 2110302 | W86: HUEVO L X 30 CARTON VERDE CANASTA | X86: 66302
L87: BELLAVISTA | M87: 2 | N87: 10601 | O87: HUEVO CX30 CARTON GRIS | P87: 24677 | T87: BELLAVISTA | U87: 1 | V87: 2110402 | W87: HUEVO M X 30 CARTON VERDE CANASTA | X87: 21279
... L108: BELLAVISTA | M108: 1 | N108: 273001 | O108: HUEVO PICADO X 30 BANDEJA GRIS CANASTA | P108: 15270 | T108: BELLAVISTA | U108: 5 | V108: 79101 | W108: HUEVO ROTO | X108: 800
L109: Total BELLAVISTA | P109: 431077 | T109: BELLAVISTA | U109: 6 | V109: 79101 | W109: HUEVO ROTO | X109: 1046
L110: LANZA | M110: 4 | N110: 79111 | O110: HUEVO ROTO ZF- SANTANDER | P110: 2400 | T110: Total BELLAVISTA | X110: 431077
L111: LANZA | M111: 4 | N111: 110303 | O111: HUEVO L X30 CARTON VERDE AMARRADO | P111: 8100 | T111: LANZA | U111: 2 | V111: 10601 | W111: HUEVO CX30 CARTON GRIS | X111: 25680
L112: LANZA | M112: 4 | N112: 13459 | O112: HUEVO A X 300 BANDEJA GRIS ALAT CAJA AMARRADO | P112: 15600 | T112: LANZA | U112: 2 | V112: 13324 | W112: HUEVO AA X 30 BAND GRIS AMARRADO TAPA VERDE ALAT - ESTIBADO | X112: 86700
L113: LANZA | M113: 3 | N113: 75201 | O113: HUEVO AAA X 30 CARTON GRIS LZ | P113: 4530 | T113: LANZA | U113: 2 | V113: 13420 | W113: HUEVO A X 30 BAND GRIS AMARRADO SOL NACIENTE SANTANDER. | X113: 86700
L114: LANZA | M114: 3 | N114: 75301 | O114: HUEVO AA X 30 CARTON GRIS LZ | P114: 30030 | T114: LANZA | U114: 2 | V114: 79111 | W114: HUEVO ROTO ZF- SANTANDER | X114: 2400
L115: LANZA | M115: 3 | N115: 75401 | O115: HUEVO A X 30 CARTON GRIS LZ | P115: 16080 | T115: LANZA | U115: 2 | V115: 114268 | W115: HUEVO XL X 15 PET CAJA X 300 PV. | X115: 600
L116: LANZA | M116: 3 | N116: 75501 | O116: HUEVO B X 30 CARTON GRIS LZ | P116: 2580 | T116: LANZA | U116: 2 | V116: 152384 | W116: HUEVO L X 15 PAGUE 14 PET CAJA X 300. | X116: 3300
L117: LANZA | M117: 3 | N117: 79111 | O117: HUEVO ROTO ZF- SANTANDER | P117: 3300 | T117: LANZA | U117: 2 | V117: 272002 | W117: HUEVO SUCIO ZF SIN MARCA X 30 BANDEJA GRIS CANASTA | X117: 4074
L118: LANZA | M118: 3 | N118: 114379 | O118: HUEVO L X 30 PET CAJA X 300 PV. | P118: 1800 | T118: LANZA | U118: 2 | V118: 272003 | W118: HUEVO SUCIO ZF MARCADO X 30 BANDEJA GRIS CANASTA | X118: 6690
L119: LANZA | M119: 3 | N119: 152384 | O119: HUEVO L X 15 PAGUE 14 PET CAJA X 300. | P119: 5100 | T119: LANZA | U119: 2 | V119: 273003 | W119: HUEVO PICADO ZF MARCADO X 30 BANDEJAS GRIS CANASTA | X119: 3630
L120: LANZA | M120: 3 | N120: 272002 | O120: HUEVO SUCIO ZF SIN MARCA X 30 BANDEJA GRIS CANASTA | P120: 1392 | T120: LANZA | U120: 2 | V120: 2010102 | W120: HUEVO YUMBO X20 CARTON VERDE CANASTA | X120: 4360
L121: LANZA | M121: 3 | N121: 2010102 | O121: HUEVO YUMBO X20 CARTON VERDE CANASTA | P121: 4814 | T121: LANZA | U121: 2 | V121: 2010501 | W121: HUEVO B X30 CARTON GRIS CANASTA | X121: 169712
L122: LANZA | M122: 3 | N122: 2114357 | O122: HUEVO L X 12 PET CANASTA X 144 PV | P122: 576 | T122: LANZA | U122: 2 | V122: 2110202 | W122: HUEVO XL X 30 CARTON VERDE CANASTA | X122: 16530
... L142: LANZA | M142: 2 | N142: 272008 | O142: HUEVO SUCIO BASE LAVADO ZF X 30 BANDEJA GRIS CANASTA | P142: 45740 | T142: LANZA | U142: 4 | V142: 110303 | W142: HUEVO L X30 CARTON VERDE AMARRADO | X142: 8100
L143: Total LANZA | P143: 1096954 | T143: LANZA | U143: 4 | V143: 13459 | W143: HUEVO A X 300 BANDEJA GRIS ALAT CAJA AMARRADO | X143: 15600
L144: PALMAS | M144: 5 | N144: 75201 | O144: HUEVO AAA X 30 CARTON GRIS LZ | P144: 12788 | T144: Total LANZA | X144: 1096954
L145: PALMAS | M145: 4 | N145: 75201 | O145: HUEVO AAA X 30 CARTON GRIS LZ | P145: 17070 | T145: PALMAS | U145: 1 | V145: 10601 | W145: HUEVO CX30 CARTON GRIS | X145: 10632
L146: PALMAS | M146: 3 | N146: 10601 | O146: HUEVO CX30 CARTON GRIS | P146: 7950 | T146: PALMAS | U146: 1 | V146: 72003 | W146: HUEVO SUCIO ZF MARCADO | X146: 15126
L147: PALMAS | M147: 3 | N147: 72003 | O147: HUEVO SUCIO ZF MARCADO | P147: 24211 | T147: PALMAS | U147: 1 | V147: 73001 | W147: HUEVO PICADO ROJO | X147: 50417
L148: PALMAS | M148: 3 | N148: 73001 | O148: HUEVO PICADO ROJO | P148: 41675 | T148: PALMAS | U148: 1 | V148: 75501 | W148: HUEVO B X 30 CARTON GRIS LZ | X148: 1906
L149: PALMAS | M149: 3 | N149: 75201 | O149: HUEVO AAA X 30 CARTON GRIS LZ | P149: 12407 | T149: PALMAS | U149: 1 | V149: 79110 | W149: HUEVO ROTO - ZF | X149: 6000
L150: PALMAS | M150: 3 | N150: 75301 | O150: HUEVO AA X 30 CARTON GRIS LZ | P150: 13095 | T150: PALMAS | U150: 1 | V150: 2010102 | W150: HUEVO YUMBO X20 CARTON VERDE CANASTA | X150: 11316
L151: PALMAS | M151: 3 | N151: 75401 | O151: HUEVO A X 30 CARTON GRIS LZ | P151: 4486 | T151: PALMAS | U151: 1 | V151: 2010301 | W151: HUEVO AA X30 CARTON GRIS CANASTA | X151: 32793
L152: PALMAS | M152: 3 | N152: 75501 | O152: HUEVO B X 30 CARTON GRIS LZ | P152: 2388 | T152: PALMAS | U152: 1 | V152: 2110202 | W152: HUEVO XL X 30 CARTON VERDE CANASTA | X152: 154406
L153: PALMAS | M153: 3 | N153: 2110202 | O153: HUEVO XL X 30 CARTON VERDE CANASTA | P153: 19440 | T153: PALMAS | U153: 1 | V153: 2110302 | W153: HUEVO L X 30 CARTON VERDE CANASTA | X153: 115867
L154: PALMAS | M154: 2 | N154: 10601 | O154: HUEVO CX30 CARTON GRIS | P154: 11250 | T154: PALMAS | U154: 1 | V154: 2410401 | W154: HUEVO CE X 30 CARTON GRIS CANASTA | X154: 168876
...

Sheet VENTA T
B2: 2010102
B3: YUMBO | G3: Días | H3: Días | I3: Días | J3: Días | K3: UND
B4: DESTINO | C4: VEHICULOS | D4: BODEGA | E4: TRANSITO | F4: PROM VENTA | G4: VEHICULOS | H4: BODEGA | I4: TRANSITO | J4: TOTAL | K4: CARGADAS
B5: TAT BOGOTA MONTEVIDEO | C5: =SUMIFS(inv!$D:$D,inv!$T:$T,'VENTA T'!$B5,inv!$U:$U,'VENTA T'!$C$4,inv!$A:$A,'VENTA T'!$B$2) -> 10590 | D5: =SUMIFS(inv!$D:$D,inv!$T:$T,'VENTA T'!$B5,inv!$U:$U,'VENTA T'!$D$4,inv!$A:$A,'VENTA T'!$B$2) -> 9676 | E5: =SUMIFS(inv!$D:$D,inv!$T:$T,'VENTA T'!$B5,inv!$U:$U,'VENTA T'!$E$4,inv!$A:$A,'VENTA T'!$B$2) -> 0 | F5: =SUMIFS(VENTAS!$H:$H,VENTAS!$G:$G,'VENTA T'!$B5,VENTAS!$B:$B,'VENTA T'!$B$2) -> 5122 | G5: =C5/$F5 -> 2.0675517 | H5: =D5/$F5 -> 1.8891058 | I5: =E5/$F5 -> 0 | J5: =H5+I5 -> 1.8891058 | K5: =IFERROR(C5-F5,0) -> 5468
B6: TAT BOGOTA SIBERIA | C6: =SUMIFS(inv!$D:$D,inv!$T:$T,'VENTA T'!$B6,inv!$U:$U,'VENTA T'!$C$4,inv!$A:$A,'VENTA T'!$B$2) -> 5544 | D6: =SUMIFS(inv!$D:$D,inv!$T:$T,'VENTA T'!$B6,inv!$U:$U,'VENTA T'!$D$4,inv!$A:$A,'VENTA T'!$B$2) -> 820 | E6: =SUMIFS(inv!$D:$D,inv!$T:$T,'VENTA T'!$B6,inv!$U:$U,'VENTA T'!$E$4,inv!$A:$A,'VENTA T'!$B$2) -> 0 | F6: =SUMIFS(VENTAS!$H:$H,VENTAS!$G:$G,'VENTA T'!$B6,VENTAS!$B:$B,'VENTA T'!$B$2) -> 2202 | G6: =C6/$F6 -> 2.5177112 | H6: =D6/$F6 -> 0.37238874 | I6: =E6/$F6 -> 0 | J6: =H6+I6 -> 0.37238874 | K6: =IFERROR(C6-F6,0) -> 3342
B7: TAT CALI | C7: =SUMIFS(inv!$D:$D,inv!$T:$T,'VENTA T'!$B7,inv!$U:$U,'VENTA T'!$C$4,inv!$A:$A,'VENTA T'!$B$2) -> 5508 | D7: =SUMIFS(inv!$D:$D,inv!$T:$T,'VENTA T'!$B7,inv!$U:$U,'VENTA T'!$D$4,inv!$A:$A,'VENTA T'!$B$2) -> 20148 | E7: =SUMIFS(inv!$D:$D,inv!$T:$T,'VENTA T'!$B7,inv!$U:$U,'VENTA T'!$E$4,inv!$A:$A,'VENTA T'!$B$2) -> 0 | F7: =SUMIFS(VENTAS!$H:$H,VENTAS!$G:$G,'VENTA T'!$B7,VENTAS!$B:$B,'VENTA T'!$B$2) -> 6428.5 | G7: =C7/$F7 -> 0.85680952 | H7: =D7/$F7 -> 3.1341682 | I7: =E7/$F7 -> 0 | J7: =H7+I7 -> 3.1341682 | K7: =IFERROR(C7-F7,0) -> -920.5
B8: TAT MEDELLIN | C8: =SUMIFS(inv!$D:$D,inv!$T:$T,'VENTA T'!$B8,inv!$U:$U,'VENTA T'!$C$4,inv!$A:$A,'VENTA T'!$B$2) -> 1461 | D8: =SUMIFS(inv!$D:$D,inv!$T:$T,'VENTA T'!$B8,inv!$U:$U,'VENTA T'!$D$4,inv!$A:$A,'VENTA T'!$B$2) -> 1005 | E8: =SUMIFS(inv!$D:$D,inv!$T:$T,'VENTA T'!$B8,inv!$U:$U,'VENTA T'!$E$4,inv!$A:$A,'VENTA T'!$B$2) -> 9600 | F8: =SUMIFS(VENTAS!$H:$H,VENTAS!$G:$G,'VENTA T'!$B8,VENTAS!$B:$B,'VENTA T'!$B$2) -> 2757 | G8: =C8/$F8 -> 0.52992383 | H8: =D8/$F8 -> 0.36452666 | I8: =E8/$F8 -> 3.4820457 | J8: =H8+I8 -> 3.8465724 | K8: =IFERROR(C8-F8,0) -> -1296
B9: TAT PASTO | C9: =SUMIFS(inv!$D:$D,inv!$T:$T,'VENTA T'!$B9,inv!$U:$U,'VENTA T'!$C$4,inv!$A:$A,'VENTA T'!$B$2) -> 1172 | D9: =SUMIFS(inv!$D:$D,inv!$T:$T,'VENTA T'!$B9,inv!$U:$U,'VENTA T'!$D$4,inv!$A:$A,'VENTA T'!$B$2) -> 2483 | E9: =SUMIFS(inv!$D:$D,inv!$T:$T,'VENTA T'!$B9,inv!$U:$U,'VENTA T'!$E$4,inv!$A:$A,'VENTA T'!$B$2) -> 0 | F9: =SUMIFS(VENTAS!$H:$H,VENTAS!$G:$G,'VENTA T'!$B9,VENTAS!$B:$B,'VENTA T'!$B$2) -> 830 | G9: =C9/$F9 -> 1.4120482 | H9: =D9/$F9 -> 2.9915663 | I9: =E9/$F9 -> 0 | J9: =H9+I9 -> 2.9915663 | K9: =IFERROR(C9-F9,0) -> 342
B10: TAT POPAYAN | C10: =SUMIFS(inv!$D:$D,inv!$T:$T,'VENTA T'!$B10,inv!$U:$U,'VENTA T'!$C$4,inv!$A:$A,'VENTA T'!$B$2) -> 2372 | D10: =SUMIFS(inv!$D:$D,inv!$T:$T,'VENTA T'!$B10,inv!$U:$U,'VENTA T'!$D$4,inv!$A:$A,'VENTA T'!$B$2) -> 3383 | E10: =SUMIFS(inv!$D:$D,inv!$T:$T,'VENTA T'!$B10,inv!$U:$U,'VENTA T'!$E$4,inv!$A:$A,'VENTA T'!$B$2) -> 0 | F10: =SUMIFS(VENTAS!$H:$H,VENTAS!$G:$G,'VENTA T'!$B10,VENTAS!$B:$B,'VENTA T'!$B$2) -> 690 | G10: =C10/$F10 -> 3.4376812 | H10: =D10/$F10 -> 4.9028986 | I10: =E10/$F10 -> 0 | J10: =H10+I10 -> 4.9028986
C11: =SUM(C5:C10) -> 26647 | D11: =SUM(D5:D10) -> 37515 | E11: =SUM(E5:E10) -> 9600 | F11: =SUM(F5:F10) -> 18029.5
B13: 2110202 | F13: 110202
B14: XL | G14: Días | H14: Días | I14: Días | J14: Días | K14: UND
B15: DESTINO | C15: VEHICULOS | D15: BODEGA | E15: TRANSITO | F15: PROM VENTA | G15: VEHICULOS | H15: BODEGA | I15: TRANSITO | J15: TOTAL | K15: CARGADAS
B16: TAT BOGOTA MONTEVIDEO | C16: =SUMIFS(inv!$D:$D,inv!$T:$T,'VENTA T'!$B16,inv!$U:$U,'VENTA T'!$C$15,inv!$A:$A,'VENTA T'!$B$13) -> 175385 | D16: =SUMIFS(inv!$D:$D,inv!$T:$T,'VENTA T'!$B16,inv!$U:$U,'VENTA T'!$D$15,inv!$A:$A,'VENTA T'!$B$13) -> 196896 | E16: =SUMIFS(inv!$D:$D,inv!$T:$T,'VENTA T'!$B16,inv!$U:$U,'VENTA T'!$E$15,inv!$A:$A,'VENTA T'!$B$13) -> 126720 | F16: =SUMIFS(VENTAS!$H:$H,VENTAS!$G:$G,'VENTA T'!$B16,VENTAS!$B:$B,'VENTA T'!$B$13) -> 85424 | G16: =C16/$F16 -> 2.0531115 | H16: =D16/$F16 -> 2.304926 | I16: =E16/$F16 -> 1.4834239 | J16: =H16+I16 -> 3.7883499 | K16: =IFERROR(C16-F16,0) -> 89961
B17: TAT MEDELLIN | C17: =SUMIFS(inv!$D:$D,inv!$T:$T,'VENTA T'!$B17,inv!$U:$U,'VENTA T'!$C$15,inv!$A:$A,'VENTA T'!$B$13) -> 176469 | D17: =SUMIFS(inv!$D:$D,inv!$T:$T,'VENTA T'!$B17,inv!$U:$U,'VENTA T'!$D$15,inv!$A:$A,'VENTA T'!$B$13) -> 283896 | E17: =SUMIFS(inv!$D:$D,inv!$T:$T,'VENTA T'!$B17,inv!$U:$U,'VENTA T'!$E$15,inv!$A:$A,'VENTA T'!$B$13) -> 160560 | F17: =SUMIFS(VENTAS!$H:$H,VENTAS!$G:$G,'VENTA T'!$B17,VENTAS!$B:$B,'VENTA T'!$B$13) -> 139221 | G17: =C17/$F17 -> 1.2675458 | H17: =D17/$F17 -> 2.0391751 | I17: =E17/$F17 -> 1.1532743 | J17: =H17+I17 -> 3.1924494 | K17: =IFERROR(C17-F17,0) -> 37248
B18: TAT CALI | C18: =SUMIFS(inv!$D:$D,inv!$T:$T,'VENTA T'!$B18,inv!$U:$U,'VENTA T'!$C$15,inv!$A:$A,'VENTA T'!$B$13) -> 92535 | D18: =SUMIFS(inv!$D:$D,inv!$T:$T,'VENTA T'!$B18,inv!$U:$U,'VENTA T'!$D$15,inv!$A:$A,'VENTA T'!$B$13) -> 167060 | E18: =SUMIFS(inv!$D:$D,inv!$T:$T,'VENTA T'!$B18,inv!$U:$U,'VENTA T'!$E$15,inv!$A:$A,'VENTA T'!$B$13) -> 0 | F18: =SUMIFS(VENTAS!$H:$H,VENTAS!$G:$G,'VENTA T'!$B18,VENTAS!$B:$B,'VENTA T'!$F$13)+SUMIFS(VENTAS!$H:$H,VENTAS!$G:$G,'VENTA T'!$B18,VENTAS!$B:$B,'VENTA T'!$B$13) -> 78612.5 | G18: =C18/$F18 -> 1.1771029 | H18: =D18/$F18 -> 2.1251073 | I18: =E18/$F18 -> 0 | J18: =H18+I18 -> 2.1251073 | K18: =IFERROR(C18-F18,0) -> 13922.5
B19: TAT PASTO | C19: =SUMIFS(inv!$D:$D,inv!$T:$T,'VENTA T'!$B19,inv!$U:$U,'VENTA T'!$C$15,inv!$A:$A,'VENTA T'!$B$13) -> 26921 | D19: =SUMIFS(inv!$D:$D,inv!$T:$T,'VENTA T'!$B19,inv!$U:$U,'VENTA T'!$D$15,inv!$A:$A,'VENTA T'!$B$13) -> 90612 | E19: =SUMIFS(inv!$D:$D,inv!$T:$T,'VENTA T'!$B19,inv!$U:$U,'VENTA T'!$E$15,inv!$A:$A,'VENTA T'!$B$13) -> 0 | F19: =SUMIFS(VENTAS!$H:$H,VENTAS!$G:$G,'VENTA T'!$B19,VENTAS!$B:$B,'VENTA T'!$B$13) -> 31317.5 | G19: =C19/$F19 -> 0.85961523 | H19: =D19/$F19 -> 2.8933344 | I19: =E19/$F19 -> 0 | J19: =H19+I19 -> 2.8933344 | K19: =IFERROR(C19-F19,0) -> -4396.5
B20: TAT BOGOTA SIBERIA | C20: =SUMIFS(inv!$D:$D,inv!$T:$T,'VENTA T'!$B20,inv!$U:$U,'VENTA T'!$C$15,inv!$A:$A,'VENTA T'!$B$13) -> 57029 | D20: =SUMIFS(inv!$D:$D,inv!$T:$T,'VENTA T'!$B20,inv!$U:$U,'VENTA T'!$D$15,inv!$A:$A,'VENTA T'!$B$13) -> 54720 | E20: =SUMIFS(inv!$D:$D,inv!$T:$T,'VENTA T'!$B20,inv!$U:$U,'VENTA T'!$E$15,inv!$A:$A,'VENTA T'!$B$13) -> 0 | F20: =SUMIFS(VENTAS!$H:$H,VENTAS!$G:$G,'VENTA T'!$B20,VENTAS!$B:$B,'VENTA T'!$B$13) -> 22649 | G20: =C20/$F20 -> 2.5179478 | H20: =D20/$F20 -> 2.4160007 | I20: =E20/$F20 -> 0 | J20: =H20+I20 -> 2.4160007 | K20: =IFERROR(C20-F20,0) -> 34380
B21: TAT POPAYAN | C21: =SUMIFS(inv!$D:$D,inv!$T:$T,'VENTA T'!$B21,inv!$U:$U,'VENTA T'!$C$15,inv!$A:$A,'VENTA T'!$B$13) -> 9576 | D21: =SUMIFS(inv!$D:$D,inv!$T:$T,'VENTA T'!$B21,inv!$U:$U,'VENTA T'!$D$15,inv!$A:$A,'VENTA T'!$B$13) -> 27360 | E21: =SUMIFS(inv!$D:$D,inv!$T:$T,'VENTA T'!$B21,inv!$U:$U,'VENTA T'!$E$15,inv!$A:$A,'VENTA T'!$B$13) -> 0 | F21: =SUMIFS(VENTAS!$H:$H,VENTAS!$G:$G,'VENTA T'!$B21,VENTAS!$B:$B,'VENTA T'!$B$13) -> 4946.5 | G21: =C21/$F21 -> 1.9359143 | H21: =D21/$F21 -> 5.5311837 | I21: =E21/$F21 -> 0 | J21: =H21+I21 -> 5.5311837 | K21: =IFERROR(C21-F21,0) -> 4629.5
B22: TAT VILLAVICENCIO | C22: =SUMIFS(inv!$D:$D,inv!$T:$T,'VENTA T'!$B22,inv!$U:$U,'VENTA T'!$C$15,inv!$A:$A,'VENTA T'!$B$13) -> 0 | D22: =SUMIFS(inv!$D:$D,inv!$T:$T,'VENTA T'!$B22,inv!$U:$U,'VENTA T'!$D$15,inv!$A:$A,'VENTA T'!$B$13) -> 0 | E22: =SUMIFS(inv!$D:$D,inv!$T:$T,'VENTA T'!$B22,inv!$U:$U,'VENTA T'!$E$15,inv!$A:$A,'VENTA T'!$B$13) -> 0 | F22: =SUMIFS(VENTAS!$H:$H,VENTAS!$G:$G,'VENTA T'!$B22,VENTAS!$B:$B,'VENTA T'!$B$13) -> 0 | G22: =IFERROR((C22/$F22),0) -> 0 | H22: =IFERROR((D22/$F22),0) -> 0 | I22: =IFERROR((E22/$F22),0) -> 0 | J22: =H22+I22 -> 0 | K22: =IFERROR(C22-F22,0) -> 0
C23: =SUM(C16:C22) -> 537915 | D23: =SUM(D16:D22) -> 820544 | E23: =SUM(E16:E22) -> 287280 | F23: =SUM(F16:F21) -> 362170.5
B24: 2110327
B25: 2110302
B26: L | G26: Días | H26: Días | I26: Días | J26: Días | K26: UND
B27: DESTINO | C27: VEHICULOS | D27: BODEGA | E27: TRANSITO | F27: PROM VENTA | G27: VEHICULOS | H27: BODEGA | I27: TRANSITO | J27: TOTAL | K27: CARGADAS
B28: TAT PASTO | C28: =SUMIFS(inv!$D:$D,inv!$T:$T,'VENTA T'!$B28,inv!$U:$U,'VENTA T'!$C$27,inv!$A:$A,'VENTA T'!$B$25) -> 196026 | D28: =SUMIFS(inv!$D:$D,inv!$T:$T,'VENTA T'!$B28,inv!$U:$U,'VENTA T'!$D$27,inv!$A:$A,'VENTA T'!$B$25) -> 158495 | E28: =SUMIFS(inv!$D:$D,inv!$T:$T,'VENTA T'!$B28,inv!$U:$U,'VENTA T'!$E$27,inv!$A:$A,'VENTA T'!$B$25) -> 255360 | F28: =SUMIFS(VENTAS!$H:$H,VENTAS!$G:$G,'VENTA T'!$B28,VENTAS!$B:$B,'VENTA T'!$B$25) -> 151599.5 | G28: =C28/$F28 -> 1.2930518 | H28: =D28/$F28 -> 1.045485 | I28: =E28/$F28 -> 1.6844383 | J28: =H28+I28 -> 2.7299233 | K28: =IFERROR(C28-F28,0) -> 44426.5
B29: TAT POPAYAN | C29: =SUMIFS(inv!$D:$D,inv!$T:$T,'VENTA T'!$B29,inv!$U:$U,'VENTA T'!$C$27,inv!$A:$A,'VENTA T'!$B$25) -> 51315 | D29: =SUMIFS(inv!$D:$D,inv!$T:$T,'VENTA T'!$B29,inv!$U:$U,'VENTA T'!$D$27,inv!$A:$A,'VENTA T'!$B$25) -> 331200 | E29: =SUMIFS(inv!$D:$D,inv!$T:$T,'VENTA T'!$B29,inv!$U:$U,'VENTA T'!$E$27,inv!$A:$A,'VENTA T'!$B$25) -> 0 | F29: =SUMIFS(VENTAS!$H:$H,VENTAS!$G:$G,'VENTA T'!$B29,VENTAS!$B:$B,'VENTA T'!$B$25) -> 131012.5 | G29: =C29/$F29 -> 0.39168018 | H29: =D29/$F29 -> 2.5280031 | I29: =E29/$F29 -> 0 | J29: =H29+I29 -> 2.5280031 | K29: =IFERROR(C29-F29,0) -> -79697.5
B30: TAT BARRANQUILLA | C30: =SUMIFS(inv!$D:$D,inv!$T:$T,'VENTA T'!$B30,inv!$U:$U,'VENTA T'!$C$27,inv!$A:$A,'VENTA T'!$B$25) -> 132806 | D30: =SUMIFS(inv!$D:$D,inv!$T:$T,'VENTA T'!$B30,inv!$U:$U,'VENTA T'!$D$27,inv!$A:$A,'VENTA T'!$B$25) -> 407 | E30: =SUMIFS(inv!$D:$D,inv!$T:$T,'VENTA T'!$B30,inv!$U:$U,'VENTA T'!$E$27,inv!$A:$A,'VENTA T'!$B$25) -> 265920 | F30: =SUMIFS(VENTAS!$H:$H,VENTAS!$G:$G,'VENTA T'!$B30,VENTAS!$B:$B,'VENTA T'!$B$25) -> 94734 | G30: =C30/$F30 -> 1.4018832 | H30: =D30/$F30 -> 0.00429624 | I30: =E30/$F30 -> 2.8070175 | J30: =H30+I30 -> 2.8113138 | K30: =IFERROR(C30-F30,0) -> 38072
B31: TAT BOGOTA MONTEVIDEO | C31: =SUMIFS(inv!$D:$D,inv!$T:$T,'VENTA T'!$B31,inv!$U:$U,'VENTA T'!$C$27,inv!$A:$A,'VENTA T'!$B$25) -> 178163 | D31: =SUMIFS(inv!$D:$D,inv!$T:$T,'VENTA T'!$B31,inv!$U:$U,'VENTA T'!$D$27,inv!$A:$A,'VENTA T'!$B$25) -> 106235 | E31: =SUMIFS(inv!$D:$D,inv!$T:$T,'VENTA T'!$B31,inv!$U:$U,'VENTA T'!$E$27,inv!$A:$A,'VENTA T'!$B$25) -> 0 | F31: =SUMIFS(VENTAS!$H:$H,VENTAS!$G:$G,'VENTA T'!$B31,VENTAS!$B:$B,'VENTA T'!$B$25) -> 77841.333 | G31: =C31/$F31 -> 2.2887969 | H31: =D31/$F31 -> 1.3647634 | I31: =E31/$F31 -> 0 | J31: =H31+I31 -> 1.3647634 | K31: =IFERROR(C31-F31,0) -> 100321.67
B32: TAT CUCUTA | C32: =SUMIFS(inv!$D:$D,inv!$T:$T,'VENTA T'!$B32,inv!$U:$U,'VENTA T'!$C$27,inv!$A:$A,'VENTA T'!$B$25) -> 93424 | D32: =SUMIFS(inv!$D:$D,inv!$T:$T,'VENTA T'!$B32,inv!$U:$U,'VENTA T'!$D$27,inv!$A:$A,'VENTA T'!$B$25) -> 92500 | E32: =SUMIFS(inv!$D:$D,inv!$T:$T,'VENTA T'!$B32,inv!$U:$U,'VENTA T'!$E$27,inv!$A:$A,'VENTA T'!$B$25) -> 0 | F32: =SUMIFS(VENTAS!$H:$H,VENTAS!$G:$G,'VENTA T'!$B32,VENTAS!$B:$B,'VENTA T'!$B$25) -> 66412 | G32: =C32/$F32 -> 1.4067337 | H32: =D32/$F32 -> 1.3928206 | I32: =E32/$F32 -> 0 | J32: =H32+I32 -> 1.3928206 | K32: =IFERROR(C32-F32,0) -> 27012
B33: TAT BUCARAMANGA | C33: =SUMIFS(inv!$D:$D,inv!$T:$T,'VENTA T'!$B33,inv!$U:$U,'VENTA T'!$C$27,inv!$A:$A,'VENTA T'!$B$24) -> 14675 | D33: =SUMIFS(inv!$D:$D,inv!$T:$T,'VENTA T'!$B33,inv!$U:$U,'VENTA T'!$D$27,inv!$A:$A,'VENTA T'!$B$24) -> 67585 | E33: =SUMIFS(inv!$D:$D,inv!$T:$T,'VENTA T'!$B33,inv!$U:$U,'VENTA T'!$E$27,inv!$A:$A,'VENTA T'!$B$24) -> 46080 | F33: =SUMIFS(VENTAS!$H:$H,VENTAS!$G:$G,'VENTA T'!$B33,VENTAS!$B:$B,'VENTA T'!$B$24) -> 45663.5 | G33: =C33/$F33 -> 0.32137265 | H33: =D33/$F33 -> 1.4800661 | I33: =E33/$F33 -> 1.0091211 | J33: =H33+I33 -> 2.4891872 | K33: =IFERROR(C33-F33,0) -> -30988.5
B34: TAT CALI | C34: =SUMIFS(inv!$D:$D,inv!$T:$T,'VENTA T'!$B34,inv!$U:$U,'VENTA T'!$C$27,inv!$A:$A,'VENTA T'!$B$25) -> 75972 | D34: =SUMIFS(inv!$D:$D,inv!$T:$T,'VENTA T'!$B34,inv!$U:$U,'VENTA T'!$D$27,inv!$A:$A,'VENTA T'!$B$25) -> 224168 | E34: =SUMIFS(inv!$D:$D,inv!$T:$T,'VENTA T'!$B34,inv!$U:$U,'VENTA T'!$E$27,inv!$A:$A,'VENTA T'!$B$25) -> 0 | F34: =SUMIFS(VENTAS!$H:$H,VENTAS!$G:$G,'VENTA T'!$B34,VENTAS!$B:$B,'VENTA T'!$B$25) -> 61413.5 | G34: =C34/$F34 -> 1.237057 | H34: =D34/$F34 -> 3.6501421 | I34: =E34/$F34 -> 0 | J34: =H34+I34 -> 3.6501421 | K34: =IFERROR(C34-F34,0) -> 14558.5
B35: TAT CARTAGENA | C35: =SUMIFS(inv!$D:$D,inv!$T:$T,'VENTA T'!$B35,inv!$U:$U,'VENTA T'!$C$27,inv!$A:$A,'VENTA T'!$B$25) -> 3945 | D35: =SUMIFS(inv!$D:$D,inv!$T:$T,'VENTA T'!$B35,inv!$U:$U,'VENTA T'!$D$27,inv!$A:$A,'VENTA T'!$B$25) -> 39075 | E35: =SUMIFS(inv!$D:$D,inv!$T:$T,'VENTA T'!$B35,inv!$U:$U,'VENTA T'!$E$27,inv!$A:$A,'VENTA T'!$B$25) -> 84480 | F35: =SUMIFS(VENTAS!$H:$H,VENTAS!$G:$G,'VENTA T'!$B35,VENTAS!$B:$B,'VENTA T'!$B$25) -> 2392.5 | G35: =C35/$F35 -> 1.6489028 | H35: =D35/$F35 -> 16.332288 | I35: =E35/$F35 -> 35.310345 | J35: =H35+I35 -> 51.642633 | K35: =IFERROR(C35-F35,0) -> 1552.5
B36: TAT BOGOTA SIBERIA | C36: =SUMIFS(inv!$D:$D,inv!$T:$T,'VENTA T'!$B36,inv!$U:$U,'VENTA T'!$C$27,inv!$A:$A,'VENTA T'!$B$25) -> 49235 | D36: =SUMIFS(inv!$D:$D,inv!$T:$T,'VENTA T'!$B36,inv!$U:$U,'VENTA T'!$D$27,inv!$A:$A,'VENTA T'!$B$25) -> 36475 | E36: =SUMIFS(inv!$D:$D,inv!$T:$T,'VENTA T'!$B36,inv!$U:$U,'VENTA T'!$E$27,inv!$A:$A,'VENTA T'!$B$25) -> 0 | F36: =SUMIFS(VENTAS!$H:$H,VENTAS!$G:$G,'VENTA T'!$B36,VENTAS!$B:$B,'VENTA T'!$B$25) -> 22647.667 | G36: =C36/$F36 -> 2.1739546 | H36: =D36/$F36 -> 1.6105412 | I36: =E36/$F36 -> 0 | J36: =H36+I36 -> 1.6105412 | K36: =IFERROR(C36-F36,0) -> 26587.333
B37: TAT MEDELLIN | C37: =SUMIFS(inv!$D:$D,inv!$T:$T,'VENTA T'!$B37,inv!$U:$U,'VENTA T'!$C$27,inv!$A:$A,'VENTA T'!$B$25) -> 78619 | D37: =SUMIFS(inv!$D:$D,inv!$T:$T,'VENTA T'!$B37,inv!$U:$U,'VENTA T'!$D$27,inv!$A:$A,'VENTA T'!$B$25) -> 133644 | E37: =SUMIFS(inv!$D:$D,inv!$T:$T,'VENTA T'!$B37,inv!$U:$U,'VENTA T'!$E$27,inv!$A:$A,'VENTA T'!$B$25) -> 84480 | F37: =SUMIFS(VENTAS!$H:$H,VENTAS!$G:$G,'VENTA T'!$B37,VENTAS!$B:$B,'VENTA T'!$B$25) -> 53177.5 | G37: =C37/$F37 -> 1.478426 | H37: =D37/$F37 -> 2.5131682 | I37: =E37/$F37 -> 1.5886418 | J37: =H37+I37 -> 4.10181 | K37: =IFERROR(C37-F37,0) -> 25441.5
B38: TAT MONTERIA | C38: =SUMIFS(inv!$D:$D,inv!$T:$T,'VENTA T'!$B38,inv!$U:$U,'VENTA T'!$C$27,inv!$A:$A,'VENTA T'!$B$25) -> 1620 | D38: =SUMIFS(inv!$D:$D,inv!$T:$T,'VENTA T'!$B38,inv!$U:$U,'VENTA T'!$D$27,inv!$A:$A,'VENTA T'!$B$25) -> 17640 | E38: =SUMIFS(inv!$D:$D,inv!$T:$T,'VENTA T'!$B38,inv!$U:$U,'VENTA T'!$E$27,inv!$A:$A,'VENTA T'!$B$25) -> 0 | F38: =SUMIFS(VENTAS!$H:$H,VENTAS!$G:$G,'VENTA T'!$B38,VENTAS!$B:$B,'VENTA T'!$B$25)+F40 -> 17173 | G38: =C38/$F38 -> 0.094334129 | H38: =D38/$F38 -> 1.0271939 | I38: =E38/$F38 -> 0 | J38: =H38+I38 -> 1.0271939 | K38: =IFERROR(C38-F38,0) -> -15553
B39: TAT SANTA MARTA | C39: =SUMIFS(inv!$D:$D,inv!$T:$T,'VENTA T'!$B39,inv!$U:$U,'VENTA T'!$C$27,inv!$A:$A,'VENTA T'!$B$25) -> 21858 | D39: =SUMIFS(inv!$D:$D,inv!$T:$T,'VENTA T'!$B39,inv!$U:$U,'VENTA T'!$D$27,inv!$A:$A,'VENTA T'!$B$25) -> 10242 | E39: =SUMIFS(inv!$D:$D,inv!$T:$T,'VENTA T'!$B39,inv!$U:$U,'VENTA T'!$E$27,inv!$A:$A,'VENTA T'!$B$25) -> 0 | F39: =SUMIFS(VENTAS!$H:$H,VENTAS!$G:$G,'VENTA T'!$B39,VENTAS!$B:$B,'VENTA T'!$B$25) -> 15672.5 | G39: =C39/$F39 -> 1.3946722 | H39: =D39/$F39 -> 0.65350136 | I39: =E39/$F39 -> 0 | J39: =H39+I39 -> 0.65350136 | K39: =IFERROR(C39-F39,0) -> 6185.5
B40: TAT SINCELEJO | C40: =SUMIFS(inv!$D:$D,inv!$T:$T,'VENTA T'!$B40,inv!$U:$U,'VENTA T'!$C$27,inv!$A:$A,'VENTA T'!$B$25) -> 2008 | D40: =SUMIFS(inv!$D:$D,inv!$T:$T,'VENTA T'!$B40,inv!$U:$U,'VENTA T'!$D$27,inv!$A:$A,'VENTA T'!$B$25) -> 24120 | E40: =SUMIFS(inv!$D:$D,inv!$T:$T,'VENTA T'!$B40,inv!$U:$U,'VENTA T'!$E$27,inv!$A:$A,'VENTA T'!$B$25) -> 0 | F40: =SUMIFS(VENTAS!$H:$H,VENTAS!$G:$G,'VENTA T'!$B40,VENTAS!$B:$B,'VENTA T'!$B$25) -> 13892.5 | G40: =C40/$F40 -> 0.14453842 | H40: =D40/$F40 -> 1.7361886 | I40: =E40/$F40 -> 0 | J40: =H40+I40 -> 1.7361886 | K40: =IFERROR(C40-F40,0) -> -11884.5
B41: TAT VILLAVICENCIO | C41: =SUMIFS(inv!$D:$D,inv!$T:$T,'VENTA T'!$B41,inv!$U:$U,'VENTA T'!$C$27,inv!$A:$A,'VENTA T'!$B$25) -> 22420 | D41: =SUMIFS(inv!$D:$D,inv!$T:$T,'VENTA T'!$B41,inv!$U:$U,'VENTA T'!$D$27,inv!$A:$A,'VENTA T'!$B$25) -> 13754 | E41: =SUMIFS(inv!$D:$D,inv!$T:$T,'VENTA T'!$B41,inv!$U:$U,'VENTA T'!$E$27,inv!$A:$A,'VENTA T'!$B$25) -> 69120 | F41: =SUMIFS(VENTAS!$H:$H,VENTAS!$G:$G,'VENTA T'!$B41,VENTAS!$B:$B,'VENTA T'!$B$25) -> 19625.5 | G41: =C41/$F41 -> 1.1423913 | H41: =D41/$F41 -> 0.70082291 | I41: =E41/$F41 -> 3.5219485 | J41: =H41+I41 -> 4.2227714 | K41: =IFERROR(C41-F41,0) -> 2794.5
C42: =SUM(C28:C41) -> 922086 | D42: =SUM(D28:D41) -> 1255540 | E42: =SUM(E28:E41) -> 805440 | F42: =SUM(F28:F41) -> 773257.5
B43: 2110427
B44: 2110402
B45: M | G45: Días | H45: Días | I45: Días | J45: Días | K45: UND
B46: DESTINO | C46: VEHICULOS | D46: BODEGA | E46: TRANSITO | F46: PROM VENTA | G46: VEHICULOS | H46: BODEGA | I46: TRANSITO | J46: TOTAL | K46: CARGADAS
B47: TAT CARTAGENA | C47: =SUMIFS(inv!$D:$D,inv!$T:$T,'VENTA T'!$B47,inv!$U:$U,'VENTA T'!$C$46,inv!$A:$A,'VENTA T'!$B$44) -> 184734 | D47: =SUMIFS(inv!$D:$D,inv!$T:$T,'VENTA T'!$B47,inv!$U:$U,'VENTA T'!$D$46,inv!$A:$A,'VENTA T'!$B$44) -> 182914 | E47: =SUMIFS(inv!$D:$D,inv!$T:$T,'VENTA T'!$B47,inv!$U:$U,'VENTA T'!$E$46,inv!$A:$A,'VENTA T'!$B$44) -> 655704 | F47: =SUMIFS(VENTAS!$H:$H,VENTAS!$G:$G,'VENTA T'!$B47,VENTAS!$B:$B,'VENTA T'!$B$44) -> 235399 | G47: =C47/$F47 -> 0.78476969 | H47: =D47/$F47 -> 0.77703814 | I47: =E47/$F47 -> 2.7855004 | J47: =H47+I47 -> 3.5625385 | K47: =IFERROR(C47-F47,0) -> -50665
B48: TAT VALLEDUPAR | C48: =SUMIFS(inv!$D:$D,inv!$T:$T,'VENTA T'!$B48,inv!$U:$U,'VENTA T'!$C$46,inv!$A:$A,'VENTA T'!$B$44) -> 121535 | D48: =SUMIFS(inv!$D:$D,inv!$T:$T,'VENTA T'!$B48,inv!$U:$U,'VENTA T'!$D$46,inv!$A:$A,'VENTA T'!$B$44) -> 172783 | E48: =SUMIFS(inv!$D:$D,inv!$T:$T,'VENTA T'!$B48,inv!$U:$U,'VENTA T'!$E$46,inv!$A:$A,'VENTA T'!$B$44) -> 0 | F48: =SUMIFS(VENTAS!$H:$H,VENTAS!$G:$G,'VENTA T'!$B48,VENTAS!$B:$B,'VENTA T'!$B$44) -> 84611 | G48: =C48/$F48 -> 1.4363972 | H48: =D48/$F48 -> 2.0420867 | I48: =E48/$F48 -> 0 | J48: =H48+I48 -> 2.0420867 | K48: =IFERROR(C48-F48,0) -> 36924
B49: TAT SANTA MARTA | C49: =SUMIFS(inv!$D:$D,inv!$T:$T,'VENTA T'!$B49,inv!$U:$U,'VENTA T'!$C$46,inv!$A:$A,'VENTA T'!$B$44) -> 132189 | D49: =SUMIFS(inv!$D:$D,inv!$T:$T,'VENTA T'!$B49,inv!$U:$U,'VENTA T'!$D$46,inv!$A:$A,'VENTA T'!$B$44) -> 194350 | E49: =SUMIFS(inv!$D:$D,inv!$T:$T,'VENTA T'!$B49,inv!$U:$U,'VENTA T'!$E$46,inv!$A:$A,'VENTA T'!$B$44) -> 0 | F49: =SUMIFS(VENTAS!$H:$H,VENTAS!$G:$G,'VENTA T'!$B49,VENTAS!$B:$B,'VENTA T'!$B$44) -> 100768.5 | G49: =C49/$F49 -> 1.3118087 | H49: =D49/$F49 -> 1.9286781 | I49: =E49/$F49 -> 0 | J49: =H49+I49 -> 1.9286781 | K49: =IFERROR(C49-F49,0) -> 31420.5
B50: TAT BARRANQUILLA | C50: =SUMIFS(inv!$D:$D,inv!$T:$T,'VENTA T'!$B50,inv!$U:$U,'VENTA T'!$C$46,inv!$A:$A,'VENTA T'!$B$44) -> 191345 | D50: =SUMIFS(inv!$D:$D,inv!$T:$T,'VENTA T'!$B50,inv!$U:$U,'VENTA T'!$D$46,inv!$A:$A,'VENTA T'!$B$44) -> 300935 | E50: =SUMIFS(inv!$D:$D,inv!$T:$T,'VENTA T'!$B50,inv!$U:$U,'VENTA T'!$E$46,inv!$A:$A,'VENTA T'!$B$44) -> 113280 | F50: =SUMIFS(VENTAS!$H:$H,VENTAS!$G:$G,'VENTA T'!$B50,VENTAS!$B:$B,'VENTA T'!$B$44) -> 141735 | G50: =C50/$F50 -> 1.3500194 | H50: =D50/$F50 -> 2.1232229 | I50: =E50/$F50 -> 0.79923801 | J50: =H50+I50 -> 2.9224609 | K50: =IFERROR(C50-F50,0) -> 49610
B51: TAT MONTERIA | C51: =SUMIFS(inv!$D:$D,inv!$T:$T,'VENTA T'!$B51,inv!$U:$U,'VENTA T'!$C$46,inv!$A:$A,'VENTA T'!$B$44) -> 13371 | D51: =SUMIFS(inv!$D:$D,inv!$T:$T,'VENTA T'!$B51,inv!$U:$U,'VENTA T'!$D$46,inv!$A:$A,'VENTA T'!$B$44) -> 266746 | E51: =SUMIFS(inv!$D:$D,inv!$T:$T,'VENTA T'!$B51,inv!$U:$U,'VENTA T'!$E$46,inv!$A:$A,'VENTA T'!$B$44) -> 0 | F51: =SUMIFS(VENTAS!$H:$H,VENTAS!$G:$G,'VENTA T'!$B51,VENTAS!$B:$B,'VENTA T'!$B$44)+F53 -> 115340.5 | G51: =C51/$F51 -> 0.11592632 | H51: =D51/$F51 -> 2.3126829 | I51: =E51/$F51 -> 0 | J51: =H51+I51 -> 2.3126829 | K51: =IFERROR(C51-F51,0) -> -101969.5
B52: TAT POPAYAN | C52: =SUMIFS(inv!$D:$D,inv!$T:$T,'VENTA T'!$B52,inv!$U:$U,'VENTA T'!$C$46,inv!$A:$A,'VENTA T'!$B$44) -> 38513 | D52: =SUMIFS(inv!$D:$D,inv!$T:$T,'VENTA T'!$B52,inv!$U:$U,'VENTA T'!$D$46,inv!$A:$A,'VENTA T'!$B$44) -> 72057 | E52: =SUMIFS(inv!$D:$D,inv!$T:$T,'VENTA T'!$B52,inv!$U:$U,'VENTA T'!$E$46,inv!$A:$A,'VENTA T'!$B$44) -> 0 | F52: =SUMIFS(VENTAS!$H:$H,VENTAS!$G:$G,'VENTA T'!$B52,VENTAS!$B:$B,'VENTA T'!$B$44) -> 27662 | G52: =C52/$F52 -> 1.392271 | H52: =D52/$F52 -> 2.6049093 | I52: =E52/$F52 -> 0 | J52: =H52+I52 -> 2.6049093 | K52: =IFERROR(C52-F52,0) -> 10851
B53: TAT SINCELEJO | C53: =SUMIFS(inv!$D:$D,inv!$T:$T,'VENTA T'!$B53,inv!$U:$U,'VENTA T'!$C$46,inv!$A:$A,'VENTA T'!$B$44) -> 2782 | D53: =SUMIFS(inv!$D:$D,inv!$T:$T,'VENTA T'!$B53,inv!$U:$U,'VENTA T'!$D$46,inv!$A:$A,'VENTA T'!$B$44) -> 13398 | E53: =SUMIFS(inv!$D:$D,inv!$T:$T,'VENTA T'!$B53,inv!$U:$U,'VENTA T'!$E$46,inv!$A:$A,'VENTA T'!$B$44) -> 0 | F53: =SUMIFS(VENTAS!$H:$H,VENTAS!$G:$G,'VENTA T'!$B53,VENTAS!$B:$B,'VENTA T'!$B$44) -> 23581 | G53: =C53/$F53 -> 0.11797634 | H53: =D53/$F53 -> 0.56816929 | I53: =E53/$F53 -> 0 | J53: =H53+I53 -> 0.56816929 | K53: =IFERROR(C53-F53,0) -> -20799
B54: TAT CUCUTA | C54: =SUMIFS(inv!$D:$D,inv!$T:$T,'VENTA T'!$B54,inv!$U:$U,'VENTA T'!$C$46,inv!$A:$A,'VENTA T'!$B$44) -> 26970 | D54: =SUMIFS(inv!$D:$D,inv!$T:$T,'VENTA T'!$B54,inv!$U:$U,'VENTA T'!$D$46,inv!$A:$A,'VENTA T'!$B$44) -> 39407 | E54: =SUMIFS(inv!$D:$D,inv!$T:$T,'VENTA T'!$B54,inv!$U:$U,'VENTA T'!$E$46,inv!$A:$A,'VENTA T'!$B$44) -> 0 | F54: =SUMIFS(VENTAS!$H:$H,VENTAS!$G:$G,'VENTA T'!$B54,VENTAS!$B:$B,'VENTA T'!$B$44) -> 19173.5 | G54: =C54/$F54 -> 1.4066289 | H54: =D54/$F54 -> 2.0552846 | I54: =E54/$F54 -> 0 | J54: =H54+I54 -> 2.0552846 | K54: =IFERROR(C54-F54,0) -> 7796.5
B55: TAT BUCARAMANGA | C55: =SUMIFS(inv!$D:$D,inv!$T:$T,'VENTA T'!$B55,inv!$U:$U,'VENTA T'!$C$46,inv!$A:$A,$B$43) -> 6411 | D55: =SUMIFS(inv!$D:$D,inv!$T:$T,'VENTA T'!$B55,inv!$U:$U,$D$46,inv!$A:$A,$B$43) -> 43330 | E55: =SUMIFS(inv!$D:$D,inv!$T:$T,'VENTA T'!$B55,inv!$U:$U,$E$46,inv!$A:$A,$B$43) -> 23040 | F55: =SUMIFS(VENTAS!$H:$H,VENTAS!$G:$G,'VENTA T'!$B55,VENTAS!$B:$B,$B$43) -> 24068.5 | G55: =C55/$F55 -> 0.26636475 | H55: =D55/$F55 -> 1.8002784 | I55: =E55/$F55 -> 0.9572678 | J55: =H55+I55 -> 2.7575462 | K55: =IFERROR(C55-F55,0) -> -17657.5
B56: TAT MEDELLIN | C56: =SUMIFS(inv!$D:$D,inv!$T:$T,'VENTA T'!$B56,inv!$U:$U,'VENTA T'!$C$46,inv!$A:$A,$B$44) -> 7791 | D56: =SUMIFS(inv!$D:$D,inv!$T:$T,'VENTA T'!$B56,inv!$U:$U,$D$46,inv!$A:$A,$B$44) -> 22750 | E56: =SUMIFS(inv!$D:$D,inv!$T:$T,'VENTA T'!$B56,inv!$U:$U,$E$46,inv!$A:$A,$B$44) -> 0 | F56: =SUMIFS(VENTAS!$H:$H,VENTAS!$G:$G,'VENTA T'!$B56,VENTAS!$B:$B,$B$44) -> 5128 | G56: =C56/$F56 -> 1.5193058 | H56: =D56/$F56 -> 4.4364275 | I56: =E56/$F56 -> 0 | J56: =H56+I56 -> 4.4364275 | K56: =IFERROR(C56-F56,0) -> 2663
B57: TAT BOGOTA MONTEVIDEO | C57: =SUMIFS(inv!$D:$D,inv!$T:$T,'VENTA T'!$B57,inv!$U:$U,'VENTA T'!$C$46,inv!$A:$A,'VENTA T'!$B$44) -> 11438 | D57: =SUMIFS(inv!$D:$D,inv!$T:$T,'VENTA T'!$B57,inv!$U:$U,'VENTA T'!$D$46,inv!$A:$A,'VENTA T'!$B$44) -> 31935 | E57: =SUMIFS(inv!$D:$D,inv!$T:$T,'VENTA T'!$B57,inv!$U:$U,'VENTA T'!$E$46,inv!$A:$A,'VENTA T'!$B$44) -> 0 | F57: =SUMIFS(VENTAS!$H:$H,VENTAS!$G:$G,'VENTA T'!$B57,VENTAS!$B:$B,'VENTA T'!$B$44) -> 5137.6667 | G57: =C57/$F57 -> 2.2263025 | H57: =D57/$F57 -> 6.2158567 | I57: =E57/$F57 -> 0 | J57: =H57+I57 -> 6.2158567 | K57: =IFERROR(C57-F57,0) -> 6300.3333
B58: TAT BOGOTA SIBERIA | C58: =SUMIFS(inv!$D:$D,inv!$T:$T,'VENTA T'!$B58,inv!$U:$U,'VENTA T'!$C$46,inv!$A:$A,'VENTA T'!$B$44) -> 4758 | D58: =SUMIFS(inv!$D:$D,inv!$T:$T,'VENTA T'!$B58,inv!$U:$U,'VENTA T'!$D$46,inv!$A:$A,'VENTA T'!$B$44) -> 2370 | E58: =SUMIFS(inv!$D:$D,inv!$T:$T,'VENTA T'!$B58,inv!$U:$U,'VENTA T'!$E$46,inv!$A:$A,'VENTA T'!$B$44) -> 0 | F58: =SUMIFS(VENTAS!$H:$H,VENTAS!$G:$G,'VENTA T'!$B58,VENTAS!$B:$B,'VENTA T'!$B$44) -> 765.33333 | G58: =C58/$F58 -> 6.216899 | H58: =D58/$F58 -> 3.0966899 | I58: =E58/$F58 -> 0 | J58: =H58+I58 -> 3.0966899 | K58: =IFERROR(C58-F58,0) -> 3992.6667
C59: =SUM(C47:C58) -> 741837 | D59: =SUM(D47:D58) -> 1342975 | E59: =SUM(E47:E58) -> 792024 | F59: =SUM(F47:F58) -> 783370
B61: 2010301 | G61: AA
B62: AA GRIS | F62: Venta promedio 7 días | G62: Venta diaria | H62: Días | I62: Días | J62: Días
B63: DESTINO | C63: BODEGA | D63: TRANSITO | E63: TOTAL | H63: BODEGA | I63: TRANSITO | J63: TOTAL
B64: TAT CE BARRANQUILLA | C64: =SUMIFS(inv!$D:$D,inv!$T:$T,'VENTA T'!$B64,inv!$U:$U,'VENTA T'!$C$63,inv!$A:$A,'VENTA T'!$B$61) -> 203100 | D64: =SUMIFS(inv!$D:$D,inv!$T:$T,'VENTA T'!$B64,inv!$U:$U,'VENTA T'!$D$63,inv!$A:$A,'VENTA T'!$B$61) -> 105600 | E64: =SUM(C64:D64) -> 308700 | F64: =SUMIFS('VENTAS CANAL'!$AA:$AA, 'VENTAS CANAL'!$R:$R, "*"&TRIM(SUBSTITUTE($B64,"TAT CE",""))&"*", 'VENTAS CANAL'!$S:$S, TRIM(LEFT($G$61,FIND(" ",$G$61&" ")-1))) -> 1136160 | G64: =IFERROR(F64/7,0) -> 162308.57 | H64: =+C64/G64 -> 1.2513202 | I64: =+D64/G64 -> 0.65061259 | J64: =+H64+I64 -> 1.9019328
B65: TAT CE BOGOTA | C65: =SUMIFS(inv!$D:$D,inv!$T:$T,'VENTA T'!$B65,inv!$U:$U,'VENTA T'!$C$63,inv!$A:$A,'VENTA T'!$B$61) -> 353760 | D65: =SUMIFS(inv!$D:$D,inv!$T:$T,'VENTA T'!$B65,inv!$U:$U,'VENTA T'!$D$63,inv!$A:$A,'VENTA T'!$B$61) -> 57600 | E65: =SUM(C65:D65) -> 411360 | F65: =SUMIFS('VENTAS CANAL'!$AA:$AA, 'VENTAS CANAL'!$R:$R, "*"&TRIM(SUBSTITUTE($B65,"TAT CE",""))&"*", 'VENTAS CANAL'!$S:$S, TRIM(LEFT($G$61,FIND(" ",$G$61&" ")-1))) -> 2096496 | G65: =IFERROR(F65/7,0) -> 299499.43 | H65: =+C65/G65 -> 1.1811709 | I65: =+D65/G65 -> 0.1923209 | J65: =+H65+I65 -> 1.3734918
B66: TAT CE MEDELLIN | C66: =SUMIFS(inv!$D:$D,inv!$T:$T,'VENTA T'!$B66,inv!$U:$U,'VENTA T'!$C$63,inv!$A:$A,'VENTA T'!$B$61) -> 200167 | D66: =SUMIFS(inv!$D:$D,inv!$T:$T,'VENTA T'!$B66,inv!$U:$U,'VENTA T'!$D$63,inv!$A:$A,'VENTA T'!$B$61) -> 86400 | E66: =SUM(C66:D66) -> 286567 | F66: =SUMIFS('VENTAS CANAL'!$AA:$AA, 'VENTAS CANAL'!$R:$R, "*"&TRIM(SUBSTITUTE($B66,"TAT CE",""))&"*", 'VENTAS CANAL'!$S:$S, TRIM(LEFT($G$61,FIND(" ",$G$61&" ")-1))) -> 2046384 | G66: =IFERROR(F66/7,0) -> 292340.57 | H66: =+C66/G66 -> 0.68470483 | I66: =+D66/G66 -> 0.2955457 | J66: =+H66+I66 -> 0.98025053
B67: TAT CE MONTERIA | C67: =SUMIFS(inv!$D:$D,inv!$T:$T,'VENTA T'!$B67,inv!$U:$U,'VENTA T'!$C$63,inv!$A:$A,'VENTA T'!$B$61) -> 30960 | D67: =SUMIFS(inv!$D:$D,inv!$T:$T,'VENTA T'!$B67,inv!$U:$U,'VENTA T'!$D$63,inv!$A:$A,'VENTA T'!$B$61) -> 84480 | E67: =SUM(C67:D67) -> 115440 | F67: =SUMIFS('VENTAS CANAL'!$AA:$AA, 'VENTAS CANAL'!$R:$R, "*"&TRIM(SUBSTITUTE($B67,"TAT CE",""))&"*", 'VENTAS CANAL'!$S:$S, TRIM(LEFT($G$61,FIND(" ",$G$61&" ")-1))) -> 84240 | G67: =IFERROR(F67/7,0) -> 12034.286 | H67: =+C67/G67 -> 2.5726496 | I67: =+D67/G67 -> 7.019943 | J67: =+H67+I67 -> 9.5925926
C68: =SUM(C64:C67) -> 787987 | D68: =SUM(D64:D67) -> 334080 | E68: =SUM(E64:E67) -> 1122067 | F68: =+SUM(F64:F67) -> 5363280 | G68: =+SUM(G64:G67) -> 766182.86 | H68: =+C68/G68 -> 1.0284581 | I68: =+D68/G68 -> 0.43603168 | J68: =+H68+I68 -> 1.4644898
B70: 2410401 | G70: A
B71: A GRIS | F71: Venta promedio 7 días | G71: Venta diaria | H71: Días | I71: Días | J71: Días
B72: DESTINO | C72: BODEGA | D72: TRANSITO | E72: TOTAL | H72: BODEGA | I72: TRANSITO | J72: TOTAL
B73: TAT CE BARRANQUILLA | C73: =SUMIFS(inv!$D:$D,inv!$T:$T,'VENTA T'!$B73,inv!$U:$U,'VENTA T'!$C$72,inv!$A:$A,'VENTA T'!$B$70) -> 197916 | D73: =SUMIFS(inv!$D:$D,inv!$T:$T,'VENTA T'!$B73,inv!$U:$U,'VENTA T'!$D$72,inv!$A:$A,'VENTA T'!$B$70) -> 136800 | E73: =SUM(C73:D73) -> 334716 | F73: =SUMIFS('VENTAS CANAL'!$AA:$AA, 'VENTAS CANAL'!$R:$R, "*"&TRIM(SUBSTITUTE($B73,"TAT CE",""))&"*", 'VENTAS CANAL'!$S:$S, TRIM(LEFT($G$70,FIND(" ",$G$70&" ")-1))) -> 830160 | G73: =IFERROR(F73/7,0) -> 118594.29 | H73: =+C73/G73 -> 1.6688494 | I73: =+D73/G73 -> 1.1535126 | J73: =+H73+I73 -> 2.822362
B74: TAT CE BOGOTA | C74: =SUMIFS(inv!$D:$D,inv!$T:$T,'VENTA T'!$B74,inv!$U:$U,'VENTA T'!$C$72,inv!$A:$A,'VENTA T'!$B$70) -> 77814 | D74: =SUMIFS(inv!$D:$D,inv!$T:$T,'VENTA T'!$B74,inv!$U:$U,'VENTA T'!$D$72,inv!$A:$A,'VENTA T'!$B$70) -> 704640 | E74: =SUM(C74:D74) -> 782454 | F74: =SUMIFS('VENTAS CANAL'!$AA:$AA, 'VENTAS CANAL'!$R:$R, "*"&TRIM(SUBSTITUTE($B74,"TAT CE",""))&"*", 'VENTAS CANAL'!$S:$S, TRIM(LEFT($G$70,FIND(" ",$G$70&" ")-1))) -> 1944000 | G74: =IFERROR(F74/7,0) -> 277714.29 | H74: =+C74/G74 -> 0.28019444 | I74: =+D74/G74 -> 2.537284 | J74: =+H74+I74 -> 2.8174784
B75: TAT CE MEDELLIN | C75: =SUMIFS(inv!$D:$D,inv!$T:$T,'VENTA T'!$B75,inv!$U:$U,'VENTA T'!$C$72,inv!$A:$A,'VENTA T'!$B$70) -> 312912 | D75: =SUMIFS(inv!$D:$D,inv!$T:$T,'VENTA T'!$B75,inv!$U:$U,'VENTA T'!$D$72,inv!$A:$A,'VENTA T'!$B$70) -> 278400 | E75: =SUM(C75:D75) -> 591312 | F75: =SUMIFS('VENTAS CANAL'!$AA:$AA, 'VENTAS CANAL'!$R:$R, "*"&TRIM(SUBSTITUTE($B75,"TAT CE",""))&"*", 'VENTAS CANAL'!$S:$S, TRIM(LEFT($G$70,FIND(" ",$G$70&" ")-1))) -> 1663200 | G75: =IFERROR(F75/7,0) -> 237600 | H75: =+C75/G75 -> 1.3169697 | I75: =+D75/G75 -> 1.1717172 | J75: =+H75+I75 -> 2.4886869
B76: TAT CE MONTERIA | C76: =SUMIFS(inv!$D:$D,inv!$T:$T,'VENTA T'!$B76,inv!$U:$U,'VENTA T'!$C$72,inv!$A:$A,'VENTA T'!$B$70) -> 293475 | D76: =SUMIFS(inv!$D:$D,inv!$T:$T,'VENTA T'!$B76,inv!$U:$U,'VENTA T'!$D$72,inv!$A:$A,'VENTA T'!$B$70) -> 115200 | E76: =SUM(C76:D76) -> 408675 | F76: =SUMIFS('VENTAS CANAL'!$AA:$AA, 'VENTAS CANAL'!$R:$R, "*"&TRIM(SUBSTITUTE($B76,"TAT CE",""))&"*", 'VENTAS CANAL'!$S:$S, TRIM(LEFT($G$70,FIND(" ",$G$70&" ")-1))) -> 425520 | G76: =IFERROR(F76/7,0) -> 60788.571 | H76: =+C76/G76 -> 4.8277989 | I76: =+D76/G76 -> 1.8950931 | J76: =+H76+I76 -> 6.722892
C77: =SUM(C73:C76) -> 882117 | D77: =SUM(D73:D76) -> 1235040 | E77: =SUM(E73:E76) -> 2117157 | F77: =+SUM(F73:F76) -> 4862880 | G77: =+SUM(G73:G76) -> 694697.14 | H77: =+C77/G77 -> 1.2697864 | I77: =+D77/G77 -> 1.7778107 | J77: =+H77+I77 -> 3.0475971
B79: 2010501 | G79: B
B80: B GRIS | F80: Venta promedio 7 días | G80: Venta diaria | H80: Días | I80: Días | J80: Días
B81: DESTINO | C81: BODEGA | D81: TRANSITO | E81: TOTAL | H81: BODEGA | I81: TRANSITO | J81: TOTAL
B82: TAT CE BARRANQUILLA | C82: =SUMIFS(inv!$D:$D,inv!$T:$T,'VENTA T'!$B82,inv!$U:$U,$C$81,inv!$A:$A,$B$79) -> 765147 | D82: =SUMIFS(inv!$D:$D,inv!$T:$T,'VENTA T'!$B82,inv!$U:$U,$D$81,inv!$A:$A,$B$79) -> 642500 | E82: =SUM(C82:D82) -> 1407647 | F82: =SUMIFS('VENTAS CANAL'!$AA:$AA, 'VENTAS CANAL'!$R:$R, "*"&TRIM(SUBSTITUTE($B82,"TAT CE",""))&"*", 'VENTAS CANAL'!$S:$S, TRIM(LEFT($G$79,FIND(" ",$G$79&" ")-1))) -> 939600 | G82: =IFERROR(F82/7,0) -> 134228.57 | H82: =+C82/G82 -> 5.7003289 | I82: =+D82/G82 -> 4.7866113 | J82: =+H82+I82 -> 10.48694
B83: TAT CE BOGOTA | C83: =SUMIFS(inv!$D:$D,inv!$T:$T,'VENTA T'!$B83,inv!$U:$U,$C$81,inv!$A:$A,$B$79) -> 0 | D83: =SUMIFS(inv!$D:$D,inv!$T:$T,'VENTA T'!$B83,inv!$U:$U,$D$81,inv!$A:$A,$B$79) -> 0 | E83: =SUM(C83:D83) -> 0 | F83: =SUMIFS('VENTAS CANAL'!$AA:$AA, 'VENTAS CANAL'!$R:$R, "*"&TRIM(SUBSTITUTE($B83,"TAT CE",""))&"*", 'VENTAS CANAL'!$S:$S, TRIM(LEFT($G$79,FIND(" ",$G$79&" ")-1))) -> 0 | G83: =IFERROR(F83/7,0) -> 0 | H83: =IFERROR((C83/G83),0) -> 0 | I83: =IFERROR((D83/G83),0) -> 0 | J83: =+H83+I83 -> 0
B84: TAT CE MEDELLIN | C84: =SUMIFS(inv!$D:$D,inv!$T:$T,'VENTA T'!$B84,inv!$U:$U,$C$81,inv!$A:$A,$B$79) -> 0 | D84: =SUMIFS(inv!$D:$D,inv!$T:$T,'VENTA T'!$B84,inv!$U:$U,$D$81,inv!$A:$A,$B$79) -> 0 | E84: =SUM(C84:D84) -> 0 | F84: =SUMIFS('VENTAS CANAL'!$AA:$AA, 'VENTAS CANAL'!$R:$R, "*"&TRIM(SUBSTITUTE($B84,"TAT CE",""))&"*", 'VENTAS CANAL'!$S:$S, TRIM(LEFT($G$79,FIND(" ",$G$79&" ")-1))) -> 0 | G84: =IFERROR(F84/7,0) -> 0 | H84: =IFERROR((C84/G84),0) -> 0 | I84: =IFERROR((D84/G84),0) -> 0 | J84: =+H84+I84 -> 0
B85: TAT CE MONTERIA | C85: =SUMIFS(inv!$D:$D,inv!$T:$T,'VENTA T'!$B85,inv!$U:$U,$C$81,inv!$A:$A,$B$79) -> 93669 | D85: =SUMIFS(inv!$D:$D,inv!$T:$T,'VENTA T'!$B85,inv!$U:$U,$D$81,inv!$A:$A,$B$79) -> 248640 | E85: =SUM(C85:D85) -> 342309 | F85: =SUMIFS('VENTAS CANAL'!$AA:$AA, 'VENTAS CANAL'!$R:$R, "*"&TRIM(SUBSTITUTE($B85,"TAT CE",""))&"*", 'VENTAS CANAL'!$S:$S, TRIM(LEFT($G$79,FIND(" ",$G$79&" ")-1))) -> 241920 | G85: =IFERROR(F85/7,0) -> 34560 | H85: =+C85/G85 -> 2.7103299 | I85: =+D85/G85 -> 7.1944444 | J85: =+H85+I85 -> 9.9047743
C86: =SUM(C82:C85) -> 858816 | D86: =SUM(D82:D85) -> 891140 | E86: =SUM(E82:E85) -> 1749956 | F86: =+SUM(F82:F85) -> 1181520 | G86: =+SUM(G82:G85) -> 168788.57 | H86: =+C86/G86 -> 5.088117 | I86: =+D86/G86 -> 5.2796229 | J86: =+H86+I86 -> 10.36774

Sheet CEDIS
A1: VOLVER
C4: CEDI | D4: COD | E4: NOMBRE | F4: INVENTARIO TOTAL | G4: PROMEDIO VENTAS | H4: PROMEDIO PROYECCIÓN | I4: DÍAS INVENTARIO | J4: COBERTURA. | K4: INV. VEHICULOS | L4: DIAS INV VEHICULOS | M4: INV. TRANSITO | N4: DÍAS INV . TRANSITO | O4: INV. BODEGA | P4: DIAS INV. BODEGA
C5: TAT BARRANQUILLA | D5: 79201 | E5: DESECHO HUEVO CASCARA | F5: 2757 | G5: 0 | H5: 0 | I5: 0 | J5: 0 | K5: 365 | L5: 0 | M5: 0 | N5: 0 | O5: 2392 | P5: 0
C6: TAT BARRANQUILLA | D6: 13503 | E6: HUEVO B X 30 BAND GRIS AMARRADO ALAT | F6: 360 | G6: 0 | H6: 0 | I6: 0 | J6: 0 | K6: 360 | L6: 0 | M6: 0 | N6: 0 | O6: 0 | P6: 0
C7: TAT BARRANQUILLA | D7: 79101 | E7: HUEVO ROTO | F7: 140 | G7: 0 | H7: 0 | I7: 0 | J7: 0 | K7: 0 | L7: 0 | M7: 0 | N7: 0 | O7: 140 | P7: 0
C8: TAT BARRANQUILLA | D8: 10501 | E8: HUEVO B X30 CARTON GRIS | F8: 80 | G8: 0 | H8: 0 | I8: 0 | J8: 0 | K8: 80 | L8: 0 | M8: 0 | N8: 0 | O8: 0 | P8: 0
C9: TAT BARRANQUILLA | D9: 13480 | E9: HUEVO A X 30 BANDEJA GRIS ALAT CAJA X 360 | F9: 0 | G9: 0 | H9: 0 | I9: 0 | J9: 0 | K9: 0 | L9: 0 | M9: 0 | N9: 0 | O9: 0 | P9: 0
C10: TAT BARRANQUILLA | D10: 72101 | E10: SUCIO ROJO PEQUEÑO | F10: 0 | G10: 0 | H10: 0 | I10: 0 | J10: 0 | K10: 0 | L10: 0 | M10: 0 | N10: 0 | O10: 0 | P10: 0
C11: TAT BARRANQUILLA | D11: 76501 | E11: REVOLTURA COMERCIAL PEQUEÑA | F11: 0 | G11: 0 | H11: 0 | I11: 0 | J11: 0 | K11: 0 | L11: 0 | M11: 0 | N11: 0 | O11: 0 | P11: 0
C12: TAT BARRANQUILLA | D12: 10104 | E12: HUEVO YUMBO X20 FS CARTON VERDE | F12: 0 | G12: 0 | H12: 0 | I12: 0 | J12: 0 | K12: 0 | L12: 0 | M12: 0 | N12: 0 | O12: 0 | P12: 0
C13: TAT BARRANQUILLA | D13: 106 | E13: HUEVO C. ROJO | F13: 0 | G13: 0 | H13: 0 | I13: 0 | J13: 0 | K13: 0 | L13: 0 | M13: 0 | N13: 0 | O13: 0 | P13: 0
C14: TAT BARRANQUILLA | D14: 10201 | E14: HUEVO AAA X30 CARTON GRIS | F14: 0 | G14: 0 | H14: 0 | I14: 0 | J14: 0 | K14: 0 | L14: 0 | M14: 0 | N14: 0 | O14: 0 | P14: 0
C15: TAT BARRANQUILLA | D15: 52378 | E15: HUEVO AA X 15 PAGUE 12 PET CAJA POR 360 | F15: 0 | G15: 0 | H15: 0 | I15: 0 | J15: 0 | K15: 0 | L15: 0 | M15: 0 | N15: 0 | O15: 0 | P15: 0
C16: TAT BARRANQUILLA | D16: 10202 | E16: HUEVO AAA X30 CARTON VERDE | F16: 0 | G16: 0 | H16: 0 | I16: 0 | J16: 0 | K16: 0 | L16: 0 | M16: 0 | N16: 0 | O16: 0 | P16: 0
... C2138: TAT BOGOTA MONTEVIDEO | D2138: 13359 | E2138: HUEVO AA X 300 BANDEJA GRIS ALAT CAJA AMARRADO | F2138: 0 | G2138: 0 | H2138: 0 | I2138: 0 | J2138: 0 | K2138: 0 | L2138: 0 | M2138: 0 | N2138: 0 | O2138: 0 | P2138: 0
C2139: Total general | F2139: 1461981 | G2139: 8616 | H2139: 19740 | I2139: 1.9242424 | J2139: 0 | K2139: 19860 | L2139: 0.69318182 | M2139: 707194 | N2139: 0 | O2139: 734927 | P2139: 1.2310606

Sheet PLANTAS
A1: VOLVER
E5: Etiquetas de fila | F5: NOMBRE | G5: INVENTARIO.
E6: SANTANDER
E7: 2110402 | F7: HUEVO M X 30 CARTON VERDE CANASTA | G7: 459727
E8: 2010501 | F8: HUEVO B X30 CARTON GRIS CANASTA | G8: 288079
E9: 10601 | F9: HUEVO CX30 CARTON GRIS | G9: 150622
E10: 2110302 | F10: HUEVO L X 30 CARTON VERDE CANASTA | G10: 90736
E11: 10501 | F11: HUEVO B X30 CARTON GRIS | G11: 38288
E12: 112379 | F12: HUEVO L X 30 PET CAJA X 300 | G12: 37200
E13: 79111 | F13: HUEVO ROTO ZF- SANTANDER | G13: 31995
E14: 75301 | F14: HUEVO AA X 30 CARTON GRIS LZ | G14: 30030
E15: 2110202 | F15: HUEVO XL X 30 CARTON VERDE CANASTA | G15: 28939
E16: 75401 | F16: HUEVO A X 30 CARTON GRIS LZ | G16: 16080
E17: 13459 | F17: HUEVO A X 300 BANDEJA GRIS ALAT CAJA AMARRADO | G17: 15600
E18: 2010102 | F18: HUEVO YUMBO X20 CARTON VERDE CANASTA | G18: 14825
... E21: 112268 | F21: HUEVO XL X 15 PET CAJA X 300 | G21: 4200
F22: HUEVO XL X 15 PET CAJA X 300. | G22: 4200
E23: 110303 | F23: HUEVO L X30 CARTON VERDE AMARRADO | G23: 8100
E24: 2152388 | F24: HUEVO L X 15 PAGUE 14 PET EN CANASTA. | G24: 7200
E25: 152384 | F25: HUEVO L X 15 PAGUE 14 PET CAJA X 300. | G25: 5100
E26: 13403 | F26: HUEVO A X 30 BAND GRIS AMARRADO ALAT | G26: 5040
E27: 10401 | F27: HUEVO A X30 CARTON GRIS | G27: 5040
E28: 75201 | F28: HUEVO AAA X 30 CARTON GRIS LZ | G28: 4530
E29: 75501 | F29: HUEVO B X 30 CARTON GRIS LZ | G29: 2580
E30: 72001 | F30: HUEVO SUCIO DE JAULA | G30: 1714
E31: 76601 | F31: REVOLTURA COMERCIAL MEDIANA | G31: 619
E32: 72003 | F32: HUEVO SUCIO ZF MARCADO | G32: 476
E33: 72005 | F33: HUEVO SUCIO SIN MARCA X30 BANDEJA GRIS L | G33: 0
E34: 2110410 | F34: HUEVO M X30 CARTON VERDE AMARRADO CON BANDEJA CANASTA | G34: 0
... E187: 10318 | F187: HUEVO AAX30 CARTÓN VERDE MICROBIOLOGICO CON ETIQUETA | G187: 0
E188: Total SANTANDER | G188: 1267968
E189: CALOTO
E190: 2110202 | F190: HUEVO XL X 30 CARTON VERDE CANASTA | G190: 620029
E191: 2010301 | F191: HUEVO AA X30 CARTON GRIS CANASTA | G191: 521124
E192: 73001 | F192: HUEVO PICADO ROJO | G192: 236592
E193: 112268 | F193: HUEVO XL X 15 PET CAJA X 300 | G193: 84000
F194: HUEVO XL X 15 PET CAJA X 300. | G194: 84000
E195: 2110302 | F195: HUEVO L X 30 CARTON VERDE CANASTA | G195: 145099
E196: 72003 | F196: HUEVO SUCIO ZF MARCADO | G196: 118294
E197: 75201 | F197: HUEVO AAA X 30 CARTON GRIS LZ | G197: 81502
E198: 75301 | F198: HUEVO AA X 30 CARTON GRIS LZ | G198: 50559
E199: 10601 | F199: HUEVO CX30 CARTON GRIS | G199: 48854
E200: 79110 | F200: HUEVO ROTO - ZF | G200: 37800
E201: 75401 | F201: HUEVO A X 30 CARTON GRIS LZ | G201: 28069
E202: 2010102 | F202: HUEVO YUMBO X20 CARTON VERDE CANASTA | G202: 24673
E203: 72001 | F203: HUEVO SUCIO DE JAULA | G203: 9144
E204: 75501 | F204: HUEVO B X 30 CARTON GRIS LZ | G204: 7040
E205: 2110402 | F205: HUEVO M X 30 CARTON VERDE CANASTA | G205: 3376
E206: 72002 | F206: HUEVO SUCIO ZF | G206: 3210
... E370: 10318 | F370: HUEVO AAX30 CARTÓN VERDE MICROBIOLOGICO CON ETIQUETA | G370: 0
E371: Total CALOTO | G371: 2105716
E372: Total general | G372: 3373684

Sheet CONVERSION DATOS
A1: DESTINO | B1: id_bodega | C1: DESTINO | D1: GRUPO
A2: KIKES - EGIPTO | B2: ALKA | C2: ALKA1 | D2: PLANTA CLASIFICACION
A3: KIKES2 - EGIPTO | B3: ALKA2 | C3: ALKA2 | D3: PLANTA CLASIFICACION
A4: BODEGA INTEGRADO JP | B4: AT1 | C4: INTEGRADO JP | D4: PLANTA CLASIFICACION
A5: BELLAVISTA | B5: BE | C5: BELLAVISTA | D5: PLANTA CLASIFICACION
A6: BARRANQUILLA CLASIFICACION | B6: BQ | C6: TAT CE BARRANQUILLA | D6: BODEGA
A7: CLASIFICADORA LANZA | B7: CLKI | C7: LANZA | D7: HUEVO SIN CLASIFICAR
A8: ELABORACION DE PRODUCTOS - ALKA | B8: EPALKA | C8: ALKA1 | D8: PLANTA CLASIFICACION
A9: ELABORACION DE PRODUCTO BARRANQUILLA CLASIFICACION | B9: EPBQ | C9: TAT CE BARRANQUILLA | D9: BODEGA
A10: ELABORACION DE PRODUCTOS - ALKA2 | B10: EPALKA2 | C10: ALKA2 | D10: PLANTA CLASIFICACION
A11: ELABORACION DE PRODUCTOS - KI | B11: EPKI | C11: LANZA | D11: PLANTA CLASIFICACION
A12: ELABORACION DE PRODUCTOS - PALMAS | B12: EPPALM | C12: PALMAS | D12: PLANTA CLASIFICACION
... A273: TATBOGOTA SIBERIA ROTURAS | B273: H5900 | C273: TAT BOGOTA SIBERIA | D273: OTROS
B274: Barranquilla | C274: TAT BARRANQUILLA
B275: BOGOTA | C275: TAT BOGOTA MONTEVIDEO
A276: BOGOTA MONTEVIDEO | B276: BOGOTA | C276: TAT BOGOTA MONTEVIDEO
B277: Alka1 | C277: ALKA1
B278: BOGOTA | C278: TAT BOGOTA MONTEVIDEO
B279: Bucaramanga | C279: TAT BUCARAMANGA
B280: Alka2 | C280: ALKA2
B281: Cali | C281: TAT CALI
B282: Cartagena | C282: TAT CARTAGENA | D282: OTROS
B283: BE | C283: BE
B284: Cucuta | C284: TAT CUCUTA
B285: Medellin | C285: TAT MEDELLIN
B286: Monteria | C286: TAT MONTERIA
B287: Lanza | C287: LANZA
B288: Pasto | C288: TAT PASTO
B289: Popayan | C289: TAT POPAYAN
B290: Santa Marta | C290: TAT SANTA MARTA | D290: OTROS
B291: Palmas | C291: PALMAS
B292: Valledupar | C292: TAT VALLEDUPAR
B293: BOGOTA | C293: TAT BOGOTA MONTEVIDEO
A294: TAT H3050 - AUTOSERVICIOS | B294: H3050 | C294: TAT MEDELLIN | D294: VEHICULOS
A295: TAT CARTAGENA H4140 - ESPECIAL | B295: H4140 | C295: TAT CARTAGENA | D295: VEHICULOS
A296: TAT SANTAMARTA - INVENTARIO TRANSITO | B296: VT42 | C296: TAT SANTA MARTA | D296: TRANSITO
A297: TAT PASTO - INVENTARIO TRANSITO | B297: VT6 | C297: TAT PASTO | D297: TRANSITO
A298: BODEGA BELLAVISTA - INVENTARIO TRANSITO | B298: VTBE | C298: BELLAVISTA | D298: PLANTA CLASIFICACION
A299: BODEGA DE CONSERVACION Y DESPACHO PUERTO TEJADA | B299: GC25 | C299: 0 | D299: BODEGA
A300: TAT CALI H2025 | B300: H2025 | C300: TAT CALI | D300: VEHICULOS
A301: TAT MEDELLIN - GRANDES SUPERFICIES | B301: H3060 | C301: TAT MEDELLIN | D301: VEHICULOS
A302: TAT PEREIRA H3507 | B302: H3507 | C302: TAT PEREIRA | D302: VEHICULOS
A303: TAT SANTAMARTA H4240 - ESPECIAL | B303: H4240 | C303: TAT SANTA MARTA | D303: VEHICULOS
B304: BOGOTA | C304: TAT BOGOTA MONTEVIDEO
B305: STA MARTA | C305: TAT SANTA MARTA | D305: OTROS
A306: TAT BARRANQUILLA - INVENTARIO TRANSITO | B306: VT4 | C306: TAT BARRANQUILLA | D306: TRANSITO
A307: PRODUCTO POR FACTURAR | B307: FS1PF | C307: TAT BUCARAMANGA
A308: TAT CALI - FOOD SERVICE | B308: FS2 | C308: TAT CALI | D308: VEHICULOS
A309: BELLAVISTA - BLOQUEADO | B309: XBE | C309: BELLAVISTA | D309: OTROS
A310: BODEGA KIKES - BLOQUEADO | B310: XKI | C310: LANZA | D310: OTROS
A311: TAT BARRANQUILLA H4040 - ESPECIAL | B311: H4040 | C311: TAT BARRANQUILLA | D311: VEHICULOS
A312: TAT CALI H2024 | B312: H2024 | C312: TAT CALI | D312: VEHICULOS
A313: TAT CALI H2007 | B313: H2007 | C313: TAT CALI | D313: VEHICULOS
A314: TAT MEDELLIN H3012 | B314: H3012 | C314: TAT MEDELLIN | D314: VEHICULOS
A315: TAT MEDELLIN H3040 - ESPECIAL | B315: H3040 | C315: TAT MEDELLIN | D315: VEHICULOS
A316: TAT PASTO H6040 - ESPECIAL | B316: H6040 | C316: TAT PASTO | D316: VEHICULOS
A317: TAT CARTAGENA H4109 | B317: H4109 | C317: TAT CARTAGENA | D317: VEHICULOS
A318: TAT SANTAMARTA H4209 | B318: H4209 | C318: TAT SANTA MARTA | D318: VEHICULOS
A319: TAT MEDELLIN H3030 | B319: H3030 | C319: TAT MEDELLIN | D319: VEHICULOS
B320: Pasto Bodega | C320: TAT PASTO | D320: VEHICULOS
B321: OplPereira | C321: TAT PEREIRA | D321: VEHICULOS
A322: TAT PEREIRA - INVENTARIO TRANSITO | B322: VT36 | C322: TAT PEREIRA | D322: TRANSITO
A323: TAT PEREIRA H3601 - OP | B323: H3601 | C323: TAT PEREIRA | D323: VEHICULOS
A324: PEREIRA - RUTA ESPECIAL OPERADOR | B324: H3640 | C324: TAT PEREIRA | D324: VEHICULOS
A325: FOOD SERVICE PEREIRA - OP | B325: FS36 | C325: TAT PEREIRA | D325: VEHICULOS
A326: TAT PEREIRA H3602 - OP | B326: H3602 | C326: TAT PEREIRA | D326: VEHICULOS
A327: TAT CARTAGENA H4111 | B327: H4111 | C327: TAT CARTAGENA | D327: VEHICULOS
A328: CENTRO DE EMPAQUES BOGOTA -INVENTARIO TRANSITO | B328: VTBO | C328: TAT CE BOGOTA | D328: TRANSITO
A329: ELABORACION PRODUCTO CENTRO DE EMPAQUES BOGOTA | B329: EPBO | C329: TAT CE BOGOTA | D329: BODEGA
A330: CENTRO DE EMPAQUES BOGOTA | B330: BO | C330: TAT CE BOGOTA | D330: BODEGA
B331: C.E BOGOTA | C331: TAT CE BOGOTA | D331: BODEGA
B332: C.E BOGOTA | C332: TAT CE BOGOTA
B333: PEREIRA | C333: OL. PEREIRA
A334: CLASIFICADORA PRODUCCION 1 y 2 | B334: CLALKA | C334: ALKA1 | D334: HUEVO SIN CLASIFICAR
A335: CLASIFICADORA PRODUCCCION 3 | B335: CLALKA2 | C335: ALKA2 | D335: HUEVO SIN CLASIFICAR | G335: PLANTA CLASIFICADORA INTEGRADO JP | H335: CLAT1
A336: CLASIFICADORA PALMAS | B336: CLPALM | C336: PALMAS | D336: HUEVO SIN CLASIFICAR | G336: CLASIFICADORA BELLAVISTA | H336: CLBE
A337: EGIPTO - INVENTARIO TRANSITO PALMA | B337: VTPALM | C337: PALMAS | D337: PLANTA CLASIFICACION | G337: ELABORACION PRODUCTO CENTRO DE EMPAQUES MEDELLIN | H337: EPME
A338: EGIPTO - INVENTARIO TRANSITO PRODUCCION 1 y 2 | B338: VTALKA | C338: ALKA1 | D338: PLANTA CLASIFICACION | G338: TAT CALI H2018 | H338: H2018
A339: EGIPTO - INVENTARIO TRANSITO PRODUCCION 3 | B339: VTALKA2 | C339: ALKA2 | D339: PLANTA CLASIFICACION | G339: TAT POPAYAN H2309 | H339: H2309
A340: KIKES - EGIPTO - BLOQUEADO | B340: XALKA | C340: ALKA1 | D340: OTROS | G340: TAT BARRANQUILLA H4019 | H340: H4019
A341: KIKES2 - EGIPTO - BLOQUEADO | B341: XALKA2 | C341: ALKA2 | D341: OTROS | G341: MONTERIA-AUTOSERVICIOS OPERADOR | H341: H4950
A342: TAT MONTERIA H4901 - OM | B342: H4901 | C342: TAT MONTERIA | D342: VEHICULOS | G342: TAT PASTO H6010 | H342: H6010
A343: TAT MONTERIA H4902 - OM | B343: H4902 | C343: TAT MONTERIA | D343: VEHICULOS | G343: PULVERIZADORA | H343: PULV
A344: TAT MONTERIA H4903 - OM | B344: H4903 | C344: TAT MONTERIA | D344: VEHICULOS | G344: ROTURA DE TRANSPORTE - PEREIRA OPERADOR | H344: RT36
A345: TAT MONTERIA H4904 - OM | B345: H4904 | C345: TAT MONTERIA | D345: VEHICULOS | G345: ROTURA DE TRANSPORTE - MONTERIA OPERADOR | H345: RT49
A346: TAT MONTERIA H4905 - OM | B346: H4905 | C346: TAT MONTERIA | D346: VEHICULOS | G346: ROTURA TRANSPORTE CENTRO DE EMPAQUES BOGOTA | H346: RTBO
A347: TAT MONTERIA H4906 - OM | B347: H4906 | C347: TAT MONTERIA | D347: VEHICULOS | G347: ROTURA TRANSPORTE LANZA | H347: RTKI
B348: OPERADOR MONTERIA | C348: TAT MONTERIA | G348: TAT BOGOTA SIBERIA - BLOQUEADO | H348: XT59
A349: TAT MONTERIA - INVENTARIO TRANSITO | B349: VT49 | C349: TAT MONTERIA | D349: TRANSITO
A350: TAT CENTRO MEDELLIN | B350: ME | C350: TAT CE MEDELLIN | D350: BODEGA | G350: BODEGA TRANSITO HUEVO ROTO PARA PULVERIZADO | H350: VTPULV
A351: TAT CE MEDELLIN - INVENTARIO TRANSITO | B351: VTME | C351: TAT CE MEDELLIN | D351: TRANSITO
B352: CE MEDELLIN | C352: TAT CE MEDELLIN | D352: BODEGA
A353: TAT CALI - H2018 | B353: H2018 | C353: TAT CALI | D353: VEHICULOS
A354: TAT POPAYAN - H2309 | B354: H2309 | C354: TAT POPAYAN | D354: VEHICULOS
A355: TAT BARRANQUILLA - H4019 | B355: H4019 | C355: TAT BARRANQUILLA | D355: VEHICULOS
A356: TAT MONTERIA - H4950 | B356: H4950 | C356: TAT MONTERIA | D356: VEHICULOS
A357: TAT PASTO - H6010 | B357: H6010 | C357: TAT PASTO | D357: VEHICULOS
B358: BOGOTA | C358: TAT BOGOTA MONTEVIDEO
A359: TAT CALI - H2011 | B359: H2011 | C359: TAT CALI | D359: VEHICULOS
A360: TAT CARTAGENA - H4110 | B360: H4110 | C360: TAT CARTAGENA | D360: VEHICULOS
...

Sheet Hoja1
A1: id_bodega | C1: DESTINO | D1: id_bodega | E1: DESTINO | F1: GRUPO
A2: 4 | C2: KIKES - EGIPTO | D2: ALKA | E2: ALKA1 | F2: PLANTA CLASIFICACION
A3: 7 | C3: KIKES2 - EGIPTO | D3: ALKA2 | E3: ALKA2 | F3: PLANTA CLASIFICACION
A4: AL04 | C4: BODEGA INTEGRADO JP | D4: AT1 | E4: INTEGRADO JP | F4: PLANTA CLASIFICACION
A5: AL12 | C5: BELLAVISTA | D5: BE | E5: BELLAVISTA | F5: PLANTA CLASIFICACION
A6: ALEM | C6: BARRANQUILLA CLASIFICACION | D6: BQ | E6: TAT CE BARRANQUILLA | F6: BODEGA
A7: EC | C7: CLASIFICADORA LANZA | D7: CLKI | E7: LANZA | F7: HUEVO SIN CLASIFICAR
A8: ECCA | C8: ELABORACION DE PRODUCTOS - ALKA | D8: EPALKA | E8: ALKA1 | F8: PLANTA CLASIFICACION
A9: EMBQ | C9: ELABORACION DE PRODUCTO BARRANQUILLA CLASIFICACION | D9: EPBQ | E9: TAT CE BARRANQUILLA | F9: BODEGA
A10: EQ | C10: ELABORACION DE PRODUCTOS - ALKA2 | D10: EPALKA2 | E10: ALKA2 | F10: PLANTA CLASIFICACION
A11: EQZF | C11: ELABORACION DE PRODUCTOS - KI | D11: EPKI | E11: LANZA | F11: PLANTA CLASIFICACION
A12: GA04 | C12: ELABORACION DE PRODUCTOS - PALMAS | D12: EPPALM | E12: PALMAS | F12: PLANTA CLASIFICACION
A13: GC02-05 | C13: ELABORACION DE PRODUCTOS - BELLAVISTA | D13: EPBE | E13: BELLAVISTA | F13: PLANTA CLASIFICACION
A14: GP25-1 | C14: TAT BUCARAMANGA - FOOD SERVICE | D14: FS1 | E14: TAT BUCARAMANGA | F14: VEHICULOS
A15: GV25 | C15: TAT MEDELLIN - FOOD SERVICE | D15: FS3 | E15: TAT MEDELLIN | F15: VEHICULOS
... A24: VTPULV | C24: TAT BUCARAMANGA H1005 | D24: H1005 | E24: TAT BUCARAMANGA | F24: VEHICULOS
A25: 1 | C25: TAT BUCARAMANGA H1006 | D25: H1006 | E25: TAT BUCARAMANGA | F25: VEHICULOS
A26: 01BE | C26: TAT BUCARAMANGA H1007 | D26: H1007 | E26: TAT BUCARAMANGA | F26: VEHICULOS
A27: 01IN | C27: TAT BUCARAMANGA H1008 | D27: H1008 | E27: TAT BUCARAMANGA | F27: VEHICULOS
A28: 01LZ | C28: TAT BUCARAMANGA H1009 | D28: H1009 | E28: TAT BUCARAMANGA | F28: VEHICULOS
A29: 01PA | C29: TAT BUCARAMANGA H1010 | D29: H1010 | E29: TAT BUCARAMANGA | F29: VEHICULOS
A30: 02BE | C30: TAT BUCARAMANGA H1011 | D30: H1011 | E30: TAT BUCARAMANGA | F30: VEHICULOS
A31: 03BE | C31: TAT BUCARAMANGA H1012 | D31: H1012 | E31: TAT BUCARAMANGA | F31: VEHICULOS
A32: 03BEPA | C32: TAT BUCARAMANGA H1013 | D32: H1013 | E32: TAT BUCARAMANGA | F32: VEHICULOS
A33: 11 | C33: TAT BUCARAMANGA H1014 | D33: H1014 | E33: TAT BUCARAMANGA | F33: VEHICULOS
A34: AL01 | C34: TAT BUCARAMANGA H1015 | D34: H1015 | E34: TAT BUCARAMANGA | F34: VEHICULOS
A35: AL02 | C35: TAT BUCARAMANGA H1016 | D35: H1016 | E35: TAT BUCARAMANGA | F35: VEHICULOS
A36: AL07 | C36: TAT BUCARAMANGA H1017 | D36: H1017 | E36: TAT BUCARAMANGA | F36: VEHICULOS
A37: AL09 | C37: TAT H1050 - AUTOSERVICIOS | D37: H1050 | E37: TAT BUCARAMANGA | F37: VEHICULOS
A38: AL09MS | C38: TAT CALI H2001 | D38: H2001 | E38: TAT CALI | F38: VEHICULOS
A39: AL11 | C39: TAT CALI H2002 | D39: H2002 | E39: TAT CALI | F39: VEHICULOS
A40: AL12PA | C40: TAT CALI H2003 | D40: H2003 | E40: TAT CALI | F40: VEHICULOS
A41: ALF01 | C41: TAT CALI H2005 | D41: H2005 | E41: TAT CALI | F41: VEHICULOS
A42: GA01 | C42: TAT CALI H2006 | D42: H2006 | E42: TAT CALI | F42: VEHICULOS
A43: GA01PA | C43: TAT CALI H2008 | D43: H2008 | E43: TAT CALI | F43: VEHICULOS
A44: GA07 | C44: TAT CALI H2009 | D44: H2009 | E44: TAT CALI | F44: VEHICULOS
A45: PL01 | C45: TAT CALI H2010 | D45: H2010 | E45: TAT CALI | F45: VEHICULOS
... A56: RTME | C56: TAT POPAYAN H2301 | D56: H2301 | E56: TAT POPAYAN | F56: VEHICULOS
C57: TAT POPAYAN H2302 | D57: H2302 | E57: TAT POPAYAN | F57: VEHICULOS
C58: TAT POPAYAN H2303 | D58: H2303 | E58: TAT POPAYAN | F58: VEHICULOS
C59: TAT POPAYAN H2304 | D59: H2304 | E59: TAT POPAYAN | F59: VEHICULOS
C60: TAT POPAYAN H2305 | D60: H2305 | E60: TAT POPAYAN | F60: VEHICULOS
C61: TAT POPAYAN H2306 | D61: H2306 | E61: TAT POPAYAN | F61: VEHICULOS
C62: TAT POPAYAN H2307 | D62: H2307 | E62: TAT POPAYAN | F62: VEHICULOS
C63: TAT POPAYAN H2308 | D63: H2308 | E63: TAT POPAYAN | F63: VEHICULOS
C64: TAT POPAYAN H2312 | D64: H2312 | E64: TAT POPAYAN | F64: VEHICULOS
C65: TAT POPAYAN H2313 | D65: H2313 | E65: TAT POPAYAN | F65: VEHICULOS
C66: TAT POPAYAN H2314 | D66: H2314 | E66: TAT POPAYAN | F66: VEHICULOS
C67: TAT MEDELLIN H3005 | D67: H3005 | E67: TAT MEDELLIN | F67: VEHICULOS
C68: TAT MEDELLIN H3010 | D68: H3010 | E68: TAT MEDELLIN | F68: VEHICULOS
... C273: TATBOGOTA SIBERIA ROTURAS | D273: H5900 | E273: TAT BOGOTA SIBERIA | F273: OTROS
D274: Barranquilla | E274: TAT BARRANQUILLA
D275: BOGOTA | E275: TAT BOGOTA MONTEVIDEO
C276: BOGOTA MONTEVIDEO | D276: BOGOTA | E276: TAT BOGOTA MONTEVIDEO
D277: Alka1 | E277: ALKA1
D278: BOGOTA | E278: TAT BOGOTA MONTEVIDEO
D279: Bucaramanga | E279: TAT BUCARAMANGA
D280: Alka2 | E280: ALKA2
D281: Cali | E281: TAT CALI
D282: Cartagena | E282: TAT CARTAGENA | F282: OTROS
D283: BE | E283: BE
D284: Cucuta | E284: TAT CUCUTA
D285: Medellin | E285: TAT MEDELLIN
D286: Monteria | E286: TAT MONTERIA
D287: Lanza | E287: LANZA
D288: Pasto | E288: TAT PASTO
D289: Popayan | E289: TAT POPAYAN
D290: Santa Marta | E290: TAT SANTA MARTA | F290: OTROS
D291: Palmas | E291: PALMAS
D292: Valledupar | E292: TAT VALLEDUPAR
D293: BOGOTA | E293: TAT BOGOTA MONTEVIDEO
C294: TAT H3050 - AUTOSERVICIOS | D294: H3050 | E294: TAT MEDELLIN | F294: VEHICULOS
C295: TAT CARTAGENA H4140 - ESPECIAL | D295: H4140 | E295: TAT CARTAGENA | F295: VEHICULOS
C296: TAT SANTAMARTA - INVENTARIO TRANSITO | D296: VT42 | E296: TAT SANTA MARTA | F296: TRANSITO
C297: TAT PASTO - INVENTARIO TRANSITO | D297: VT6 | E297: TAT PASTO | F297: TRANSITO
C298: BODEGA BELLAVISTA - INVENTARIO TRANSITO | D298: VTBE | E298: BELLAVISTA | F298: TRANSITO
C299: BODEGA DE CONSERVACION Y DESPACHO PUERTO TEJADA | D299: GC25 | E299: 0 | F299: BODEGA
C300: TAT CALI H2025 | D300: H2025 | E300: TAT CALI | F300: VEHICULOS
C301: TAT MEDELLIN - GRANDES SUPERFICIES | D301: H3060 | E301: TAT MEDELLIN | F301: VEHICULOS
C302: TAT PEREIRA H3507 | D302: H3507 | E302: TAT PEREIRA | F302: VEHICULOS
C303: TAT SANTAMARTA H4240 - ESPECIAL | D303: H4240 | E303: TAT SANTA MARTA | F303: VEHICULOS
D304: BOGOTA | E304: TAT BOGOTA MONTEVIDEO
D305: STA MARTA | E305: TAT SANTA MARTA | F305: OTROS
C306: TAT BARRANQUILLA - INVENTARIO TRANSITO | D306: VT4 | E306: TAT BARRANQUILLA | F306: TRANSITO
C307: PRODUCTO POR FACTURAR | D307: FS1PF | E307: TAT BUCARAMANGA
C308: TAT CALI - FOOD SERVICE | D308: FS2 | E308: TAT CALI | F308: VEHICULOS
C309: BELLAVISTA - BLOQUEADO | D309: XBE | E309: BELLAVISTA | F309: OTROS
C310: BODEGA KIKES - BLOQUEADO | D310: XKI | E310: LANZA | F310: OTROS
C311: TAT BARRANQUILLA H4040 - ESPECIAL | D311: H4040 | E311: TAT BARRANQUILLA | F311: VEHICULOS
C312: TAT CALI H2024 | D312: H2024 | E312: TAT CALI | F312: VEHICULOS
C313: TAT CALI H2007 | D313: H2007 | E313: TAT CALI | F313: VEHICULOS
C314: TAT MEDELLIN H3012 | D314: H3012 | E314: TAT MEDELLIN | F314: VEHICULOS
C315: TAT MEDELLIN H3040 - ESPECIAL | D315: H3040 | E315: TAT MEDELLIN | F315: VEHICULOS
C316: TAT PASTO H6040 - ESPECIAL | D316: H6040 | E316: TAT PASTO | F316: VEHICULOS
C317: TAT CARTAGENA H4109 | D317: H4109 | E317: TAT CARTAGENA | F317: VEHICULOS
C318: TAT SANTAMARTA H4209 | D318: H4209 | E318: TAT SANTA MARTA | F318: VEHICULOS
C319: TAT MEDELLIN H3030 | D319: H3030 | E319: TAT MEDELLIN | F319: VEHICULOS
D320: Pasto Bodega | E320: TAT PASTO | F320: VEHICULOS
D321: OplPereira | E321: TAT PEREIRA | F321: VEHICULOS
C322: TAT PEREIRA - INVENTARIO TRANSITO | D322: VT36 | E322: TAT PEREIRA | F322: TRANSITO
...

Sheet DT HUEVO
A1: CODIGO | B1: NOMBRE | C1: TIPO | D1: TIPO2 | E1: TIPO3 | F1: CANAL | H1: PLANTA | I1: ZONA | J1: P | K1: ZONA
A2: 90 | B2: HUEVO ROJO SIN CLASIFICAR GRANJAS | C2: HUEVO SIN CLASIFICAR | D2: HUEVO SIN CLASIFICAR | E2: HUEVO SIN CLASIFICAR | F2: SIN CL | H2: ALKA1 | I2: - | J2: CALOTO | K2: PLANTAS
A3: 91 | B3: HUEVO ROJO SIN CLASIFICAR JAULA EGIPTO PROD1 | C3: HUEVO SIN CLASIFICAR | D3: HUEVO SIN CLASIFICAR | E3: HUEVO SIN CLASIFICAR | F3: SIN CL | H3: ALKA2 | I3: - | J3: CALOTO | K3: PLANTAS
A4: 92 | B4: HUEVO ROJO SIN CLASIFICAR BELLAVISTA | C4: HUEVO SIN CLASIFICAR | D4: HUEVO SIN CLASIFICAR | E4: HUEVO SIN CLASIFICAR | F4: SIN CL | H4: PALMAS | I4: - | J4: CALOTO | K4: PLANTAS
A5: 93 | B5: HUEVO ROJO SIN CLASIFICAR JAULA EGIPTO PROD2 | C5: HUEVO SIN CLASIFICAR | D5: HUEVO SIN CLASIFICAR | E5: HUEVO SIN CLASIFICAR | F5: SIN CL | H5: BELLAVISTA | I5: - | J5: SANTANDER | K5: PLANTAS
A6: 94 | B6: HUEVO ROJO SIN CLASIFICAR DE LA GRANJA PALMAS | C6: HUEVO SIN CLASIFICAR | D6: HUEVO SIN CLASIFICAR | E6: HUEVO SIN CLASIFICAR | F6: SIN CL | H6: LANZA | I6: - | J6: SANTANDER | K6: PLANTAS
A7: 100 | B7: HUEVO SIN CLASIFICAR ROJO | C7: HUEVO SIN CLASIFICAR | D7: HUEVO SIN CLASIFICAR | E7: HUEVO SIN CLASIFICAR | F7: SIN CL | H7: EXPENDIO | I7: - | J7: - | K7: -
A8: 101 | B8: HUEVO YUMBO ROJO | C8: YUMBO | D8: GRIS SUELTO | F8: MAY | H8: TAT BUCARAMANGA | I8: COSTA | J8: SANTANDER | K8: CENTRO ORIENTE
A9: 102 | B9: HUEVO A.A.A. ROJO | C9: AAA | D9: GRIS SUELTO | F9: MAY | H9: TAT CALI | I9: OCCIDENTE | J9: CALOTO | K9: OCCIDENTE
A10: 103 | B10: HUEVO A.A. ROJO | C10: AA | D10: GRIS SUELTO | F10: MAY | H10: TAT MEDELLIN | I10: OCCIDENTE | J10: CALOTO | K10: OCCIDENTE
A11: 104 | B11: HUEVO A. ROJO | C11: A | D11: GRIS SUELTO | F11: MAY | H11: TAT BARRANQUILLA | I11: COSTA | J11: CALOTO | K11: COSTA ORIENTE
A12: 105 | B12: HUEVO B. ROJO | C12: B | D12: GRIS SUELTO | F12: MAY | H12: TAT CARTAGENA | I12: COSTA | J12: CALOTO | K12: COSTA ORIENTE
A13: 106 | B13: HUEVO C. ROJO | C13: C | D13: SEGUNDA | F13: SEGUNDA | H13: TAT BOGOTA MONTEVIDEO | I13: CENTRO ORIENTE | J13: SANTANDER | K13: CENTRO ORIENTE
A14: 130 | B14: HUEVO PICADO ROJO | C14: SEGUNDA | D14: SEGUNDA | E14: PICADO | F14: SEGUNDA | H14: TAT POPAYAN | I14: OCCIDENTE | J14: CALOTO | K14: OCCIDENTE
A15: 300 | B15: HUEVO SIN CLASIFICAR COMERCIAL | C15: HUEVO SIN CLASIFICAR | D15: HUEVO SIN CLASIFICAR | E15: HUEVO SIN CLASIFICAR | F15: SIN CL | H15: TAT PEREIRA | I15: OCCIDENTE | J15: CALOTO | K15: OCCIDENTE
A16: 901 | B16: HUEVO ROTO | C16: HUEVO SIN CLASIFICAR | D16: HUEVO SIN CLASIFICAR | E16: HUEVO SIN CLASIFICAR | F16: SIN CL | H16: TAT STA MARTA | I16: COSTA | J16: SANTANDER | K16: COSTA ORIENTE
A17: 902 | B17: DESECHOS | C17: SEGUNDA | D17: SEGUNDA | F17: SEGUNDA | H17: TAT VALLEDUPAR | I17: COSTA | J17: SANTANDER | K17: COSTA ORIENTE
A18: 1042 | B18: HUEVO A2 ROJO | C18: A | H18: TAT BOGOTA SIBERIA | I18: CENTRO ORIENTE | J18: CALOTO | K18: CENTRO ORIENTE
A19: 10101 | B19: HUEVO YUMBO X20 CARTON GRIS | C19: YUMBO | D19: GRIS SUELTO | F19: MAY | H19: TAT VILLAVICENCIO | I19: CENTRO ORIENTE | J19: SANTANDER | K19: CENTRO ORIENTE
A20: 10102 | B20: HUEVO YUMBO X20 CARTON VERDE | C20: YUMBO | D20: VERDE | F20: TAT | H20: TAT PASTO | I20: OCCIDENTE | J20: CALOTO | K20: OCCIDENTE
A21: 10103 | B21: HUEVO YUMBO X20 CARTON VERDE AMARRADO | C21: YUMBO | D21: EMPACADOS | F21: AU/FS/GS | H21: TAT CUCUTA | I21: COSTA | J21: SANTANDER | K21: CENTRO ORIENTE
A22: 10104 | B22: HUEVO YUMBO X20 FS CARTON VERDE | C22: YUMBO | D22: EMPACADOS | H22: TAT MONTERIA | I22: COSTA | J22: SANTANDER | K22: COSTA ORIENTE
A23: 10106 | B23: HUEVO YUMBO X 20 BANDEJA VERDE CON ETIQUETA | C23: YUMBO | D23: VERDE | F23: TAT | H23: TAT BOGOTA SIBERIA | I23: CENTRO ORIENTE | J23: CALOTO | K23: CENTRO ORIENTE
A24: 10201 | B24: HUEVO AAA X30 CARTON GRIS | C24: AAA | D24: GRIS SUELTO | F24: MAY | H24: EXPENDIO - EGIPTO | I24: - | J24: - | K24: -
A25: 10202 | B25: HUEVO AAA X30 CARTON VERDE | C25: AAA | D25: VERDE | F25: TAT | H25: CENTRO DE EMPAQUES | I25: COSTA | J25: - | K25: COSTA ORIENTE
A26: 10203 | B26: HUEVO AAA X30 CARTON VERDE AMARRADO | C26: AAA | D26: EMPACADOS | H26: HUEVO SIN CLASIFICAR | I26: - | J26: - | K26: -
A27: 10204 | B27: HUEVO AAA X30 FS CARTON VERDE | C27: AAA | D27: FS | H27: BODEGA MAYORISTA | I27: NA | J27: NA | K27: NA
A28: 10205 | B28: HUEVO AAA X30 FS CARTON VERDE AMARRADO | C28: AAA | D28: FS | H28: FOODSERVICE NACIONAL | I28: NA | J28: NA | K28: NA
A29: 10213 | B29: HUEVO AAA X 45 BANDEJA VERDE AMARRADO | C29: AAA | D29: VERDE | F29: TAT | H29: TAT BOGOTA MONTEVIDEO | I29: CENTRO ORIENTE | J29: SANTANDER | K29: CENTRO ORIENTE
A30: 10216 | B30: HUEVO AAA X 30 CARTON VERDE CON ETIQUETA | C30: AAA | D30: ETIQUETA | F30: AU/FS/GS | H30: BODEGA ZF | I30: ZF | J30: ZF | K30: ZF
A31: 10268 | B31: HUEVO AAA X 288 BAND GRIS CAJA DOCENERA EXTRA | C31: AAA | D31: EMPACADOS | F31: HD | H31: INTEGRADO JP | I31: - | J31: - | K31: -
A32: 10269 | B32: HUEVO AAA X 300 BANDEJA VERDE CAJA AMARRADO | C32: AAA | D32: EMPACADOS | H32: BODEGA GAITAN | I32: - | J32: SANTANDER
A33: 10278 | B33: HUEVO AAA X 30 BANDEJA VERDE CAJA X 240 AMARRADO | C33: AAA | D33: EMPACADOS | H33: TAT SANTA MARTA | I33: COSTA | J33: SANTANDER | K33: COSTA ORIENTE
A34: 10289 | B34: HUEVO AAA X 360 FS CARTON VERDE CAJA | C34: AAA | D34: EMPACADOS | H34: GRANJAS DE PISO | I34: - | J34: - | K34: -
A35: 10301 | B35: HUEVO AA X30 CARTON GRIS | C35: AA | D35: GRIS SUELTO | F35: MAY | H35: TAT Barranquilla | I35: COSTA | J35: CALOTO | K35: COSTA ORIENTE
A36: 10302 | B36: HUEVO AA X30 CARTON VERDE | C36: AA | D36: VERDE | F36: TAT | H36: TAT BOGOTA MONTEVIDEO | I36: CENTRO ORIENTE | J36: SANTANDER | K36: CENTRO ORIENTE
A37: 10303 | B37: HUEVO AA X30 CARTON VERDE AMARRADO | C37: AA | D37: EMPACADOS | H37: TAT Bogota Montevideo | I37: CENTRO ORIENTE | J37: CALOTO | K37: CENTRO ORIENTE
A38: 10304 | B38: HUEVO AA X30 FS CARTON VERDE | C38: AA | D38: FS | H38: Alka1 | I38: - | J38: CALOTO | K38: PLANTAS
A39: 10305 | B39: HUEVO AA X30 FS CARTON VERDE AMARRADO | C39: AA | D39: FS | H39: TAT BOGOTA SIBERIA | I39: CENTRO ORIENTE | J39: CALOTO | K39: CENTRO ORIENTE
A40: 10306 | B40: HUEVO AA X12 CARTON VERDE | C40: AA | D40: VERDE | F40: TAT | H40: TAT Bucaramanga | I40: CENTRO ORIENTE | J40: SANTANDER | K40: CENTRO ORIENTE
A41: 10307 | B41: HUEVO AA X15 CARTON VERDE AMARRADO | C41: AA | D41: EMPACADOS | H41: ALKA2 | I41: - | J41: CALOTO | K41: PLANTAS
A42: 10309 | B42: HUEVO AA X 15 FS CARTON VERDE AMARRADO | C42: AA | D42: FS | H42: TAT Cali | I42: OCCIDENTE | J42: CALOTO | K42: OCCIDENTE
A43: 10311 | B43: HUEVO AA X 30 CARTON GRIS AMARRADO | C43: AA | D43: EMPACADOS | H43: TAT Cartagena | I43: COSTA | J43: CALOTO | K43: COSTA ORIENTE
A44: 10312 | B44: HUEVO AA X 30 CARTON GRIS AMARRADO - MAKRO | C44: AA | D44: EMPACADOS | H44: BELLAVISTA | I44: - | J44: SANTANDER | K44: PLANTAS
A45: 10314 | B45: HUEVO AA X 30 CARTON GRIS BA | C45: AA | D45: EMPACADOS | H45: TAT Cucuta | I45: CENTRO ORIENTE | J45: SANTANDER | K45: CENTRO ORIENTE
A46: 10316 | B46: HUEVO AA X 30 CARTON VERDE CON ETIQUETA | C46: AA | D46: ETIQUETA | F46: AU/FS/GS | H46: TAT Medellin | I46: OCCIDENTE | J46: CALOTO | K46: OCCIDENTE
A47: 10317 | B47: HUEVO AA X 30 CARTON VERDE AMARRADO CON BANDEJA | C47: AA | D47: EMPACADOS | H47: TAT Monteria | I47: COSTA | J47: SANTANDER | K47: COSTA ORIENTE
A48: 10318 | B48: HUEVO AAX30 CARTÓN VERDE MICROBIOLOGICO CON ETIQUETA | C48: AA | D48: EMPACADOS | H48: Lanza | I48: - | J48: SANTANDER | K48: PLANTAS
A49: 10324 | B49: HUEVO AA X 30 CARTÓN VERDE AMARRADO CON BANDEJA MICROBIOLÓGI | C49: AA | D49: EMPACADOS | H49: TAT Pasto | I49: OCCIDENTE | J49: CALOTO | K49: OCCIDENTE
A50: 10348 | B50: HUEVO AA ROJO X 288 CARTON GRIS CAJA-EN DOCENERA- MERCADERIA | C50: AA | D50: EMPACADOS | F50: HD | H50: TAT Pereira | I50: OCCIDENTE | J50: CALOTO | K50: OCCIDENTE
A51: 10357 | B51: HUEVO AA ROJO X 240 CARTON GRIS CAJA AMARRADO | C51: AA | D51: EMPACADOS | H51: TAT Popayan | I51: OCCIDENTE | J51: CALOTO | K51: OCCIDENTE
A52: 10358 | B52: HUEVO AA ROJO X 288 CARTON GRIS CAJA-EN DOCENERA-SOL NACIENT | C52: AA | D52: EMPACADOS | F52: HD | H52: TAT Santa Marta | I52: COSTA | J52: SANTANDER | K52: COSTA ORIENTE
A53: 10367 | B53: HUEVO AA X12 FS CARTON VERDE | C53: AA | D53: FS | H53: Palmas | I53: - | J53: CALOTO | K53: PLANTAS
A54: 10369 | B54: HUEVO AA X 300 BANDEJA VERDE CAJA AMARRADO | C54: AA | D54: EMPACADOS | H54: TAT Valledupar | I54: COSTA | J54: SANTANDER | K54: COSTA ORIENTE
A55: 10371 | B55: HUEVO AA X30 CARTON VERDE CAJA | C55: AA | D55: EMPACADOS | H55: TAT Villavicencio | I55: CENTRO ORIENTE | J55: SANTANDER | K55: CENTRO ORIENTE
A56: 10372 | B56: HUEVO AA X60 CARTON VERDE CAJA | C56: AA | D56: EMPACADOS | H56: TAT BOGOTA MONTEVIDEO | I56: CENTRO ORIENTE | J56: CALOTO | K56: CENTRO ORIENTE
A57: 10380 | B57: HUEVO AA X360 CARTON VERDE CAJA | C57: AA | D57: EMPACADOS | H57: TAT SANTA MARTA | I57: COSTA | J57: SANTANDER | K57: COSTA ORIENTE
A58: 10385 | B58: HUEVO AA X 30 CARTON VERDE FS X 150 | C58: AA | D58: FS | H58: BOGOTA MONTEVIDEO | I58: CENTRO ORIENTE | J58: SANTANDER | K58: CENTRO ORIENTE
A59: 10388 | B59: HUEVO AA X 30 FS CARTON VERDE CAJA X 300 AMARRADO | C59: AA | D59: FS | H59: BOGOTA MONTEVIDEO | I59: CENTRO ORIENTE | J59: SANTANDER | K59: CENTRO ORIENTE
A60: 10389 | B60: HUEVO AA X 360 FS CARTON VERDE CAJA | C60: AA | D60: FS | H60: CE BOGOTA | I60: CENTRO ORIENTE | J60: CALOTO | K60: CENTRO EMPAQUES
A61: 10401 | B61: HUEVO A X30 CARTON GRIS | C61: A | D61: GRIS SUELTO | F61: MAY | H61: CENTRO DE EMPAQUES BOGOTA | I61: CENTRO DE EMPAQUES | J61: CALOTO | K61: CENTRO EMPAQUES
A62: 10402 | B62: HUEVO A X30 CARTON VERDE | C62: A | D62: VERDE | F62: TAT | H62: OL. PEREIRA | I62: OCCIDENTE | J62: CALOTO | K62: OCCIDENTE
A63: 10403 | B63: HUEVO A X30 CARTON VERDE AMARRADO | C63: A | D63: EMPACADOS | H63: BOGOTA SIBERIA | I63: CENTRO ORIENTE | J63: CALOTO | K63: CENTRO ORIENTE
A64: 10404 | B64: HUEVO A X30 FS CARTON VERDE | C64: A | D64: FS | H64: TAT BOGOTA MONTEVIDEO | I64: CENTRO ORIENTE | J64: SANTANDER | K64: CENTRO ORIENTE
A65: 10405 | B65: HUEVO A X30 FS CARTON VERDE AMARRADO | C65: A | D65: FS | H65: CE BOGOTA | I65: CENTRO DE EMPAQUES | J65: SANTANDER | K65: CENTRO EMPAQUES
A66: 10406 | B66: HUEVO A X12 CARTON VERDE | C66: A | D66: VERDE | F66: TAT | H66: OL. MONTERIA | I66: COSTA | J66: SANTANDER | K66: COSTA ORIENTE
A67: 10407 | B67: HUEVO A X15 CARTON VERDE AMARRADO | C67: A | D67: EMPACADOS | H67: CE MEDELLIN | I67: CENTRO DE EMPAQUES | J67: CALOTO | K67: CENTRO EMPAQUES
A68: 10409 | B68: HUEVO A X 15 FS CARTON VERDE AMARRADO | C68: A | D68: FS | H68: BOGOTA | I68: CENTRO ORIENTE | J68: CALOTO | K68: CENTRO ORIENTE
A69: 10410 | B69: HUEVO A X 30 CARTON VERDE AMARRADO CON BANDEJA | C69: A | D69: EMPACADOS | H69: BOGOTA | I69: CENTRO ORIENTE | J69: CALOTO | K69: CENTRO ORIENTE
A70: 10411 | B70: HUEVO A X 30 CARTON GRIS AMARRADO- MERCADERIA | C70: A | D70: EMPACADOS | H70: C.E BOGOTA | I70: - | J70: SANTANDER | K70: CENTRO EMPAQUES
A71: 10414 | B71: HUEVO A X 30 CARTON GRIS BA | C71: A | D71: EMPACADOS | H71: TAT CENTRO MEDELLIN | I71: CENTRO DE EMPAQUES | J71: CALOTO | K71: CENTRO EMPAQUES
A72: 10415 | B72: HUEVO A X 4 FS CARTON VERDE | C72: A | D72: EMPACADOS | H72: CE BARRANQUILLA | I72: COSTA ORIENTE | J72: - | K72: CENTRO EMPAQUES
A73: 10416 | B73: HUEVO A X 30 CARTON VERDE CON ETIQUETA | C73: A | D73: ETIQUETA | F73: AU/FS/GS | H73: PLANTA CLASIFICADORA INTEGRADO JP | I73: COSTA
A74: 10417 | B74: HUEVO A X 30 CARTON GRIS AMARRADO SOL NACIENTE BARRANQUILLA | C74: A | D74: EMPACADOS | F74: HD | H74: CLASIFICADORA BELLAVISTA | I74: CENTRO ORIENTE | J74: SANTANDER
A75: 10418 | B75: HUEVO A X30 CARTÓN VERDE MICROBIOLOGICO CON ETIQUETA | C75: A | D75: EMPACADOS | H75: ELABORACION PRODUCTO PLANTA CLASIFICACIÓN BQUILLA
A76: 10419 | B76: HUEVO A X 30 CARTON GRIS AMARRADO SOL NACIENTE | C76: A | D76: EMPACADOS | F76: HD | H76: ELABORACION PRODUCTO PLANTA CLASIFICACIÓN BQUILLA
A77: 10420 | B77: HUEVO A X 30 BAND GRIS AMARRADO SOL NACIENTE SANTANDER | C77: A | D77: EMPACADOS | F77: HD | H77: ELABORACION PRODUCTO CENTRO DE EMPAQUES MEDELLIN | I77: OCCIDENTE | J77: CALOTO | K77: CENTRO EMPAQUES
A78: 10421 | B78: HUEVO A X 30 CARTON GRIS AMARRADO - ALKOSTO | C78: A | D78: EMPACADOS | H78: ELABORACION PRODUCTO CENTRO DE EMPAQUES MEDELLIN | I78: OCCIDENTE | J78: CALOTO | K78: CENTRO EMPAQUES
A79: 10425 | B79: HUEVO A X 30 CART”N VERDE AMARRADO MICROBIOL”GICO | C79: A | D79: EMPACADOS | H79: ELABORACION PRODUCTO CENTRO DE EMPAQUES MEDELLIN | I79: OCCIDENTE | J79: CALOTO | K79: CENTRO EMPAQUES
A80: 10441 | B80: HUEVO A X 30 CARTON VERDE AMARRADO X 150 | C80: A | D80: EMPACADOS | H80: ELABORACION PRODUCTO CENTRO DE EMPAQUES MEDELLIN | I80: OCCIDENTE | J80: CALOTO | K80: CENTRO EMPAQUES
A81: 10447 | B81: HUEVO A X12 BANDEJA GRIS CAJA X 288 PUERTO | C81: A | D81: EMPACADOS | H81: BEES BUCARAMANGA H1080 | I81: CENTRO ORIENTE | J81: SANTANDER | K81: CENTRO ORIENTE
A82: 10457 | B82: HUEVO A ROJO X 240 CARTON GRIS CAJA AMARRADO SOL NACIENTE | C82: A | D82: EMPACADOS | F82: HD | H82: BEES BUCARAMANGA H1080 | I82: CENTRO ORIENTE | J82: SANTANDER | K82: CENTRO ORIENTE
A83: 10460 | B83: HUEVO A X 360 BANDEJA GRIS CAJA | C83: A | D83: EMPACADOS | H83: TAT MEDELLIN H3001 | I83: OCCIDENTE | J83: CALOTO | K83: OCCIDENTE
A84: 10467 | B84: HUEVO A X 12 FS CARTON GRIS CAJA X 288 | C84: A | D84: EMPACADOS | H84: TAT MEDELLIN H3001 | I84: OCCIDENTE | J84: CALOTO | K84: OCCIDENTE
A85: 10469 | B85: HUEVO A X 300 BANDEJA VERDE CAJA AMARRADO | C85: A | D85: EMPACADOS | F85: AU/FS/GS | H85: TAT MEDELLIN H3001 | I85: OCCIDENTE | J85: CALOTO | K85: OCCIDENTE
A86: 10469 | B86: HUEVO A X 300 BANDEJA VERDE CAJA AMARRADO | C86: A | D86: EMPACADOS | F86: AU/FS/GS | H86: TAT MEDELLIN H3001 | I86: OCCIDENTE | J86: CALOTO | K86: OCCIDENTE
A87: 10470 | B87: HUEVO A X 30 BANDEJA VERDE CAJA X 90 MCDONLADS | C87: A | D87: EMPACADOS | H87: TAT MEDELLIN H3001 | I87: OCCIDENTE | J87: CALOTO | K87: OCCIDENTE
A88: 10472 | B88: HUEVO A X60 CARTON VERDE CAJA | C88: A | D88: EMPACADOS | F88: AU/FS/GS | H88: TAT CARTAGENA H4112 | I88: COSTA | J88: CALOTO | K88: COSTA ORIENTE
A89: 10473 | B89: HUEVO A X90 CARTON VERDE CAJA | C89: A | D89: EMPACADOS | H89: TAT CARTAGENA H4112 | I89: COSTA | J89: CALOTO | K89: COSTA ORIENTE
A90: 10477 | B90: HUEVO A X 30 BANDEJA VERDE AMARRADO CAJA X 240 | C90: A | D90: VERDE | F90: TAT | H90: TAT BOGOTA MONTEVIDEO H5001 | I90: CENTRO ORIENTE | J90: CALOTO | K90: CENTRO ORIENTE
A91: 10478 | B91: HUEVO AX 30 BANDEJA VERDE AMARRADO CON BANDEJA CAJA X 240 | C91: A | D91: EMPACADOS | H91: TAT BOGOTA MONTEVIDEO H5001 | I91: CENTRO ORIENTE | J91: CALOTO | K91: CENTRO ORIENTE
A92: 10480 | B92: HUEVO A X360 CARTON VERDE CAJA | C92: A | D92: EMPACADOS | H92: TAT BOGOTA MONTEVIDEO H5001 | I92: CENTRO ORIENTE | J92: CALOTO | K92: CENTRO ORIENTE
A93: 10485 | B93: HUEVO A X 30 CARTON VERDE FS X 150 | C93: A | D93: EMPACADOS | H93: TAT BOGOTA MONTEVIDEO H5001 | I93: CENTRO ORIENTE | J93: CALOTO | K93: CENTRO ORIENTE
A94: 10488 | B94: HUEVO A X 30 FS CARTON VERDE CAJA X 300 AMARRADO | C94: A | D94: FS | H94: TAT BOGOTA MONTEVIDEO H5001 | I94: CENTRO ORIENTE | J94: CALOTO | K94: CENTRO ORIENTE
A95: 10488 | B95: HUEVO A X 30 FS CARTON VERDE CAJA X 300 AMARRADO | C95: A | D95: FS | H95: TAT BOGOTA MONTEVIDEO H5004 | I95: CENTRO ORIENTE | J95: CALOTO | K95: CENTRO ORIENTE
A96: 10489 | B96: HUEVO A X 360 FS CARTON VERDE CAJA | C96: A | D96: FS | H96: TAT BOGOTA MONTEVIDEO H5004 | I96: CENTRO ORIENTE | J96: CALOTO | K96: CENTRO ORIENTE
A97: 10501 | B97: HUEVO B X30 CARTON GRIS | C97: B | D97: GRIS SUELTO | F97: MAY | H97: TAT BOGOTA MONTEVIDEO H5004 | I97: CENTRO ORIENTE | J97: CALOTO | K97: CENTRO ORIENTE
A98: 10511 | B98: HUEVO B X 30 CARTON GRIS AMARRADO | C98: B | D98: EMPACADOS | H98: TAT BOGOTA MONTEVIDEO H5004 | I98: CENTRO ORIENTE | J98: CALOTO | K98: CENTRO ORIENTE
A99: 10512 | B99: HUEVO B X 30 CARTON GRIS AMARRADO BUENASOS | C99: B | D99: EMPACADOS | H99: TAT BOGOTA MONTEVIDEO H5004 | I99: CENTRO ORIENTE | J99: CALOTO | K99: CENTRO ORIENTE
A100: 10515 | B100: HUEVO B X 30 CARTON GRIS AMARRADO ETIQUETA K | C100: B | D100: EMPACADOS | H100: TAT BOGOTA MONTEVIDEO H5005 | I100: CENTRO ORIENTE | J100: CALOTO | K100: CENTRO ORIENTE
...

Sheet Hoja2
A1: id_bodega
A24: EC
A25: ECCA
A26: EMBQ
A33: GC02
A34: GC02-05
A35: GP25-1
A36: GV25
A45: SV01
A46: SV02
A47: SV1CAL
A48: VT01BE

Sheet inv
A1: articulo | B1: descripcion_articulo | C1: id_unidad | D1: cantidad | E1: por_dsto | F1: ind_iva_venta | G1: iva_ventas | H1: por_iva | I1: precio_unitario | J1: codigo_linea | K1: descripcion_linea | L1: costo_promedio | M1: fecha | N1: codigo_plu | O1: descripcion | P1: cod_barras1 | Q1: id_bodega | R1: num_piezas | S1: id_item_bodega | T1: id_item_bodega2 | U1: GRUPO | V1: TIPO DE HUEVO | W1: TIPO DE HUEVO 2 | X1: ZONA | Y1: P | Z1: MAY | AA1: GRUPO 2 | AB1: CANAL
A2: 10601 | B2: HUEVO C X30 CARTON GRIS | C2: UN | D2: 9212 | E2: 0 | F2: S | G2: IV82 | H2: 0 | I2: 400 | J2: HU | K2: HUEVO COMERCIAL | L2: 130.24 | M2: 46307 | N2: 10601 | O2: KIKES - EGIPTO | P2: 10601 | Q2: ALKA | R2: 0 | T2: =+VLOOKUP(Tabla1[[#This Row],[id_bodega]],'CONVERSION DATOS'!B:D,2,0) -> ALKA1 | U2: =+VLOOKUP(Q2,'CONVERSION DATOS'!B:D,3,0) -> PLANTA CLASIFICACION | V2: =+VLOOKUP($A$1:$A$20894,'DT HUEVO'!$A:$E,3,0) -> C | W2: =+VLOOKUP($A$1:$A$20734,'DT HUEVO'!$A:$E,4,0) -> GRIS SUELTO | X2: =+VLOOKUP(T$1:T$20894,'DT HUEVO'!$H:$K,2,0) -> - | Y2: =+VLOOKUP(T$1:T$20894,'DT HUEVO'!$H:$K,3,0) -> CALOTO | Z2: =+VLOOKUP(A$1:A$20894,'DT HUEVO'!$A:$E,5,0) -> 0 | AA2: =IF(Tabla1[[#This Row],[GRUPO]]="PLANTA CLASIFICACION","BODEGA",IF(Tabla1[[#This Row],[GRUPO]]="BODEGA","BODEGA",Tabla1[[#This Row],[GRUPO]])) -> BODEGA | AB2: =VLOOKUP(Tabla1[[#This Row],[articulo]],'DT HUEVO'!$A:$F,6,0) -> MAY
A3: 72002 | B3: HUEVO SUCIO ZF SIN MARCA X30 BANDEJA GRIS | C3: UN | D3: 3210 | E3: 0 | F3: S | G3: IV82 | H3: 0 | I3: 254 | J3: HU | K3: HUEVO COMERCIAL | L3: 188.68 | M3: 46307 | N3: 72002 | O3: KIKES - EGIPTO | P3: 72002 | Q3: ALKA | R3: 0 | T3: =+VLOOKUP(Tabla1[[#This Row],[id_bodega]],'CONVERSION DATOS'!B:D,2,0) -> ALKA1 | U3: =+VLOOKUP(Q3,'CONVERSION DATOS'!B:D,3,0) -> PLANTA CLASIFICACION | V3: =+VLOOKUP($A$1:$A$21035,'DT HUEVO'!$A:$E,3,0) -> SEGUNDA | W3: =+VLOOKUP($A$1:$A$20875,'DT HUEVO'!$A:$E,4,0) -> SEGUNDA | X3: =+VLOOKUP(T$1:T$21035,'DT HUEVO'!$H:$K,2,0) -> - | Y3: =+VLOOKUP(T$1:T$21035,'DT HUEVO'!$H:$K,3,0) -> CALOTO | Z3: =+VLOOKUP(A$1:A$21035,'DT HUEVO'!$A:$E,5,0) -> SUCIO | AA3: =IF(Tabla1[[#This Row],[GRUPO]]="PLANTA CLASIFICACION","BODEGA",IF(Tabla1[[#This Row],[GRUPO]]="BODEGA","BODEGA",Tabla1[[#This Row],[GRUPO]])) -> BODEGA | AB3: =VLOOKUP(Tabla1[[#This Row],[articulo]],'DT HUEVO'!$A:$F,6,0) -> SEGUNDA
A4: 73001 | B4: HUEVO PICADO ROJO X30 BANDEJA GRIS | C4: UN | D4: 62423 | E4: 0 | F4: S | G4: IV82 | H4: 0 | I4: 145 | J4: HU | K4: HUEVO COMERCIAL | L4: 164.38 | M4: 46307 | N4: 0 | O4: KIKES - EGIPTO | P4: 73001 | Q4: ALKA | R4: 0 | T4: =+VLOOKUP(Tabla1[[#This Row],[id_bodega]],'CONVERSION DATOS'!B:D,2,0) -> ALKA1 | U4: =+VLOOKUP(Q4,'CONVERSION DATOS'!B:D,3,0) -> PLANTA CLASIFICACION | V4: =+VLOOKUP($A$1:$A$21035,'DT HUEVO'!$A:$E,3,0) -> SEGUNDA | W4: =+VLOOKUP($A$1:$A$20875,'DT HUEVO'!$A:$E,4,0) -> SEGUNDA | X4: =+VLOOKUP(T$1:T$21035,'DT HUEVO'!$H:$K,2,0) -> - | Y4: =+VLOOKUP(T$1:T$21035,'DT HUEVO'!$H:$K,3,0) -> CALOTO | Z4: =+VLOOKUP(A$1:A$21035,'DT HUEVO'!$A:$E,5,0) -> PICADO | AA4: =IF(Tabla1[[#This Row],[GRUPO]]="PLANTA CLASIFICACION","BODEGA",IF(Tabla1[[#This Row],[GRUPO]]="BODEGA","BODEGA",Tabla1[[#This Row],[GRUPO]])) -> BODEGA | AB4: =VLOOKUP(Tabla1[[#This Row],[articulo]],'DT HUEVO'!$A:$F,6,0) -> SEGUNDA
A5: 75201 | B5: HUEVO AAA X 30 CARTON GRIS LZ | C5: UN | D5: 23645 | E5: 0 | F5: S | G5: IV82 | H5: 0 | I5: 310 | J5: HU | K5: HUEVO COMERCIAL | L5: 261.72 | M5: 46307 | N5: 75201 | O5: KIKES - EGIPTO | P5: 75201 | Q5: ALKA | R5: 0 | T5: =+VLOOKUP(Tabla1[[#This Row],[id_bodega]],'CONVERSION DATOS'!B:D,2,0) -> ALKA1 | U5: =+VLOOKUP(Q5,'CONVERSION DATOS'!B:D,3,0) -> PLANTA CLASIFICACION | V5: =+VLOOKUP($A$1:$A$21035,'DT HUEVO'!$A:$E,3,0) -> AAA | W5: =+VLOOKUP($A$1:$A$20875,'DT HUEVO'!$A:$E,4,0) -> GRIS SUELTO | X5: =+VLOOKUP(T$1:T$21035,'DT HUEVO'!$H:$K,2,0) -> - | Y5: =+VLOOKUP(T$1:T$21035,'DT HUEVO'!$H:$K,3,0) -> CALOTO | Z5: =+VLOOKUP(A$1:A$21035,'DT HUEVO'!$A:$E,5,0) -> 0 | AA5: =IF(Tabla1[[#This Row],[GRUPO]]="PLANTA CLASIFICACION","BODEGA",IF(Tabla1[[#This Row],[GRUPO]]="BODEGA","BODEGA",Tabla1[[#This Row],[GRUPO]])) -> BODEGA | AB5: =VLOOKUP(Tabla1[[#This Row],[articulo]],'DT HUEVO'!$A:$F,6,0) -> MAY
A6: 75301 | B6: HUEVO AA X 30 CARTON GRIS LZ | C6: UN | D6: 15450 | E6: 0 | F6: S | G6: IV82 | H6: 0 | I6: 250 | J6: HU | K6: HUEVO COMERCIAL | L6: 224.76 | M6: 46307 | N6: 75301 | O6: KIKES - EGIPTO | P6: 75301 | Q6: ALKA | R6: 0 | T6: =+VLOOKUP(Tabla1[[#This Row],[id_bodega]],'CONVERSION DATOS'!B:D,2,0) -> ALKA1 | U6: =+VLOOKUP(Q6,'CONVERSION DATOS'!B:D,3,0) -> PLANTA CLASIFICACION | V6: =+VLOOKUP($A$1:$A$21097,'DT HUEVO'!$A:$E,3,0) -> AA | W6: =+VLOOKUP($A$1:$A$20937,'DT HUEVO'!$A:$E,4,0) -> GRIS SUELTO | X6: =+VLOOKUP(T$1:T$21097,'DT HUEVO'!$H:$K,2,0) -> - | Y6: =+VLOOKUP(T$1:T$21097,'DT HUEVO'!$H:$K,3,0) -> CALOTO | Z6: =+VLOOKUP(A$1:A$21097,'DT HUEVO'!$A:$E,5,0) -> 0 | AA6: =IF(Tabla1[[#This Row],[GRUPO]]="PLANTA CLASIFICACION","BODEGA",IF(Tabla1[[#This Row],[GRUPO]]="BODEGA","BODEGA",Tabla1[[#This Row],[GRUPO]])) -> BODEGA | AB6: =VLOOKUP(Tabla1[[#This Row],[articulo]],'DT HUEVO'!$A:$F,6,0) -> MAY
A7: 75401 | B7: HUEVO A X 30 CARTON GRIS LZ | C7: UN | D7: 9723 | E7: 0 | F7: S | G7: IV82 | H7: 0 | I7: 220 | J7: HU | K7: HUEVO COMERCIAL | L7: 268.84 | M7: 46307 | N7: 75401 | O7: KIKES - EGIPTO | P7: 75401 | Q7: ALKA | R7: 0 | T7: =+VLOOKUP(Tabla1[[#This Row],[id_bodega]],'CONVERSION DATOS'!B:D,2,0) -> ALKA1 | U7: =+VLOOKUP(Q7,'CONVERSION DATOS'!B:D,3,0) -> PLANTA CLASIFICACION | V7: =+VLOOKUP($A$1:$A$21097,'DT HUEVO'!$A:$E,3,0) -> A | W7: =+VLOOKUP($A$1:$A$20937,'DT HUEVO'!$A:$E,4,0) -> GRIS SUELTO | X7: =+VLOOKUP(T$1:T$21097,'DT HUEVO'!$H:$K,2,0) -> - | Y7: =+VLOOKUP(T$1:T$21097,'DT HUEVO'!$H:$K,3,0) -> CALOTO | Z7: =+VLOOKUP(A$1:A$21097,'DT HUEVO'!$A:$E,5,0) -> 0 | AA7: =IF(Tabla1[[#This Row],[GRUPO]]="PLANTA CLASIFICACION","BODEGA",IF(Tabla1[[#This Row],[GRUPO]]="BODEGA","BODEGA",Tabla1[[#This Row],[GRUPO]])) -> BODEGA | AB7: =VLOOKUP(Tabla1[[#This Row],[articulo]],'DT HUEVO'!$A:$F,6,0) -> MAY
A8: 75501 | B8: HUEVO B X 30 CARTON GRIS LZ | C8: UN | D8: 492 | E8: 0 | F8: S | G8: IV82 | H8: 0 | I8: 210 | J8: HU | K8: HUEVO COMERCIAL | L8: 225.96 | M8: 46307 | N8: 75501 | O8: KIKES - EGIPTO | P8: 75501 | Q8: ALKA | R8: 0 | T8: =+VLOOKUP(Tabla1[[#This Row],[id_bodega]],'CONVERSION DATOS'!B:D,2,0) -> ALKA1 | U8: =+VLOOKUP(Q8,'CONVERSION DATOS'!B:D,3,0) -> PLANTA CLASIFICACION | V8: =+VLOOKUP($A$1:$A$21097,'DT HUEVO'!$A:$E,3,0) -> B | W8: =+VLOOKUP($A$1:$A$20937,'DT HUEVO'!$A:$E,4,0) -> GRIS SUELTO | X8: =+VLOOKUP(T$1:T$21097,'DT HUEVO'!$H:$K,2,0) -> - | Y8: =+VLOOKUP(T$1:T$21097,'DT HUEVO'!$H:$K,3,0) -> CALOTO | Z8: =+VLOOKUP(A$1:A$21097,'DT HUEVO'!$A:$E,5,0) -> 0 | AA8: =IF(Tabla1[[#This Row],[GRUPO]]="PLANTA CLASIFICACION","BODEGA",IF(Tabla1[[#This Row],[GRUPO]]="BODEGA","BODEGA",Tabla1[[#This Row],[GRUPO]])) -> BODEGA | AB8: =VLOOKUP(Tabla1[[#This Row],[articulo]],'DT HUEVO'!$A:$F,6,0) -> MAY
A9: 79110 | B9: HUEVO ROTO - ZF | C9: UN | D9: 31800 | E9: 0 | F9: S | G9: IV82 | H9: 0 | I9: 235 | J9: HU | K9: HUEVO COMERCIAL | L9: 85.68 | M9: 46307 | N9: 79110 | O9: KIKES - EGIPTO | P9: 79110 | Q9: ALKA | R9: 0 | T9: =+VLOOKUP(Tabla1[[#This Row],[id_bodega]],'CONVERSION DATOS'!B:D,2,0) -> ALKA1 | U9: =+VLOOKUP(Q9,'CONVERSION DATOS'!B:D,3,0) -> PLANTA CLASIFICACION | V9: =+VLOOKUP($A$1:$A$21120,'DT HUEVO'!$A:$E,3,0) -> SEGUNDA | W9: =+VLOOKUP($A$1:$A$20960,'DT HUEVO'!$A:$E,4,0) -> SEGUNDA | X9: =+VLOOKUP(T$1:T$21120,'DT HUEVO'!$H:$K,2,0) -> - | Y9: =+VLOOKUP(T$1:T$21120,'DT HUEVO'!$H:$K,3,0) -> CALOTO | Z9: =+VLOOKUP(A$1:A$21120,'DT HUEVO'!$A:$E,5,0) -> ROTO | AA9: =IF(Tabla1[[#This Row],[GRUPO]]="PLANTA CLASIFICACION","BODEGA",IF(Tabla1[[#This Row],[GRUPO]]="BODEGA","BODEGA",Tabla1[[#This Row],[GRUPO]])) -> BODEGA | AB9: =VLOOKUP(Tabla1[[#This Row],[articulo]],'DT HUEVO'!$A:$F,6,0) -> SEGUNDA
A10: 112268 | B10: HUEVO XL X 15 PET CAJA X 300. | C10: UN | D10: 39000 | F10: S | G10: IV82 | J10: HU | K10: HUEVO COMERCIAL | L10: 684.07 | M10: 46307 | O10: KIKES - EGIPTO | P10: 112268 | Q10: ALKA | R10: 0 | T10: =+VLOOKUP(Tabla1[[#This Row],[id_bodega]],'CONVERSION DATOS'!B:D,2,0) -> ALKA1 | U10: =+VLOOKUP(Q10,'CONVERSION DATOS'!B:D,3,0) -> PLANTA CLASIFICACION | V10: =+VLOOKUP($A$1:$A$21120,'DT HUEVO'!$A:$E,3,0) -> XL | W10: =+VLOOKUP($A$1:$A$20960,'DT HUEVO'!$A:$E,4,0) -> EMPACADOS | X10: =+VLOOKUP(T$1:T$21120,'DT HUEVO'!$H:$K,2,0) -> - | Y10: =+VLOOKUP(T$1:T$21120,'DT HUEVO'!$H:$K,3,0) -> CALOTO | Z10: =+VLOOKUP(A$1:A$21120,'DT HUEVO'!$A:$E,5,0) -> 0 | AA10: =IF(Tabla1[[#This Row],[GRUPO]]="PLANTA CLASIFICACION","BODEGA",IF(Tabla1[[#This Row],[GRUPO]]="BODEGA","BODEGA",Tabla1[[#This Row],[GRUPO]])) -> BODEGA | AB10: =VLOOKUP(Tabla1[[#This Row],[articulo]],'DT HUEVO'!$A:$F,6,0) -> AU/FS/GS
A11: 2010102 | B11: HUEVO YUMBO X20 CARTON VERDE CANASTA. | C11: UN | D11: 5259 | F11: S | G11: IV82 | J11: HU | K11: HUEVO COMERCIAL | L11: 629.68 | M11: 46307 | O11: KIKES - EGIPTO | P11: 2010102 | Q11: ALKA | R11: 0 | T11: =+VLOOKUP(Tabla1[[#This Row],[id_bodega]],'CONVERSION DATOS'!B:D,2,0) -> ALKA1 | U11: =+VLOOKUP(Q11,'CONVERSION DATOS'!B:D,3,0) -> PLANTA CLASIFICACION | V11: =+VLOOKUP($A$1:$A$21120,'DT HUEVO'!$A:$E,3,0) -> YUMBO | W11: =+VLOOKUP($A$1:$A$20960,'DT HUEVO'!$A:$E,4,0) -> VERDE | X11: =+VLOOKUP(T$1:T$21120,'DT HUEVO'!$H:$K,2,0) -> - | Y11: =+VLOOKUP(T$1:T$21120,'DT HUEVO'!$H:$K,3,0) -> CALOTO | Z11: =+VLOOKUP(A$1:A$21120,'DT HUEVO'!$A:$E,5,0) -> 0 | AA11: =IF(Tabla1[[#This Row],[GRUPO]]="PLANTA CLASIFICACION","BODEGA",IF(Tabla1[[#This Row],[GRUPO]]="BODEGA","BODEGA",Tabla1[[#This Row],[GRUPO]])) -> BODEGA | AB11: =VLOOKUP(Tabla1[[#This Row],[articulo]],'DT HUEVO'!$A:$F,6,0) -> TAT
A12: 2010301 | B12: HUEVO AA X30 CARTON GRIS CANASTA. | C12: UN | D12: 224793 | F12: S | G12: IV82 | J12: HU | K12: HUEVO COMERCIAL | L12: 376.83 | M12: 46307 | O12: KIKES - EGIPTO | P12: 2010301 | Q12: ALKA | R12: 0 | T12: =+VLOOKUP(Tabla1[[#This Row],[id_bodega]],'CONVERSION DATOS'!B:D,2,0) -> ALKA1 | U12: =+VLOOKUP(Q12,'CONVERSION DATOS'!B:D,3,0) -> PLANTA CLASIFICACION | V12: =+VLOOKUP($A$1:$A$21120,'DT HUEVO'!$A:$E,3,0) -> AA | W12: =+VLOOKUP($A$1:$A$20960,'DT HUEVO'!$A:$E,4,0) -> GRIS SUELTO | X12: =+VLOOKUP(T$1:T$21120,'DT HUEVO'!$H:$K,2,0) -> - | Y12: =+VLOOKUP(T$1:T$21120,'DT HUEVO'!$H:$K,3,0) -> CALOTO | Z12: =+VLOOKUP(A$1:A$21120,'DT HUEVO'!$A:$E,5,0) -> 0 | AA12: =IF(Tabla1[[#This Row],[GRUPO]]="PLANTA CLASIFICACION","BODEGA",IF(Tabla1[[#This Row],[GRUPO]]="BODEGA","BODEGA",Tabla1[[#This Row],[GRUPO]])) -> BODEGA | AB12: =VLOOKUP(Tabla1[[#This Row],[articulo]],'DT HUEVO'!$A:$F,6,0) -> HD
A13: 2010501 | B13: HUEVO B X30 CARTON GRIS CANASTA. | C13: UN | D13: 1989 | F13: S | G13: IV82 | J13: HU | K13: HUEVO COMERCIAL | L13: 319.65 | M13: 46307 | O13: KIKES - EGIPTO | P13: 2010501 | Q13: ALKA | R13: 0 | T13: =+VLOOKUP(Tabla1[[#This Row],[id_bodega]],'CONVERSION DATOS'!B:D,2,0) -> ALKA1 | U13: =+VLOOKUP(Q13,'CONVERSION DATOS'!B:D,3,0) -> PLANTA CLASIFICACION | V13: =+VLOOKUP($A$1:$A$21120,'DT HUEVO'!$A:$E,3,0) -> B | W13: =+VLOOKUP($A$1:$A$20960,'DT HUEVO'!$A:$E,4,0) -> GRIS SUELTO | X13: =+VLOOKUP(T$1:T$21120,'DT HUEVO'!$H:$K,2,0) -> - | Y13: =+VLOOKUP(T$1:T$21120,'DT HUEVO'!$H:$K,3,0) -> CALOTO | Z13: =+VLOOKUP(A$1:A$21120,'DT HUEVO'!$A:$E,5,0) -> 0 | AA13: =IF(Tabla1[[#This Row],[GRUPO]]="PLANTA CLASIFICACION","BODEGA",IF(Tabla1[[#This Row],[GRUPO]]="BODEGA","BODEGA",Tabla1[[#This Row],[GRUPO]])) -> BODEGA | AB13: =VLOOKUP(Tabla1[[#This Row],[articulo]],'DT HUEVO'!$A:$F,6,0) -> hd
A14: 2110202 | B14: HUEVO XL X 30 CARTON VERDE CANASTA | C14: UN | D14: 100036 | F14: S | G14: IV82 | J14: HU | K14: HUEVO COMERCIAL | L14: 394.26 | M14: 46307 | O14: KIKES - EGIPTO | P14: 2110202 | Q14: ALKA | R14: 0 | T14: =+VLOOKUP(Tabla1[[#This Row],[id_bodega]],'CONVERSION DATOS'!B:D,2,0) -> ALKA1 | U14: =+VLOOKUP(Q14,'CONVERSION DATOS'!B:D,3,0) -> PLANTA CLASIFICACION | V14: =+VLOOKUP($A$1:$A$21177,'DT HUEVO'!$A:$E,3,0) -> XL | W14: =+VLOOKUP($A$1:$A$21017,'DT HUEVO'!$A:$E,4,0) -> VERDE | X14: =+VLOOKUP(T$1:T$21177,'DT HUEVO'!$H:$K,2,0) -> - | Y14: =+VLOOKUP(T$1:T$21177,'DT HUEVO'!$H:$K,3,0) -> CALOTO | Z14: =+VLOOKUP(A$1:A$21177,'DT HUEVO'!$A:$E,5,0) -> 0 | AA14: =IF(Tabla1[[#This Row],[GRUPO]]="PLANTA CLASIFICACION","BODEGA",IF(Tabla1[[#This Row],[GRUPO]]="BODEGA","BODEGA",Tabla1[[#This Row],[GRUPO]])) -> BODEGA | AB14: =VLOOKUP(Tabla1[[#This Row],[articulo]],'DT HUEVO'!$A:$F,6,0) -> TAT
A15: 2110302 | B15: HUEVO L X 30 CARTON VERDE CANASTA | C15: UN | D15: 23256 | F15: S | G15: IV82 | J15: HU | K15: HUEVO COMERCIAL | L15: 363.24 | M15: 46307 | O15: KIKES - EGIPTO | P15: 2110302 | Q15: ALKA | R15: 0 | T15: =+VLOOKUP(Tabla1[[#This Row],[id_bodega]],'CONVERSION DATOS'!B:D,2,0) -> ALKA1 | U15: =+VLOOKUP(Q15,'CONVERSION DATOS'!B:D,3,0) -> PLANTA CLASIFICACION | V15: =+VLOOKUP($A$1:$A$21177,'DT HUEVO'!$A:$E,3,0) -> L | W15: =+VLOOKUP($A$1:$A$21017,'DT HUEVO'!$A:$E,4,0) -> VERDE | X15: =+VLOOKUP(T$1:T$21177,'DT HUEVO'!$H:$K,2,0) -> - | Y15: =+VLOOKUP(T$1:T$21177,'DT HUEVO'!$H:$K,3,0) -> CALOTO | Z15: =+VLOOKUP(A$1:A$21177,'DT HUEVO'!$A:$E,5,0) -> 0 | AA15: =IF(Tabla1[[#This Row],[GRUPO]]="PLANTA CLASIFICACION","BODEGA",IF(Tabla1[[#This Row],[GRUPO]]="BODEGA","BODEGA",Tabla1[[#This Row],[GRUPO]])) -> BODEGA | AB15: =VLOOKUP(Tabla1[[#This Row],[articulo]],'DT HUEVO'!$A:$F,6,0) -> TAT
A16: 2110402 | B16: HUEVO M X 30 CARTON VERDE CANASTA | C16: UN | D16: 120 | F16: S | G16: IV82 | J16: HU | K16: HUEVO COMERCIAL | L16: 349.55 | M16: 46304 | O16: KIKES - EGIPTO | P16: 2110402 | Q16: ALKA | R16: 0 | T16: =+VLOOKUP(Tabla1[[#This Row],[id_bodega]],'CONVERSION DATOS'!B:D,2,0) -> ALKA1 | U16: =+VLOOKUP(Q16,'CONVERSION DATOS'!B:D,3,0) -> PLANTA CLASIFICACION | V16: =+VLOOKUP($A$1:$A$21206,'DT HUEVO'!$A:$E,3,0) -> M | W16: =+VLOOKUP($A$1:$A$21046,'DT HUEVO'!$A:$E,4,0) -> VERDE | X16: =+VLOOKUP(T$1:T$21206,'DT HUEVO'!$H:$K,2,0) -> - | Y16: =+VLOOKUP(T$1:T$21206,'DT HUEVO'!$H:$K,3,0) -> CALOTO | Z16: =+VLOOKUP(A$1:A$21206,'DT HUEVO'!$A:$E,5,0) -> 0 | AA16: =IF(Tabla1[[#This Row],[GRUPO]]="PLANTA CLASIFICACION","BODEGA",IF(Tabla1[[#This Row],[GRUPO]]="BODEGA","BODEGA",Tabla1[[#This Row],[GRUPO]])) -> BODEGA | AB16: =VLOOKUP(Tabla1[[#This Row],[articulo]],'DT HUEVO'!$A:$F,6,0) -> TAT
A17: 2410401 | B17: HUEVO CE X 30 CARTON GRIS CANASTA | C17: UN | D17: 302316 | F17: S | G17: IV82 | J17: HU | K17: HUEVO COMERCIAL | L17: 406.83 | M17: 46307 | N17: 0 | O17: KIKES - EGIPTO | P17: 2410401 | Q17: ALKA | R17: 0 | T17: =+VLOOKUP(Tabla1[[#This Row],[id_bodega]],'CONVERSION DATOS'!B:D,2,0) -> ALKA1 | U17: =+VLOOKUP(Q17,'CONVERSION DATOS'!B:D,3,0) -> PLANTA CLASIFICACION | V17: =+VLOOKUP($A$1:$A$21235,'DT HUEVO'!$A:$E,3,0) -> A | W17: =+VLOOKUP($A$1:$A$21075,'DT HUEVO'!$A:$E,4,0) -> GRIS SUELTO | X17: =+VLOOKUP(T$1:T$21235,'DT HUEVO'!$H:$K,2,0) -> - | Y17: =+VLOOKUP(T$1:T$21235,'DT HUEVO'!$H:$K,3,0) -> CALOTO | Z17: =+VLOOKUP(A$1:A$21235,'DT HUEVO'!$A:$E,5,0) -> 0 | AA17: =IF(Tabla1[[#This Row],[GRUPO]]="PLANTA CLASIFICACION","BODEGA",IF(Tabla1[[#This Row],[GRUPO]]="BODEGA","BODEGA",Tabla1[[#This Row],[GRUPO]])) -> BODEGA | AB17: =VLOOKUP(Tabla1[[#This Row],[articulo]],'DT HUEVO'!$A:$F,6,0) -> HD
A18: 10601 | B18: HUEVO C X30 CARTON GRIS | C18: UN | D18: 9810 | E18: 0 | F18: S | G18: IV82 | H18: 0 | I18: 400 | J18: HU | K18: HUEVO COMERCIAL | L18: 130.24 | M18: 46307 | N18: 10601 | O18: KIKES2 - EGIPTO | P18: 10601 | Q18: ALKA2 | R18: 0 | T18: =+VLOOKUP(Tabla1[[#This Row],[id_bodega]],'CONVERSION DATOS'!B:D,2,0) -> ALKA2 | U18: =+VLOOKUP(Q18,'CONVERSION DATOS'!B:D,3,0) -> PLANTA CLASIFICACION | V18: =+VLOOKUP($A$1:$A$21329,'DT HUEVO'!$A:$E,3,0) -> C | W18: =+VLOOKUP($A$1:$A$21169,'DT HUEVO'!$A:$E,4,0) -> GRIS SUELTO | X18: =+VLOOKUP(T$1:T$21329,'DT HUEVO'!$H:$K,2,0) -> - | Y18: =+VLOOKUP(T$1:T$21329,'DT HUEVO'!$H:$K,3,0) -> CALOTO | Z18: =+VLOOKUP(A$1:A$21329,'DT HUEVO'!$A:$E,5,0) -> 0 | AA18: =IF(Tabla1[[#This Row],[GRUPO]]="PLANTA CLASIFICACION","BODEGA",IF(Tabla1[[#This Row],[GRUPO]]="BODEGA","BODEGA",Tabla1[[#This Row],[GRUPO]])) -> BODEGA | AB18: =VLOOKUP(Tabla1[[#This Row],[articulo]],'DT HUEVO'!$A:$F,6,0) -> MAY
A19: 13322 | B19: HUEVO AA X 30 BAND GRIS AMARRADO TAPA VERDE ALAT. | C19: UN | D19: 2160 | F19: S | G19: IV82 | J19: HU | K19: HUEVO COMERCIAL | L19: 478.25 | M19: 46308 | O19: KIKES2 - EGIPTO | P19: 13322 | Q19: ALKA2 | R19: 0 | T19: =+VLOOKUP(Tabla1[[#This Row],[id_bodega]],'CONVERSION DATOS'!B:D,2,0) -> ALKA2 | U19: =+VLOOKUP(Q19,'CONVERSION DATOS'!B:D,3,0) -> PLANTA CLASIFICACION | V19: =+VLOOKUP($A$1:$A$21362,'DT HUEVO'!$A:$E,3,0) -> AA | W19: =+VLOOKUP($A$1:$A$21202,'DT HUEVO'!$A:$E,4,0) -> EMPACADOS | X19: =+VLOOKUP(T$1:T$21362,'DT HUEVO'!$H:$K,2,0) -> - | Y19: =+VLOOKUP(T$1:T$21362,'DT HUEVO'!$H:$K,3,0) -> CALOTO | Z19: =+VLOOKUP(A$1:A$21362,'DT HUEVO'!$A:$E,5,0) -> 0 | AA19: =IF(Tabla1[[#This Row],[GRUPO]]="PLANTA CLASIFICACION","BODEGA",IF(Tabla1[[#This Row],[GRUPO]]="BODEGA","BODEGA",Tabla1[[#This Row],[GRUPO]])) -> BODEGA | AB19: =VLOOKUP(Tabla1[[#This Row],[articulo]],'DT HUEVO'!$A:$F,6,0) -> HD
A20: 13419 | B20: HUEVO A X 30 CARTON GRIS AMARRADO SOL NACIENTE. | C20: UN | D20: 2160 | F20: S | G20: IV82 | J20: HU | K20: HUEVO COMERCIAL | L20: 392.29 | M20: 46308 | O20: KIKES2 - EGIPTO | P20: 13419 | Q20: ALKA2 | R20: 0 | T20: =+VLOOKUP(Tabla1[[#This Row],[id_bodega]],'CONVERSION DATOS'!B:D,2,0) -> ALKA2 | U20: =+VLOOKUP(Q20,'CONVERSION DATOS'!B:D,3,0) -> PLANTA CLASIFICACION | V20: =+VLOOKUP($A$1:$A$21362,'DT HUEVO'!$A:$E,3,0) -> A | W20: =+VLOOKUP($A$1:$A$21202,'DT HUEVO'!$A:$E,4,0) -> EMPACADOS | X20: =+VLOOKUP(T$1:T$21362,'DT HUEVO'!$H:$K,2,0) -> - | Y20: =+VLOOKUP(T$1:T$21362,'DT HUEVO'!$H:$K,3,0) -> CALOTO | Z20: =+VLOOKUP(A$1:A$21362,'DT HUEVO'!$A:$E,5,0) -> 0 | AA20: =IF(Tabla1[[#This Row],[GRUPO]]="PLANTA CLASIFICACION","BODEGA",IF(Tabla1[[#This Row],[GRUPO]]="BODEGA","BODEGA",Tabla1[[#This Row],[GRUPO]])) -> BODEGA | AB20: =VLOOKUP(Tabla1[[#This Row],[articulo]],'DT HUEVO'!$A:$F,6,0) -> HD
A21: 72001 | B21: HUEVO SUCIO SIN MARCA X30 BANDEJA GRIS | C21: UN | D21: 9144 | E21: 0 | F21: S | G21: IV82 | H21: 0 | I21: 220 | J21: HU | K21: HUEVO COMERCIAL | L21: 162.88 | M21: 46307 | N21: 72001 | O21: KIKES2 - EGIPTO | P21: 72001 | Q21: ALKA2 | R21: 0 | T21: =+VLOOKUP(Tabla1[[#This Row],[id_bodega]],'CONVERSION DATOS'!B:D,2,0) -> ALKA2 | U21: =+VLOOKUP(Q21,'CONVERSION DATOS'!B:D,3,0) -> PLANTA CLASIFICACION | V21: =+VLOOKUP($A$1:$A$21362,'DT HUEVO'!$A:$E,3,0) -> SEGUNDA | W21: =+VLOOKUP($A$1:$A$21202,'DT HUEVO'!$A:$E,4,0) -> SEGUNDA | X21: =+VLOOKUP(T$1:T$21362,'DT HUEVO'!$H:$K,2,0) -> - | Y21: =+VLOOKUP(T$1:T$21362,'DT HUEVO'!$H:$K,3,0) -> CALOTO | Z21: =+VLOOKUP(A$1:A$21362,'DT HUEVO'!$A:$E,5,0) -> SUCIO | AA21: =IF(Tabla1[[#This Row],[GRUPO]]="PLANTA CLASIFICACION","BODEGA",IF(Tabla1[[#This Row],[GRUPO]]="BODEGA","BODEGA",Tabla1[[#This Row],[GRUPO]])) -> BODEGA | AB21: =VLOOKUP(Tabla1[[#This Row],[articulo]],'DT HUEVO'!$A:$F,6,0) -> SEGUNDA
A22: 72003 | B22: HUEVO SUCIO ZF MARCADO X30 BANDEJA GRIS | C22: UN | D22: 3240 | F22: S | G22: IV82 | J22: HU | K22: HUEVO COMERCIAL | L22: 85.68 | M22: 46306 | N22: 72003 | O22: KIKES2 - EGIPTO | P22: 72003 | Q22: ALKA2 | R22: 0 | T22: =+VLOOKUP(Tabla1[[#This Row],[id_bodega]],'CONVERSION DATOS'!B:D,2,0) -> ALKA2 | U22: =+VLOOKUP(Q22,'CONVERSION DATOS'!B:D,3,0) -> PLANTA CLASIFICACION | V22: =+VLOOKUP($A$1:$A$21362,'DT HUEVO'!$A:$E,3,0) -> SEGUNDA | W22: =+VLOOKUP($A$1:$A$21202,'DT HUEVO'!$A:$E,4,0) -> SEGUNDA | X22: =+VLOOKUP(T$1:T$21362,'DT HUEVO'!$H:$K,2,0) -> - | Y22: =+VLOOKUP(T$1:T$21362,'DT HUEVO'!$H:$K,3,0) -> CALOTO | Z22: =+VLOOKUP(A$1:A$21362,'DT HUEVO'!$A:$E,5,0) -> SUCIO | AA22: =IF(Tabla1[[#This Row],[GRUPO]]="PLANTA CLASIFICACION","BODEGA",IF(Tabla1[[#This Row],[GRUPO]]="BODEGA","BODEGA",Tabla1[[#This Row],[GRUPO]])) -> BODEGA | AB22: =VLOOKUP(Tabla1[[#This Row],[articulo]],'DT HUEVO'!$A:$F,6,0) -> SEGUNDA
A23: 73001 | B23: HUEVO PICADO ROJO X30 BANDEJA GRIS | C23: UN | D23: 39569 | E23: 0 | F23: S | G23: IV82 | H23: 0 | I23: 150 | J23: HU | K23: HUEVO COMERCIAL | L23: 164.38 | M23: 46307 | N23: 0 | O23: KIKES2 - EGIPTO | P23: 73001 | Q23: ALKA2 | R23: 0 | T23: =+VLOOKUP(Tabla1[[#This Row],[id_bodega]],'CONVERSION DATOS'!B:D,2,0) -> ALKA2 | U23: =+VLOOKUP(Q23,'CONVERSION DATOS'!B:D,3,0) -> PLANTA CLASIFICACION | V23: =+VLOOKUP($A$1:$A$21362,'DT HUEVO'!$A:$E,3,0) -> SEGUNDA | W23: =+VLOOKUP($A$1:$A$21202,'DT HUEVO'!$A:$E,4,0) -> SEGUNDA | X23: =+VLOOKUP(T$1:T$21362,'DT HUEVO'!$H:$K,2,0) -> - | Y23: =+VLOOKUP(T$1:T$21362,'DT HUEVO'!$H:$K,3,0) -> CALOTO | Z23: =+VLOOKUP(A$1:A$21362,'DT HUEVO'!$A:$E,5,0) -> PICADO | AA23: =IF(Tabla1[[#This Row],[GRUPO]]="PLANTA CLASIFICACION","BODEGA",IF(Tabla1[[#This Row],[GRUPO]]="BODEGA","BODEGA",Tabla1[[#This Row],[GRUPO]])) -> BODEGA | AB23: =VLOOKUP(Tabla1[[#This Row],[articulo]],'DT HUEVO'!$A:$F,6,0) -> SEGUNDA
A24: 112268 | B24: HUEVO XL X 15 PET CAJA X 300. | C24: UN | D24: 45000 | F24: S | G24: IV82 | J24: HU | K24: HUEVO COMERCIAL | L24: 684.07 | M24: 46307 | O24: KIKES2 - EGIPTO | P24: 112268 | Q24: ALKA2 | R24: 0 | T24: =+VLOOKUP(Tabla1[[#This Row],[id_bodega]],'CONVERSION DATOS'!B:D,2,0) -> ALKA2 | U24: =+VLOOKUP(Q24,'CONVERSION DATOS'!B:D,3,0) -> PLANTA CLASIFICACION | V24: =+VLOOKUP($A$1:$A$21394,'DT HUEVO'!$A:$E,3,0) -> XL | W24: =+VLOOKUP($A$1:$A$21234,'DT HUEVO'!$A:$E,4,0) -> EMPACADOS | X24: =+VLOOKUP(T$1:T$21394,'DT HUEVO'!$H:$K,2,0) -> - | Y24: =+VLOOKUP(T$1:T$21394,'DT HUEVO'!$H:$K,3,0) -> CALOTO | Z24: =+VLOOKUP(A$1:A$21394,'DT HUEVO'!$A:$E,5,0) -> 0 | AA24: =IF(Tabla1[[#This Row],[GRUPO]]="PLANTA CLASIFICACION","BODEGA",IF(Tabla1[[#This Row],[GRUPO]]="BODEGA","BODEGA",Tabla1[[#This Row],[GRUPO]])) -> BODEGA | AB24: =VLOOKUP(Tabla1[[#This Row],[articulo]],'DT HUEVO'!$A:$F,6,0) -> AU/FS/GS
A25: 2010102 | B25: HUEVO YUMBO X20 CARTON VERDE CANASTA. | C25: UN | D25: 6156 | F25: S | G25: IV82 | J25: HU | K25: HUEVO COMERCIAL | L25: 629.68 | M25: 46307 | O25: KIKES2 - EGIPTO | P25: 2010102 | Q25: ALKA2 | R25: 0 | T25: =+VLOOKUP(Tabla1[[#This Row],[id_bodega]],'CONVERSION DATOS'!B:D,2,0) -> ALKA2 | U25: =+VLOOKUP(Q25,'CONVERSION DATOS'!B:D,3,0) -> PLANTA CLASIFICACION | V25: =+VLOOKUP($A$1:$A$21425,'DT HUEVO'!$A:$E,3,0) -> YUMBO | W25: =+VLOOKUP($A$1:$A$21265,'DT HUEVO'!$A:$E,4,0) -> VERDE | X25: =+VLOOKUP(T$1:T$21425,'DT HUEVO'!$H:$K,2,0) -> - | Y25: =+VLOOKUP(T$1:T$21425,'DT HUEVO'!$H:$K,3,0) -> CALOTO | Z25: =+VLOOKUP(A$1:A$21425,'DT HUEVO'!$A:$E,5,0) -> 0 | AA25: =IF(Tabla1[[#This Row],[GRUPO]]="PLANTA CLASIFICACION","BODEGA",IF(Tabla1[[#This Row],[GRUPO]]="BODEGA","BODEGA",Tabla1[[#This Row],[GRUPO]])) -> BODEGA | AB25: =VLOOKUP(Tabla1[[#This Row],[articulo]],'DT HUEVO'!$A:$F,6,0) -> TAT
A26: 2010301 | B26: HUEVO AA X30 CARTON GRIS CANASTA. | C26: UN | D26: 263538 | F26: S | G26: IV82 | J26: HU | K26: HUEVO COMERCIAL | L26: 376.83 | M26: 46307 | O26: KIKES2 - EGIPTO | P26: 2010301 | Q26: ALKA2 | R26: 0 | T26: =+VLOOKUP(Tabla1[[#This Row],[id_bodega]],'CONVERSION DATOS'!B:D,2,0) -> ALKA2 | U26: =+VLOOKUP(Q26,'CONVERSION DATOS'!B:D,3,0) -> PLANTA CLASIFICACION | V26: =+VLOOKUP($A$1:$A$21425,'DT HUEVO'!$A:$E,3,0) -> AA | W26: =+VLOOKUP($A$1:$A$21265,'DT HUEVO'!$A:$E,4,0) -> GRIS SUELTO | X26: =+VLOOKUP(T$1:T$21425,'DT HUEVO'!$H:$K,2,0) -> - | Y26: =+VLOOKUP(T$1:T$21425,'DT HUEVO'!$H:$K,3,0) -> CALOTO | Z26: =+VLOOKUP(A$1:A$21425,'DT HUEVO'!$A:$E,5,0) -> 0 | AA26: =IF(Tabla1[[#This Row],[GRUPO]]="PLANTA CLASIFICACION","BODEGA",IF(Tabla1[[#This Row],[GRUPO]]="BODEGA","BODEGA",Tabla1[[#This Row],[GRUPO]])) -> BODEGA | AB26: =VLOOKUP(Tabla1[[#This Row],[articulo]],'DT HUEVO'!$A:$F,6,0) -> HD
A27: 2010501 | B27: HUEVO B X30 CARTON GRIS CANASTA. | C27: UN | D27: 362 | F27: S | G27: IV82 | J27: HU | K27: HUEVO COMERCIAL | L27: 319.65 | M27: 46307 | O27: KIKES2 - EGIPTO | P27: 2010501 | Q27: ALKA2 | R27: 0 | T27: =+VLOOKUP(Tabla1[[#This Row],[id_bodega]],'CONVERSION DATOS'!B:D,2,0) -> ALKA2 | U27: =+VLOOKUP(Q27,'CONVERSION DATOS'!B:D,3,0) -> PLANTA CLASIFICACION | V27: =+VLOOKUP($A$1:$A$21425,'DT HUEVO'!$A:$E,3,0) -> B | W27: =+VLOOKUP($A$1:$A$21265,'DT HUEVO'!$A:$E,4,0) -> GRIS SUELTO | X27: =+VLOOKUP(T$1:T$21425,'DT HUEVO'!$H:$K,2,0) -> - | Y27: =+VLOOKUP(T$1:T$21425,'DT HUEVO'!$H:$K,3,0) -> CALOTO | Z27: =+VLOOKUP(A$1:A$21425,'DT HUEVO'!$A:$E,5,0) -> 0 | AA27: =IF(Tabla1[[#This Row],[GRUPO]]="PLANTA CLASIFICACION","BODEGA",IF(Tabla1[[#This Row],[GRUPO]]="BODEGA","BODEGA",Tabla1[[#This Row],[GRUPO]])) -> BODEGA | AB27: =VLOOKUP(Tabla1[[#This Row],[articulo]],'DT HUEVO'!$A:$F,6,0) -> hd
A28: 2110202 | B28: HUEVO XL X 30 CARTON VERDE CANASTA | C28: UN | D28: 177934 | F28: S | G28: IV82 | J28: HU | K28: HUEVO COMERCIAL | L28: 394.26 | M28: 46307 | O28: KIKES2 - EGIPTO | P28: 2110202 | Q28: ALKA2 | R28: 0 | T28: =+VLOOKUP(Tabla1[[#This Row],[id_bodega]],'CONVERSION DATOS'!B:D,2,0) -> ALKA2 | U28: =+VLOOKUP(Q28,'CONVERSION DATOS'!B:D,3,0) -> PLANTA CLASIFICACION | V28: =+VLOOKUP($A$1:$A$21439,'DT HUEVO'!$A:$E,3,0) -> XL | W28: =+VLOOKUP($A$1:$A$21279,'DT HUEVO'!$A:$E,4,0) -> VERDE | X28: =+VLOOKUP(T$1:T$21439,'DT HUEVO'!$H:$K,2,0) -> - | Y28: =+VLOOKUP(T$1:T$21439,'DT HUEVO'!$H:$K,3,0) -> CALOTO | Z28: =+VLOOKUP(A$1:A$21439,'DT HUEVO'!$A:$E,5,0) -> 0 | AA28: =IF(Tabla1[[#This Row],[GRUPO]]="PLANTA CLASIFICACION","BODEGA",IF(Tabla1[[#This Row],[GRUPO]]="BODEGA","BODEGA",Tabla1[[#This Row],[GRUPO]])) -> BODEGA | AB28: =VLOOKUP(Tabla1[[#This Row],[articulo]],'DT HUEVO'!$A:$F,6,0) -> TAT
A29: 2110302 | B29: HUEVO L X 30 CARTON VERDE CANASTA | C29: UN | D29: 5976 | F29: S | G29: IV82 | J29: HU | K29: HUEVO COMERCIAL | L29: 363.24 | M29: 46307 | O29: KIKES2 - EGIPTO | P29: 2110302 | Q29: ALKA2 | R29: 0 | T29: =+VLOOKUP(Tabla1[[#This Row],[id_bodega]],'CONVERSION DATOS'!B:D,2,0) -> ALKA2 | U29: =+VLOOKUP(Q29,'CONVERSION DATOS'!B:D,3,0) -> PLANTA CLASIFICACION | V29: =+VLOOKUP($A$1:$A$21470,'DT HUEVO'!$A:$E,3,0) -> L | W29: =+VLOOKUP($A$1:$A$21310,'DT HUEVO'!$A:$E,4,0) -> VERDE | X29: =+VLOOKUP(T$1:T$21470,'DT HUEVO'!$H:$K,2,0) -> - | Y29: =+VLOOKUP(T$1:T$21470,'DT HUEVO'!$H:$K,3,0) -> CALOTO | Z29: =+VLOOKUP(A$1:A$21470,'DT HUEVO'!$A:$E,5,0) -> 0 | AA29: =IF(Tabla1[[#This Row],[GRUPO]]="PLANTA CLASIFICACION","BODEGA",IF(Tabla1[[#This Row],[GRUPO]]="BODEGA","BODEGA",Tabla1[[#This Row],[GRUPO]])) -> BODEGA | AB29: =VLOOKUP(Tabla1[[#This Row],[articulo]],'DT HUEVO'!$A:$F,6,0) -> TAT
A30: 2110402 | B30: HUEVO M X 30 CARTON VERDE CANASTA | C30: UN | D30: 3256 | F30: S | G30: IV82 | J30: HU | K30: HUEVO COMERCIAL | L30: 349.55 | M30: 46305 | O30: KIKES2 - EGIPTO | P30: 2110402 | Q30: ALKA2 | R30: 0 | T30: =+VLOOKUP(Tabla1[[#This Row],[id_bodega]],'CONVERSION DATOS'!B:D,2,0) -> ALKA2 | U30: =+VLOOKUP(Q30,'CONVERSION DATOS'!B:D,3,0) -> PLANTA CLASIFICACION | V30: =+VLOOKUP($A$1:$A$21470,'DT HUEVO'!$A:$E,3,0) -> M | W30: =+VLOOKUP($A$1:$A$21310,'DT HUEVO'!$A:$E,4,0) -> VERDE | X30: =+VLOOKUP(T$1:T$21470,'DT HUEVO'!$H:$K,2,0) -> - | Y30: =+VLOOKUP(T$1:T$21470,'DT HUEVO'!$H:$K,3,0) -> CALOTO | Z30: =+VLOOKUP(A$1:A$21470,'DT HUEVO'!$A:$E,5,0) -> 0 | AA30: =IF(Tabla1[[#This Row],[GRUPO]]="PLANTA CLASIFICACION","BODEGA",IF(Tabla1[[#This Row],[GRUPO]]="BODEGA","BODEGA",Tabla1[[#This Row],[GRUPO]])) -> BODEGA | AB30: =VLOOKUP(Tabla1[[#This Row],[articulo]],'DT HUEVO'!$A:$F,6,0) -> TAT
A31: 2410401 | B31: HUEVO CE X 30 CARTON GRIS CANASTA | C31: UN | D31: 180757 | F31: S | G31: IV82 | J31: HU | K31: HUEVO COMERCIAL | L31: 406.83 | M31: 46307 | N31: 0 | O31: KIKES2 - EGIPTO | P31: 2410401 | Q31: ALKA2 | R31: 0 | T31: =+VLOOKUP(Tabla1[[#This Row],[id_bodega]],'CONVERSION DATOS'!B:D,2,0) -> ALKA2 | U31: =+VLOOKUP(Q31,'CONVERSION DATOS'!B:D,3,0) -> PLANTA CLASIFICACION | V31: =+VLOOKUP($A$1:$A$21470,'DT HUEVO'!$A:$E,3,0) -> A | W31: =+VLOOKUP($A$1:$A$21310,'DT HUEVO'!$A:$E,4,0) -> GRIS SUELTO | X31: =+VLOOKUP(T$1:T$21470,'DT HUEVO'!$H:$K,2,0) -> - | Y31: =+VLOOKUP(T$1:T$21470,'DT HUEVO'!$H:$K,3,0) -> CALOTO | Z31: =+VLOOKUP(A$1:A$21470,'DT HUEVO'!$A:$E,5,0) -> 0 | AA31: =IF(Tabla1[[#This Row],[GRUPO]]="PLANTA CLASIFICACION","BODEGA",IF(Tabla1[[#This Row],[GRUPO]]="BODEGA","BODEGA",Tabla1[[#This Row],[GRUPO]])) -> BODEGA | AB31: =VLOOKUP(Tabla1[[#This Row],[articulo]],'DT HUEVO'!$A:$F,6,0) -> HD
A32: 10501 | B32: HUEVO B X30 CARTON GRIS | C32: UN | D32: 38288 | E32: 0 | F32: S | G32: IV82 | H32: 0 | I32: 400 | J32: HU | K32: HUEVO COMERCIAL | L32: 225.96 | M32: 46305 | N32: 10501 | O32: BELLAVISTA | P32: 10501 | Q32: BE | R32: 0 | T32: =+VLOOKUP(Tabla1[[#This Row],[id_bodega]],'CONVERSION DATOS'!B:D,2,0) -> BELLAVISTA | U32: =+VLOOKUP(Q32,'CONVERSION DATOS'!B:D,3,0) -> PLANTA CLASIFICACION | V32: =+VLOOKUP($A$1:$A$21470,'DT HUEVO'!$A:$E,3,0) -> B | W32: =+VLOOKUP($A$1:$A$21310,'DT HUEVO'!$A:$E,4,0) -> GRIS SUELTO | X32: =+VLOOKUP(T$1:T$21470,'DT HUEVO'!$H:$K,2,0) -> - | Y32: =+VLOOKUP(T$1:T$21470,'DT HUEVO'!$H:$K,3,0) -> SANTANDER | Z32: =+VLOOKUP(A$1:A$21470,'DT HUEVO'!$A:$E,5,0) -> 0 | AA32: =IF(Tabla1[[#This Row],[GRUPO]]="PLANTA CLASIFICACION","BODEGA",IF(Tabla1[[#This Row],[GRUPO]]="BODEGA","BODEGA",Tabla1[[#This Row],[GRUPO]])) -> BODEGA | AB32: =VLOOKUP(Tabla1[[#This Row],[articulo]],'DT HUEVO'!$A:$F,6,0) -> MAY
A33: 10601 | B33: HUEVO C X30 CARTON GRIS | C33: UN | D33: 124942 | E33: 0 | F33: S | G33: IV82 | H33: 0 | I33: 400 | J33: HU | K33: HUEVO COMERCIAL | L33: 130.24 | M33: 46307 | N33: 10601 | O33: BELLAVISTA | P33: 10601 | Q33: BE | R33: 0 | T33: =+VLOOKUP(Tabla1[[#This Row],[id_bodega]],'CONVERSION DATOS'!B:D,2,0) -> BELLAVISTA | U33: =+VLOOKUP(Q33,'CONVERSION DATOS'!B:D,3,0) -> PLANTA CLASIFICACION | V33: =+VLOOKUP($A$1:$A$21470,'DT HUEVO'!$A:$E,3,0) -> C | W33: =+VLOOKUP($A$1:$A$21310,'DT HUEVO'!$A:$E,4,0) -> GRIS SUELTO | X33: =+VLOOKUP(T$1:T$21470,'DT HUEVO'!$H:$K,2,0) -> - | Y33: =+VLOOKUP(T$1:T$21470,'DT HUEVO'!$H:$K,3,0) -> SANTANDER | Z33: =+VLOOKUP(A$1:A$21470,'DT HUEVO'!$A:$E,5,0) -> 0 | AA33: =IF(Tabla1[[#This Row],[GRUPO]]="PLANTA CLASIFICACION","BODEGA",IF(Tabla1[[#This Row],[GRUPO]]="BODEGA","BODEGA",Tabla1[[#This Row],[GRUPO]])) -> BODEGA | AB33: =VLOOKUP(Tabla1[[#This Row],[articulo]],'DT HUEVO'!$A:$F,6,0) -> MAY
A34: 72001 | B34: HUEVO SUCIO SIN MARCA X30 BANDEJA GRIS | C34: UN | D34: 1714 | E34: 0 | F34: S | G34: IV82 | H34: 0 | I34: 400 | J34: HU | K34: HUEVO COMERCIAL | L34: 162.88 | M34: 46307 | N34: 72001 | O34: BELLAVISTA | P34: 72001 | Q34: BE | R34: 0 | T34: =+VLOOKUP(Tabla1[[#This Row],[id_bodega]],'CONVERSION DATOS'!B:D,2,0) -> BELLAVISTA | U34: =+VLOOKUP(Q34,'CONVERSION DATOS'!B:D,3,0) -> PLANTA CLASIFICACION | V34: =+VLOOKUP($A$1:$A$21541,'DT HUEVO'!$A:$E,3,0) -> SEGUNDA | W34: =+VLOOKUP($A$1:$A$21381,'DT HUEVO'!$A:$E,4,0) -> SEGUNDA | X34: =+VLOOKUP(T$1:T$21541,'DT HUEVO'!$H:$K,2,0) -> - | Y34: =+VLOOKUP(T$1:T$21541,'DT HUEVO'!$H:$K,3,0) -> SANTANDER | Z34: =+VLOOKUP(A$1:A$21541,'DT HUEVO'!$A:$E,5,0) -> SUCIO | AA34: =IF(Tabla1[[#This Row],[GRUPO]]="PLANTA CLASIFICACION","BODEGA",IF(Tabla1[[#This Row],[GRUPO]]="BODEGA","BODEGA",Tabla1[[#This Row],[GRUPO]])) -> BODEGA | AB34: =VLOOKUP(Tabla1[[#This Row],[articulo]],'DT HUEVO'!$A:$F,6,0) -> SEGUNDA
A35: 72003 | B35: HUEVO SUCIO ZF MARCADO X30 BANDEJA GRIS | C35: UN | D35: 238 | F35: S | G35: IV82 | J35: HU | K35: HUEVO COMERCIAL | L35: 85.68 | M35: 46307 | N35: 72003 | O35: BELLAVISTA | P35: 72003 | Q35: BE | R35: 0 | T35: =+VLOOKUP(Tabla1[[#This Row],[id_bodega]],'CONVERSION DATOS'!B:D,2,0) -> BELLAVISTA | U35: =+VLOOKUP(Q35,'CONVERSION DATOS'!B:D,3,0) -> PLANTA CLASIFICACION | V35: =+VLOOKUP($A$1:$A$21582,'DT HUEVO'!$A:$E,3,0) -> SEGUNDA | W35: =+VLOOKUP($A$1:$A$21422,'DT HUEVO'!$A:$E,4,0) -> SEGUNDA | X35: =+VLOOKUP(T$1:T$21582,'DT HUEVO'!$H:$K,2,0) -> - | Y35: =+VLOOKUP(T$1:T$21582,'DT HUEVO'!$H:$K,3,0) -> SANTANDER | Z35: =+VLOOKUP(A$1:A$21582,'DT HUEVO'!$A:$E,5,0) -> SUCIO | AA35: =IF(Tabla1[[#This Row],[GRUPO]]="PLANTA CLASIFICACION","BODEGA",IF(Tabla1[[#This Row],[GRUPO]]="BODEGA","BODEGA",Tabla1[[#This Row],[GRUPO]])) -> BODEGA | AB35: =VLOOKUP(Tabla1[[#This Row],[articulo]],'DT HUEVO'!$A:$F,6,0) -> SEGUNDA
A36: 76601 | B36: REVOLTURA COMERCIAL MEDIANA | C36: UN | D36: 619 | E36: 0 | F36: S | G36: IV82 | H36: 0 | I36: 400 | J36: HU | K36: HUEVO COMERCIAL | L36: 144.5 | M36: 46307 | N36: 76601 | O36: BELLAVISTA | P36: 76601 | Q36: BE | R36: 0 | T36: =+VLOOKUP(Tabla1[[#This Row],[id_bodega]],'CONVERSION DATOS'!B:D,2,0) -> BELLAVISTA | U36: =+VLOOKUP(Q36,'CONVERSION DATOS'!B:D,3,0) -> PLANTA CLASIFICACION | V36: =+VLOOKUP($A$1:$A$21623,'DT HUEVO'!$A:$E,3,0) -> SEGUNDA | W36: =+VLOOKUP($A$1:$A$21463,'DT HUEVO'!$A:$E,4,0) -> SEGUNDA | X36: =+VLOOKUP(T$1:T$21623,'DT HUEVO'!$H:$K,2,0) -> - | Y36: =+VLOOKUP(T$1:T$21623,'DT HUEVO'!$H:$K,3,0) -> SANTANDER | Z36: =+VLOOKUP(A$1:A$21623,'DT HUEVO'!$A:$E,5,0) -> REVOLTURA | AA36: =IF(Tabla1[[#This Row],[GRUPO]]="PLANTA CLASIFICACION","BODEGA",IF(Tabla1[[#This Row],[GRUPO]]="BODEGA","BODEGA",Tabla1[[#This Row],[GRUPO]])) -> BODEGA | AB36: =VLOOKUP(Tabla1[[#This Row],[articulo]],'DT HUEVO'!$A:$F,6,0) -> SEGUNDA
A37: 79101 | B37: HUEVO ROTO | C37: UN | D37: 8408 | E37: 0 | F37: S | G37: IV82 | H37: 0 | I37: 400 | J37: HU | K37: HUEVO COMERCIAL | L37: 95.13 | M37: 46307 | N37: 79101 | O37: BELLAVISTA | P37: 79101 | Q37: BE | R37: 0 | T37: =+VLOOKUP(Tabla1[[#This Row],[id_bodega]],'CONVERSION DATOS'!B:D,2,0) -> BELLAVISTA | U37: =+VLOOKUP(Q37,'CONVERSION DATOS'!B:D,3,0) -> PLANTA CLASIFICACION | V37: =+VLOOKUP($A$1:$A$21664,'DT HUEVO'!$A:$E,3,0) -> SEGUNDA | W37: =+VLOOKUP($A$1:$A$21504,'DT HUEVO'!$A:$E,4,0) -> SEGUNDA | X37: =+VLOOKUP(T$1:T$21664,'DT HUEVO'!$H:$K,2,0) -> - | Y37: =+VLOOKUP(T$1:T$21664,'DT HUEVO'!$H:$K,3,0) -> SANTANDER | Z37: =+VLOOKUP(A$1:A$21664,'DT HUEVO'!$A:$E,5,0) -> ROTO | AA37: =IF(Tabla1[[#This Row],[GRUPO]]="PLANTA CLASIFICACION","BODEGA",IF(Tabla1[[#This Row],[GRUPO]]="BODEGA","BODEGA",Tabla1[[#This Row],[GRUPO]])) -> BODEGA | AB37: =VLOOKUP(Tabla1[[#This Row],[articulo]],'DT HUEVO'!$A:$F,6,0) -> SEGUNDA
A38: 79111 | B38: HUEVO ROTO ZF - SANTANDER | C38: UN | D38: 23895 | F38: S | G38: IV82 | J38: HU | K38: HUEVO COMERCIAL | L38: 115.68 | M38: 46307 | N38: 79111 | O38: BELLAVISTA | P38: 79111 | Q38: BE | R38: 0 | T38: =+VLOOKUP(Tabla1[[#This Row],[id_bodega]],'CONVERSION DATOS'!B:D,2,0) -> BELLAVISTA | U38: =+VLOOKUP(Q38,'CONVERSION DATOS'!B:D,3,0) -> PLANTA CLASIFICACION | V38: =+VLOOKUP($A$1:$A$21664,'DT HUEVO'!$A:$E,3,0) -> SEGUNDA | W38: =+VLOOKUP($A$1:$A$21504,'DT HUEVO'!$A:$E,4,0) -> SEGUNDA | X38: =+VLOOKUP(T$1:T$21664,'DT HUEVO'!$H:$K,2,0) -> - | Y38: =+VLOOKUP(T$1:T$21664,'DT HUEVO'!$H:$K,3,0) -> SANTANDER | Z38: =+VLOOKUP(A$1:A$21664,'DT HUEVO'!$A:$E,5,0) -> ROTO | AA38: =IF(Tabla1[[#This Row],[GRUPO]]="PLANTA CLASIFICACION","BODEGA",IF(Tabla1[[#This Row],[GRUPO]]="BODEGA","BODEGA",Tabla1[[#This Row],[GRUPO]])) -> BODEGA | AB38: =VLOOKUP(Tabla1[[#This Row],[articulo]],'DT HUEVO'!$A:$F,6,0) -> SEGUNDA
A39: 271901 | B39: HUEVO MAL MARCADO CANASTA | C39: UN | D39: 345 | F39: S | G39: IV82 | J39: HU | K39: HUEVO COMERCIAL | L39: 175.89 | M39: 46307 | N39: 0 | O39: BELLAVISTA | P39: 271901 | Q39: BE | R39: 0 | T39: =+VLOOKUP(Tabla1[[#This Row],[id_bodega]],'CONVERSION DATOS'!B:D,2,0) -> BELLAVISTA | U39: =+VLOOKUP(Q39,'CONVERSION DATOS'!B:D,3,0) -> PLANTA CLASIFICACION | V39: =+VLOOKUP($A$1:$A$21701,'DT HUEVO'!$A:$E,3,0) -> SEGUNDA | W39: =+VLOOKUP($A$1:$A$21541,'DT HUEVO'!$A:$E,4,0) -> SEGUNDA | X39: =+VLOOKUP(T$1:T$21701,'DT HUEVO'!$H:$K,2,0) -> - | Y39: =+VLOOKUP(T$1:T$21701,'DT HUEVO'!$H:$K,3,0) -> SANTANDER | Z39: =+VLOOKUP(A$1:A$21701,'DT HUEVO'!$A:$E,5,0) -> MAL MARCADO | AA39: =IF(Tabla1[[#This Row],[GRUPO]]="PLANTA CLASIFICACION","BODEGA",IF(Tabla1[[#This Row],[GRUPO]]="BODEGA","BODEGA",Tabla1[[#This Row],[GRUPO]])) -> BODEGA | AB39: =VLOOKUP(Tabla1[[#This Row],[articulo]],'DT HUEVO'!$A:$F,6,0) -> SEGUNDA
A40: 273001 | B40: HUEVO PICADO X 30 BANDEJA GRIS CANASTA | C40: UN | D40: 29069 | F40: S | G40: IV82 | J40: HU | K40: HUEVO COMERCIAL | L40: 176.68 | M40: 46307 | N40: 0 | O40: BELLAVISTA | P40: 273001 | Q40: BE | R40: 0 | T40: =+VLOOKUP(Tabla1[[#This Row],[id_bodega]],'CONVERSION DATOS'!B:D,2,0) -> BELLAVISTA | U40: =+VLOOKUP(Q40,'CONVERSION DATOS'!B:D,3,0) -> PLANTA CLASIFICACION | V40: =+VLOOKUP($A$1:$A$21701,'DT HUEVO'!$A:$E,3,0) -> SEGUNDA | W40: =+VLOOKUP($A$1:$A$21541,'DT HUEVO'!$A:$E,4,0) -> SEGUNDA | X40: =+VLOOKUP(T$1:T$21701,'DT HUEVO'!$H:$K,2,0) -> - | Y40: =+VLOOKUP(T$1:T$21701,'DT HUEVO'!$H:$K,3,0) -> SANTANDER | Z40: =+VLOOKUP(A$1:A$21701,'DT HUEVO'!$A:$E,5,0) -> PICADO | AA40: =IF(Tabla1[[#This Row],[GRUPO]]="PLANTA CLASIFICACION","BODEGA",IF(Tabla1[[#This Row],[GRUPO]]="BODEGA","BODEGA",Tabla1[[#This Row],[GRUPO]])) -> BODEGA | AB40: =VLOOKUP(Tabla1[[#This Row],[articulo]],'DT HUEVO'!$A:$F,6,0) -> SEGUNDA
A41: 273003 | B41: HUEVO PICADO ZF MARCADO X 30 BANDEJA GRIS CANASTA | C41: UN | D41: 2300 | F41: S | G41: IV82 | J41: HU | K41: HUEVO COMERCIAL | L41: 175.18 | M41: 46307 | O41: BELLAVISTA | P41: 273003 | Q41: BE | R41: 0 | T41: =+VLOOKUP(Tabla1[[#This Row],[id_bodega]],'CONVERSION DATOS'!B:D,2,0) -> BELLAVISTA | U41: =+VLOOKUP(Q41,'CONVERSION DATOS'!B:D,3,0) -> PLANTA CLASIFICACION | V41: =+VLOOKUP($A$1:$A$21701,'DT HUEVO'!$A:$E,3,0) -> SEGUNDA | W41: =+VLOOKUP($A$1:$A$21541,'DT HUEVO'!$A:$E,4,0) -> SEGUNDA | X41: =+VLOOKUP(T$1:T$21701,'DT HUEVO'!$H:$K,2,0) -> - | Y41: =+VLOOKUP(T$1:T$21701,'DT HUEVO'!$H:$K,3,0) -> SANTANDER | Z41: =+VLOOKUP(A$1:A$21701,'DT HUEVO'!$A:$E,5,0) -> PICADO | AA41: =IF(Tabla1[[#This Row],[GRUPO]]="PLANTA CLASIFICACION","BODEGA",IF(Tabla1[[#This Row],[GRUPO]]="BODEGA","BODEGA",Tabla1[[#This Row],[GRUPO]])) -> BODEGA | AB41: =VLOOKUP(Tabla1[[#This Row],[articulo]],'DT HUEVO'!$A:$F,6,0) -> SEGUNDA
A42: 2010102 | B42: HUEVO YUMBO X20 CARTON VERDE CANASTA. | C42: UN | D42: 5651 | F42: S | G42: IV82 | J42: HU | K42: HUEVO COMERCIAL | L42: 629.68 | M42: 46307 | O42: BELLAVISTA | P42: 2010102 | Q42: BE | R42: 0 | T42: =+VLOOKUP(Tabla1[[#This Row],[id_bodega]],'CONVERSION DATOS'!B:D,2,0) -> BELLAVISTA | U42: =+VLOOKUP(Q42,'CONVERSION DATOS'!B:D,3,0) -> PLANTA CLASIFICACION | V42: =+VLOOKUP($A$1:$A$21701,'DT HUEVO'!$A:$E,3,0) -> YUMBO | W42: =+VLOOKUP($A$1:$A$21541,'DT HUEVO'!$A:$E,4,0) -> VERDE | X42: =+VLOOKUP(T$1:T$21701,'DT HUEVO'!$H:$K,2,0) -> - | Y42: =+VLOOKUP(T$1:T$21701,'DT HUEVO'!$H:$K,3,0) -> SANTANDER | Z42: =+VLOOKUP(A$1:A$21701,'DT HUEVO'!$A:$E,5,0) -> 0 | AA42: =IF(Tabla1[[#This Row],[GRUPO]]="PLANTA CLASIFICACION","BODEGA",IF(Tabla1[[#This Row],[GRUPO]]="BODEGA","BODEGA",Tabla1[[#This Row],[GRUPO]])) -> BODEGA | AB42: =VLOOKUP(Tabla1[[#This Row],[articulo]],'DT HUEVO'!$A:$F,6,0) -> TAT
A43: 2010501 | B43: HUEVO B X30 CARTON GRIS CANASTA. | C43: UN | D43: 72984 | F43: S | G43: IV82 | J43: HU | K43: HUEVO COMERCIAL | L43: 319.65 | M43: 46307 | O43: BELLAVISTA | P43: 2010501 | Q43: BE | R43: 0 | T43: =+VLOOKUP(Tabla1[[#This Row],[id_bodega]],'CONVERSION DATOS'!B:D,2,0) -> BELLAVISTA | U43: =+VLOOKUP(Q43,'CONVERSION DATOS'!B:D,3,0) -> PLANTA CLASIFICACION | V43: =+VLOOKUP($A$1:$A$21701,'DT HUEVO'!$A:$E,3,0) -> B | W43: =+VLOOKUP($A$1:$A$21541,'DT HUEVO'!$A:$E,4,0) -> GRIS SUELTO | X43: =+VLOOKUP(T$1:T$21701,'DT HUEVO'!$H:$K,2,0) -> - | Y43: =+VLOOKUP(T$1:T$21701,'DT HUEVO'!$H:$K,3,0) -> SANTANDER | Z43: =+VLOOKUP(A$1:A$21701,'DT HUEVO'!$A:$E,5,0) -> 0 | AA43: =IF(Tabla1[[#This Row],[GRUPO]]="PLANTA CLASIFICACION","BODEGA",IF(Tabla1[[#This Row],[GRUPO]]="BODEGA","BODEGA",Tabla1[[#This Row],[GRUPO]])) -> BODEGA | AB43: =VLOOKUP(Tabla1[[#This Row],[articulo]],'DT HUEVO'!$A:$F,6,0) -> hd
A44: 2110202 | B44: HUEVO XL X 30 CARTON VERDE CANASTA | C44: UN | D44: 2951 | F44: S | G44: IV82 | J44: HU | K44: HUEVO COMERCIAL | L44: 394.26 | M44: 46307 | O44: BELLAVISTA | P44: 2110202 | Q44: BE | R44: 0 | T44: =+VLOOKUP(Tabla1[[#This Row],[id_bodega]],'CONVERSION DATOS'!B:D,2,0) -> BELLAVISTA | U44: =+VLOOKUP(Q44,'CONVERSION DATOS'!B:D,3,0) -> PLANTA CLASIFICACION | V44: =+VLOOKUP($A$1:$A$21701,'DT HUEVO'!$A:$E,3,0) -> XL | W44: =+VLOOKUP($A$1:$A$21541,'DT HUEVO'!$A:$E,4,0) -> VERDE | X44: =+VLOOKUP(T$1:T$21701,'DT HUEVO'!$H:$K,2,0) -> - | Y44: =+VLOOKUP(T$1:T$21701,'DT HUEVO'!$H:$K,3,0) -> SANTANDER | Z44: =+VLOOKUP(A$1:A$21701,'DT HUEVO'!$A:$E,5,0) -> 0 | AA44: =IF(Tabla1[[#This Row],[GRUPO]]="PLANTA CLASIFICACION","BODEGA",IF(Tabla1[[#This Row],[GRUPO]]="BODEGA","BODEGA",Tabla1[[#This Row],[GRUPO]])) -> BODEGA | AB44: =VLOOKUP(Tabla1[[#This Row],[articulo]],'DT HUEVO'!$A:$F,6,0) -> TAT
A45: 2110302 | B45: HUEVO L X 30 CARTON VERDE CANASTA | C45: UN | D45: 66302 | F45: S | G45: IV82 | J45: HU | K45: HUEVO COMERCIAL | L45: 363.24 | M45: 46307 | O45: BELLAVISTA | P45: 2110302 | Q45: BE | R45: 0 | T45: =+VLOOKUP(Tabla1[[#This Row],[id_bodega]],'CONVERSION DATOS'!B:D,2,0) -> BELLAVISTA | U45: =+VLOOKUP(Q45,'CONVERSION DATOS'!B:D,3,0) -> PLANTA CLASIFICACION | V45: =+VLOOKUP($A$1:$A$21701,'DT HUEVO'!$A:$E,3,0) -> L | W45: =+VLOOKUP($A$1:$A$21541,'DT HUEVO'!$A:$E,4,0) -> VERDE | X45: =+VLOOKUP(T$1:T$21701,'DT HUEVO'!$H:$K,2,0) -> - | Y45: =+VLOOKUP(T$1:T$21701,'DT HUEVO'!$H:$K,3,0) -> SANTANDER | Z45: =+VLOOKUP(A$1:A$21701,'DT HUEVO'!$A:$E,5,0) -> 0 | AA45: =IF(Tabla1[[#This Row],[GRUPO]]="PLANTA CLASIFICACION","BODEGA",IF(Tabla1[[#This Row],[GRUPO]]="BODEGA","BODEGA",Tabla1[[#This Row],[GRUPO]])) -> BODEGA | AB45: =VLOOKUP(Tabla1[[#This Row],[articulo]],'DT HUEVO'!$A:$F,6,0) -> TAT
A46: 2110402 | B46: HUEVO M X 30 CARTON VERDE CANASTA | C46: UN | D46: 21279 | F46: S | G46: IV82 | J46: HU | K46: HUEVO COMERCIAL | L46: 349.55 | M46: 46307 | O46: BELLAVISTA | P46: 2110402 | Q46: BE | R46: 0 | T46: =+VLOOKUP(Tabla1[[#This Row],[id_bodega]],'CONVERSION DATOS'!B:D,2,0) -> BELLAVISTA | U46: =+VLOOKUP(Q46,'CONVERSION DATOS'!B:D,3,0) -> PLANTA CLASIFICACION | V46: =+VLOOKUP($A$1:$A$21701,'DT HUEVO'!$A:$E,3,0) -> M | W46: =+VLOOKUP($A$1:$A$21541,'DT HUEVO'!$A:$E,4,0) -> VERDE | X46: =+VLOOKUP(T$1:T$21701,'DT HUEVO'!$H:$K,2,0) -> - | Y46: =+VLOOKUP(T$1:T$21701,'DT HUEVO'!$H:$K,3,0) -> SANTANDER | Z46: =+VLOOKUP(A$1:A$21701,'DT HUEVO'!$A:$E,5,0) -> 0 | AA46: =IF(Tabla1[[#This Row],[GRUPO]]="PLANTA CLASIFICACION","BODEGA",IF(Tabla1[[#This Row],[GRUPO]]="BODEGA","BODEGA",Tabla1[[#This Row],[GRUPO]])) -> BODEGA | AB46: =VLOOKUP(Tabla1[[#This Row],[articulo]],'DT HUEVO'!$A:$F,6,0) -> TAT
A47: 2410401 | B47: HUEVO CE X 30 CARTON GRIS CANASTA | C47: UN | D47: 31991 | F47: S | G47: IV82 | J47: HU | K47: HUEVO COMERCIAL | L47: 406.83 | M47: 46307 | N47: 0 | O47: BELLAVISTA | P47: 2410401 | Q47: BE | R47: 0 | T47: =+VLOOKUP(Tabla1[[#This Row],[id_bodega]],'CONVERSION DATOS'!B:D,2,0) -> BELLAVISTA | U47: =+VLOOKUP(Q47,'CONVERSION DATOS'!B:D,3,0) -> PLANTA CLASIFICACION | V47: =+VLOOKUP($A$1:$A$21701,'DT HUEVO'!$A:$E,3,0) -> A | W47: =+VLOOKUP($A$1:$A$21541,'DT HUEVO'!$A:$E,4,0) -> GRIS SUELTO | X47: =+VLOOKUP(T$1:T$21701,'DT HUEVO'!$H:$K,2,0) -> - | Y47: =+VLOOKUP(T$1:T$21701,'DT HUEVO'!$H:$K,3,0) -> SANTANDER | Z47: =+VLOOKUP(A$1:A$21701,'DT HUEVO'!$A:$E,5,0) -> 0 | AA47: =IF(Tabla1[[#This Row],[GRUPO]]="PLANTA CLASIFICACION","BODEGA",IF(Tabla1[[#This Row],[GRUPO]]="BODEGA","BODEGA",Tabla1[[#This Row],[GRUPO]])) -> BODEGA | AB47: =VLOOKUP(Tabla1[[#This Row],[articulo]],'DT HUEVO'!$A:$F,6,0) -> HD
A48: 13324 | B48: HUEVO AA X 30 BAND GRIS AMARRADO TAPA VERDE ALAT - ESTIBADO | C48: UN | D48: 2160 | F48: S | G48: IV82 | J48: HU | K48: HUEVO COMERCIAL | L48: 470.72 | M48: 46308 | N48: 0 | O48: BODEGA BOGOTA | P48: 13324 | Q48: BO | R48: 0 | T48: =+VLOOKUP(Tabla1[[#This Row],[id_bodega]],'CONVERSION DATOS'!B:D,2,0) -> TAT CE BOGOTA | U48: =+VLOOKUP(Q48,'CONVERSION DATOS'!B:D,3,0) -> BODEGA | V48: =+VLOOKUP($A$1:$A$21701,'DT HUEVO'!$A:$E,3,0) -> AA | W48: =+VLOOKUP($A$1:$A$21541,'DT HUEVO'!$A:$E,4,0) -> EMPACADOS | X48: =+VLOOKUP(T$1:T$21701,'DT HUEVO'!$H:$K,2,0) -> CENTRO DE EMPAQUES | Y48: =+VLOOKUP(T$1:T$21701,'DT HUEVO'!$H:$K,3,0) -> CALOTO | Z48: =+VLOOKUP(A$1:A$21701,'DT HUEVO'!$A:$E,5,0) -> 0 | AA48: =IF(Tabla1[[#This Row],[GRUPO]]="PLANTA CLASIFICACION","BODEGA",IF(Tabla1[[#This Row],[GRUPO]]="BODEGA","BODEGA",Tabla1[[#This Row],[GRUPO]])) -> BODEGA | AB48: =VLOOKUP(Tabla1[[#This Row],[articulo]],'DT HUEVO'!$A:$F,6,0) -> HD
A49: 13358 | B49: HUEVO AA ROJO X 288 CARTON GRIS CAJA-EN DOCENERA-SOL NACIENT | C49: UN | D49: 197856 | F49: S | G49: IV82 | J49: HU | K49: HUEVO COMERCIAL | L49: 493.6 | M49: 46307 | O49: BODEGA BOGOTA | P49: 13358 | Q49: BO | R49: 0 | T49: =+VLOOKUP(Tabla1[[#This Row],[id_bodega]],'CONVERSION DATOS'!B:D,2,0) -> TAT CE BOGOTA | U49: =+VLOOKUP(Q49,'CONVERSION DATOS'!B:D,3,0) -> BODEGA | V49: =+VLOOKUP($A$1:$A$21701,'DT HUEVO'!$A:$E,3,0) -> AA | W49: =+VLOOKUP($A$1:$A$21541,'DT HUEVO'!$A:$E,4,0) -> EMPACADOS | X49: =+VLOOKUP(T$1:T$21701,'DT HUEVO'!$H:$K,2,0) -> CENTRO DE EMPAQUES | Y49: =+VLOOKUP(T$1:T$21701,'DT HUEVO'!$H:$K,3,0) -> CALOTO | Z49: =+VLOOKUP(A$1:A$21701,'DT HUEVO'!$A:$E,5,0) -> 0 | AA49: =IF(Tabla1[[#This Row],[GRUPO]]="PLANTA CLASIFICACION","BODEGA",IF(Tabla1[[#This Row],[GRUPO]]="BODEGA","BODEGA",Tabla1[[#This Row],[GRUPO]])) -> BODEGA | AB49: =VLOOKUP(Tabla1[[#This Row],[articulo]],'DT HUEVO'!$A:$F,6,0) -> HD
A50: 79101 | B50: HUEVO ROTO | C50: UN | D50: 7564 | E50: 0 | F50: S | G50: IV82 | H50: 0 | I50: 260 | J50: HU | K50: HUEVO COMERCIAL | L50: 96.133249 | M50: 46305 | N50: 79101 | O50: BODEGA BOGOTA | P50: 79101 | Q50: BO | R50: 0 | T50: =+VLOOKUP(Tabla1[[#This Row],[id_bodega]],'CONVERSION DATOS'!B:D,2,0) -> TAT CE BOGOTA | U50: =+VLOOKUP(Q50,'CONVERSION DATOS'!B:D,3,0) -> BODEGA | V50: =+VLOOKUP($A$1:$A$21701,'DT HUEVO'!$A:$E,3,0) -> SEGUNDA | W50: =+VLOOKUP($A$1:$A$21541,'DT HUEVO'!$A:$E,4,0) -> SEGUNDA | X50: =+VLOOKUP(T$1:T$21701,'DT HUEVO'!$H:$K,2,0) -> CENTRO DE EMPAQUES | Y50: =+VLOOKUP(T$1:T$21701,'DT HUEVO'!$H:$K,3,0) -> CALOTO | Z50: =+VLOOKUP(A$1:A$21701,'DT HUEVO'!$A:$E,5,0) -> ROTO | AA50: =IF(Tabla1[[#This Row],[GRUPO]]="PLANTA CLASIFICACION","BODEGA",IF(Tabla1[[#This Row],[GRUPO]]="BODEGA","BODEGA",Tabla1[[#This Row],[GRUPO]])) -> BODEGA | AB50: =VLOOKUP(Tabla1[[#This Row],[articulo]],'DT HUEVO'!$A:$F,6,0) -> SEGUNDA
A51: 2010301 | B51: HUEVO AA X30 CARTON GRIS CANASTA. | C51: UN | D51: 353760 | F51: S | G51: IV82 | J51: HU | K51: HUEVO COMERCIAL | L51: 376.62799 | M51: 46307 | O51: BODEGA BOGOTA | P51: 2010301 | Q51: BO | R51: 0 | T51: =+VLOOKUP(Tabla1[[#This Row],[id_bodega]],'CONVERSION DATOS'!B:D,2,0) -> TAT CE BOGOTA | U51: =+VLOOKUP(Q51,'CONVERSION DATOS'!B:D,3,0) -> BODEGA | V51: =+VLOOKUP($A$1:$A$21742,'DT HUEVO'!$A:$E,3,0) -> AA | W51: =+VLOOKUP($A$1:$A$21582,'DT HUEVO'!$A:$E,4,0) -> GRIS SUELTO | X51: =+VLOOKUP(T$1:T$21742,'DT HUEVO'!$H:$K,2,0) -> CENTRO DE EMPAQUES | Y51: =+VLOOKUP(T$1:T$21742,'DT HUEVO'!$H:$K,3,0) -> CALOTO | Z51: =+VLOOKUP(A$1:A$21742,'DT HUEVO'!$A:$E,5,0) -> 0 | AA51: =IF(Tabla1[[#This Row],[GRUPO]]="PLANTA CLASIFICACION","BODEGA",IF(Tabla1[[#This Row],[GRUPO]]="BODEGA","BODEGA",Tabla1[[#This Row],[GRUPO]])) -> BODEGA | AB51: =VLOOKUP(Tabla1[[#This Row],[articulo]],'DT HUEVO'!$A:$F,6,0) -> HD
A52: 2410401 | B52: HUEVO CE X 30 CARTON GRIS CANASTA | C52: UN | D52: 77814 | F52: S | G52: IV82 | J52: HU | K52: HUEVO COMERCIAL | L52: 406.82669 | M52: 46307 | N52: 0 | O52: BODEGA BOGOTA | P52: 2410401 | Q52: BO | R52: 0 | T52: =+VLOOKUP(Tabla1[[#This Row],[id_bodega]],'CONVERSION DATOS'!B:D,2,0) -> TAT CE BOGOTA | U52: =+VLOOKUP(Q52,'CONVERSION DATOS'!B:D,3,0) -> BODEGA | V52: =+VLOOKUP($A$1:$A$21742,'DT HUEVO'!$A:$E,3,0) -> A | W52: =+VLOOKUP($A$1:$A$21582,'DT HUEVO'!$A:$E,4,0) -> GRIS SUELTO | X52: =+VLOOKUP(T$1:T$21742,'DT HUEVO'!$H:$K,2,0) -> CENTRO DE EMPAQUES | Y52: =+VLOOKUP(T$1:T$21742,'DT HUEVO'!$H:$K,3,0) -> CALOTO | Z52: =+VLOOKUP(A$1:A$21742,'DT HUEVO'!$A:$E,5,0) -> 0 | AA52: =IF(Tabla1[[#This Row],[GRUPO]]="PLANTA CLASIFICACION","BODEGA",IF(Tabla1[[#This Row],[GRUPO]]="BODEGA","BODEGA",Tabla1[[#This Row],[GRUPO]])) -> BODEGA | AB52: =VLOOKUP(Tabla1[[#This Row],[articulo]],'DT HUEVO'!$A:$F,6,0) -> HD
A53: 10601 | B53: HUEVO C X30 CARTON GRIS | C53: UN | D53: 14814 | E53: 0 | F53: S | G53: IV82 | H53: 0 | I53: 400 | J53: HU | K53: HUEVO COMERCIAL | L53: 130.24 | M53: 46307 | N53: 10601 | O53: BARRANQUILLA CLASIFICACION | P53: 10601 | Q53: BQ | R53: 0 | T53: =+VLOOKUP(Tabla1[[#This Row],[id_bodega]],'CONVERSION DATOS'!B:D,2,0) -> TAT CE BARRANQUILLA | U53: =+VLOOKUP(Q53,'CONVERSION DATOS'!B:D,3,0) -> BODEGA | V53: =+VLOOKUP($A$1:$A$21742,'DT HUEVO'!$A:$E,3,0) -> C | W53: =+VLOOKUP($A$1:$A$21582,'DT HUEVO'!$A:$E,4,0) -> GRIS SUELTO | X53: =+VLOOKUP(T$1:T$21742,'DT HUEVO'!$H:$K,2,0) -> CENTRO DE EMPAQUES | Y53: =+VLOOKUP(T$1:T$21742,'DT HUEVO'!$H:$K,3,0) -> SANTANDER | Z53: =+VLOOKUP(A$1:A$21742,'DT HUEVO'!$A:$E,5,0) -> 0 | AA53: =IF(Tabla1[[#This Row],[GRUPO]]="PLANTA CLASIFICACION","BODEGA",IF(Tabla1[[#This Row],[GRUPO]]="BODEGA","BODEGA",Tabla1[[#This Row],[GRUPO]])) -> BODEGA | AB53: =VLOOKUP(Tabla1[[#This Row],[articulo]],'DT HUEVO'!$A:$F,6,0) -> MAY
A54: 13324 | B54: HUEVO AA X 30 BAND GRIS AMARRADO TAPA VERDE ALAT - ESTIBADO | C54: UN | D54: 2610 | F54: S | G54: IV82 | J54: HU | K54: HUEVO COMERCIAL | L54: 470.72 | M54: 46308 | N54: 0 | O54: BARRANQUILLA CLASIFICACION | P54: 13324 | Q54: BQ | R54: 0 | T54: =+VLOOKUP(Tabla1[[#This Row],[id_bodega]],'CONVERSION DATOS'!B:D,2,0) -> TAT CE BARRANQUILLA | U54: =+VLOOKUP(Q54,'CONVERSION DATOS'!B:D,3,0) -> BODEGA | V54: =+VLOOKUP($A$1:$A$21742,'DT HUEVO'!$A:$E,3,0) -> AA | W54: =+VLOOKUP($A$1:$A$21582,'DT HUEVO'!$A:$E,4,0) -> EMPACADOS | X54: =+VLOOKUP(T$1:T$21742,'DT HUEVO'!$H:$K,2,0) -> CENTRO DE EMPAQUES | Y54: =+VLOOKUP(T$1:T$21742,'DT HUEVO'!$H:$K,3,0) -> SANTANDER | Z54: =+VLOOKUP(A$1:A$21742,'DT HUEVO'!$A:$E,5,0) -> 0 | AA54: =IF(Tabla1[[#This Row],[GRUPO]]="PLANTA CLASIFICACION","BODEGA",IF(Tabla1[[#This Row],[GRUPO]]="BODEGA","BODEGA",Tabla1[[#This Row],[GRUPO]])) -> BODEGA | AB54: =VLOOKUP(Tabla1[[#This Row],[articulo]],'DT HUEVO'!$A:$F,6,0) -> HD
A55: 13358 | B55: HUEVO AA ROJO X 288 CARTON GRIS CAJA-EN DOCENERA-SOL NACIENT | C55: UN | D55: 72000 | F55: S | G55: IV82 | J55: HU | K55: HUEVO COMERCIAL | L55: 493.6 | M55: 46308 | O55: BARRANQUILLA CLASIFICACION | P55: 13358 | Q55: BQ | R55: 0 | T55: =+VLOOKUP(Tabla1[[#This Row],[id_bodega]],'CONVERSION DATOS'!B:D,2,0) -> TAT CE BARRANQUILLA | U55: =+VLOOKUP(Q55,'CONVERSION DATOS'!B:D,3,0) -> BODEGA | V55: =+VLOOKUP($A$1:$A$21742,'DT HUEVO'!$A:$E,3,0) -> AA | W55: =+VLOOKUP($A$1:$A$21582,'DT HUEVO'!$A:$E,4,0) -> EMPACADOS | X55: =+VLOOKUP(T$1:T$21742,'DT HUEVO'!$H:$K,2,0) -> CENTRO DE EMPAQUES | Y55: =+VLOOKUP(T$1:T$21742,'DT HUEVO'!$H:$K,3,0) -> SANTANDER | Z55: =+VLOOKUP(A$1:A$21742,'DT HUEVO'!$A:$E,5,0) -> 0 | AA55: =IF(Tabla1[[#This Row],[GRUPO]]="PLANTA CLASIFICACION","BODEGA",IF(Tabla1[[#This Row],[GRUPO]]="BODEGA","BODEGA",Tabla1[[#This Row],[GRUPO]])) -> BODEGA | AB55: =VLOOKUP(Tabla1[[#This Row],[articulo]],'DT HUEVO'!$A:$F,6,0) -> HD
A56: 13423 | B56: HUEVO A X 30 BAND GRIS AMARRADO SOL NACIENTE - BQ - ESTIBADO | C56: UN | D56: 82590 | F56: S | G56: IV82 | J56: HU | K56: HUEVO COMERCIAL | L56: 406.83 | M56: 46308 | N56: 0 | O56: BARRANQUILLA CLASIFICACION | P56: 13423 | Q56: BQ | R56: 0 | T56: =+VLOOKUP(Tabla1[[#This Row],[id_bodega]],'CONVERSION DATOS'!B:D,2,0) -> TAT CE BARRANQUILLA | U56: =+VLOOKUP(Q56,'CONVERSION DATOS'!B:D,3,0) -> BODEGA | V56: =+VLOOKUP($A$1:$A$21742,'DT HUEVO'!$A:$E,3,0) -> A | W56: =+VLOOKUP($A$1:$A$21582,'DT HUEVO'!$A:$E,4,0) -> EMPACADOS | X56: =+VLOOKUP(T$1:T$21742,'DT HUEVO'!$H:$K,2,0) -> CENTRO DE EMPAQUES | Y56: =+VLOOKUP(T$1:T$21742,'DT HUEVO'!$H:$K,3,0) -> SANTANDER | Z56: =+VLOOKUP(A$1:A$21742,'DT HUEVO'!$A:$E,5,0) -> 0 | AA56: =IF(Tabla1[[#This Row],[GRUPO]]="PLANTA CLASIFICACION","BODEGA",IF(Tabla1[[#This Row],[GRUPO]]="BODEGA","BODEGA",Tabla1[[#This Row],[GRUPO]])) -> BODEGA | AB56: =VLOOKUP(Tabla1[[#This Row],[articulo]],'DT HUEVO'!$A:$F,6,0) -> HD
A57: 13424 | B57: HUEVO A X 30 BAND GRIS AMARRADO ALAT - ESTIBADO | C57: UN | D57: 189360 | F57: S | G57: IV82 | J57: HU | K57: HUEVO COMERCIAL | L57: 373.46 | M57: 46308 | N57: 0 | O57: BARRANQUILLA CLASIFICACION | P57: 13424 | Q57: BQ | R57: 0 | T57: =+VLOOKUP(Tabla1[[#This Row],[id_bodega]],'CONVERSION DATOS'!B:D,2,0) -> TAT CE BARRANQUILLA | U57: =+VLOOKUP(Q57,'CONVERSION DATOS'!B:D,3,0) -> BODEGA | V57: =+VLOOKUP($A$1:$A$21742,'DT HUEVO'!$A:$E,3,0) -> A | W57: =+VLOOKUP($A$1:$A$21582,'DT HUEVO'!$A:$E,4,0) -> EMPACADOS | X57: =+VLOOKUP(T$1:T$21742,'DT HUEVO'!$H:$K,2,0) -> CENTRO DE EMPAQUES | Y57: =+VLOOKUP(T$1:T$21742,'DT HUEVO'!$H:$K,3,0) -> SANTANDER | Z57: =+VLOOKUP(A$1:A$21742,'DT HUEVO'!$A:$E,5,0) -> 0 | AA57: =IF(Tabla1[[#This Row],[GRUPO]]="PLANTA CLASIFICACION","BODEGA",IF(Tabla1[[#This Row],[GRUPO]]="BODEGA","BODEGA",Tabla1[[#This Row],[GRUPO]])) -> BODEGA | AB57: =VLOOKUP(Tabla1[[#This Row],[articulo]],'DT HUEVO'!$A:$F,6,0) -> HD
A58: 13525 | B58: HUEVO B X 30 BAND GRIS AMARRADO ALAT - ESTIBADO | C58: UN | D58: 7500 | F58: S | G58: IV82 | J58: HU | K58: HUEVO COMERCIAL | L58: 389.01 | M58: 46308 | N58: 0 | O58: BARRANQUILLA CLASIFICACION | P58: 13525 | Q58: BQ | R58: 0 | T58: =+VLOOKUP(Tabla1[[#This Row],[id_bodega]],'CONVERSION DATOS'!B:D,2,0) -> TAT CE BARRANQUILLA | U58: =+VLOOKUP(Q58,'CONVERSION DATOS'!B:D,3,0) -> BODEGA | V58: =+VLOOKUP($A$1:$A$21742,'DT HUEVO'!$A:$E,3,0) -> B | W58: =+VLOOKUP($A$1:$A$21582,'DT HUEVO'!$A:$E,4,0) -> EMPACADOS | X58: =+VLOOKUP(T$1:T$21742,'DT HUEVO'!$H:$K,2,0) -> CENTRO DE EMPAQUES | Y58: =+VLOOKUP(T$1:T$21742,'DT HUEVO'!$H:$K,3,0) -> SANTANDER | Z58: =+VLOOKUP(A$1:A$21742,'DT HUEVO'!$A:$E,5,0) -> 0 | AA58: =IF(Tabla1[[#This Row],[GRUPO]]="PLANTA CLASIFICACION","BODEGA",IF(Tabla1[[#This Row],[GRUPO]]="BODEGA","BODEGA",Tabla1[[#This Row],[GRUPO]])) -> BODEGA | AB58: =VLOOKUP(Tabla1[[#This Row],[articulo]],'DT HUEVO'!$A:$F,6,0) -> HD
A59: 72001 | B59: HUEVO SUCIO SIN MARCA X30 BANDEJA GRIS | C59: UN | D59: 927 | E59: 0 | F59: S | G59: IV82 | H59: 0 | I59: 400 | J59: HU | K59: HUEVO COMERCIAL | L59: 162.88 | M59: 46308 | N59: 72001 | O59: BARRANQUILLA CLASIFICACION | P59: 72001 | Q59: BQ | R59: 0 | T59: =+VLOOKUP(Tabla1[[#This Row],[id_bodega]],'CONVERSION DATOS'!B:D,2,0) -> TAT CE BARRANQUILLA | U59: =+VLOOKUP(Q59,'CONVERSION DATOS'!B:D,3,0) -> BODEGA | V59: =+VLOOKUP($A$1:$A$21742,'DT HUEVO'!$A:$E,3,0) -> SEGUNDA | W59: =+VLOOKUP($A$1:$A$21582,'DT HUEVO'!$A:$E,4,0) -> SEGUNDA | X59: =+VLOOKUP(T$1:T$21742,'DT HUEVO'!$H:$K,2,0) -> CENTRO DE EMPAQUES | Y59: =+VLOOKUP(T$1:T$21742,'DT HUEVO'!$H:$K,3,0) -> SANTANDER | Z59: =+VLOOKUP(A$1:A$21742,'DT HUEVO'!$A:$E,5,0) -> SUCIO | AA59: =IF(Tabla1[[#This Row],[GRUPO]]="PLANTA CLASIFICACION","BODEGA",IF(Tabla1[[#This Row],[GRUPO]]="BODEGA","BODEGA",Tabla1[[#This Row],[GRUPO]])) -> BODEGA | AB59: =VLOOKUP(Tabla1[[#This Row],[articulo]],'DT HUEVO'!$A:$F,6,0) -> SEGUNDA
A60: 112268 | B60: HUEVO XL X 15 PET CAJA X 300. | C60: UN | D60: 900 | F60: S | G60: IV82 | J60: HU | K60: HUEVO COMERCIAL | L60: 684.07 | M60: 46304 | O60: BARRANQUILLA CLASIFICACION | P60: 112268 | Q60: BQ | R60: 0 | T60: =+VLOOKUP(Tabla1[[#This Row],[id_bodega]],'CONVERSION DATOS'!B:D,2,0) -> TAT CE BARRANQUILLA | U60: =+VLOOKUP(Q60,'CONVERSION DATOS'!B:D,3,0) -> BODEGA | V60: =+VLOOKUP($A$1:$A$21742,'DT HUEVO'!$A:$E,3,0) -> XL | W60: =+VLOOKUP($A$1:$A$21582,'DT HUEVO'!$A:$E,4,0) -> EMPACADOS | X60: =+VLOOKUP(T$1:T$21742,'DT HUEVO'!$H:$K,2,0) -> CENTRO DE EMPAQUES | Y60: =+VLOOKUP(T$1:T$21742,'DT HUEVO'!$H:$K,3,0) -> SANTANDER | Z60: =+VLOOKUP(A$1:A$21742,'DT HUEVO'!$A:$E,5,0) -> 0 | AA60: =IF(Tabla1[[#This Row],[GRUPO]]="PLANTA CLASIFICACION","BODEGA",IF(Tabla1[[#This Row],[GRUPO]]="BODEGA","BODEGA",Tabla1[[#This Row],[GRUPO]])) -> BODEGA | AB60: =VLOOKUP(Tabla1[[#This Row],[articulo]],'DT HUEVO'!$A:$F,6,0) -> AU/FS/GS
A61: 112357 | B61: HUEVO L X 12 PET CAJA X 120 | C61: UN | D61: 240 | F61: S | G61: IV82 | J61: HU | K61: HUEVO COMERCIAL | L61: 638.05 | M61: 46304 | O61: BARRANQUILLA CLASIFICACION | P61: 112357 | Q61: BQ | R61: 0 | T61: =+VLOOKUP(Tabla1[[#This Row],[id_bodega]],'CONVERSION DATOS'!B:D,2,0) -> TAT CE BARRANQUILLA | U61: =+VLOOKUP(Q61,'CONVERSION DATOS'!B:D,3,0) -> BODEGA | V61: =+VLOOKUP($A$1:$A$21742,'DT HUEVO'!$A:$E,3,0) -> L | W61: =+VLOOKUP($A$1:$A$21582,'DT HUEVO'!$A:$E,4,0) -> EMPACADOS | X61: =+VLOOKUP(T$1:T$21742,'DT HUEVO'!$H:$K,2,0) -> CENTRO DE EMPAQUES | Y61: =+VLOOKUP(T$1:T$21742,'DT HUEVO'!$H:$K,3,0) -> SANTANDER | Z61: =+VLOOKUP(A$1:A$21742,'DT HUEVO'!$A:$E,5,0) -> 0 | AA61: =IF(Tabla1[[#This Row],[GRUPO]]="PLANTA CLASIFICACION","BODEGA",IF(Tabla1[[#This Row],[GRUPO]]="BODEGA","BODEGA",Tabla1[[#This Row],[GRUPO]])) -> BODEGA | AB61: =VLOOKUP(Tabla1[[#This Row],[articulo]],'DT HUEVO'!$A:$F,6,0) -> AU/FS/GS
A62: 112379 | B62: HUEVO L X 30 PET CAJA X 300 | C62: UN | D62: 300 | F62: S | G62: IV82 | J62: HU | K62: HUEVO COMERCIAL | L62: 538.38 | M62: 46304 | O62: BARRANQUILLA CLASIFICACION | P62: 112379 | Q62: BQ | R62: 0 | T62: =+VLOOKUP(Tabla1[[#This Row],[id_bodega]],'CONVERSION DATOS'!B:D,2,0) -> TAT CE BARRANQUILLA | U62: =+VLOOKUP(Q62,'CONVERSION DATOS'!B:D,3,0) -> BODEGA | V62: =+VLOOKUP($A$1:$A$21747,'DT HUEVO'!$A:$E,3,0) -> L | W62: =+VLOOKUP($A$1:$A$21587,'DT HUEVO'!$A:$E,4,0) -> EMPACADOS | X62: =+VLOOKUP(T$1:T$21747,'DT HUEVO'!$H:$K,2,0) -> CENTRO DE EMPAQUES | Y62: =+VLOOKUP(T$1:T$21747,'DT HUEVO'!$H:$K,3,0) -> SANTANDER | Z62: =+VLOOKUP(A$1:A$21747,'DT HUEVO'!$A:$E,5,0) -> 0 | AA62: =IF(Tabla1[[#This Row],[GRUPO]]="PLANTA CLASIFICACION","BODEGA",IF(Tabla1[[#This Row],[GRUPO]]="BODEGA","BODEGA",Tabla1[[#This Row],[GRUPO]])) -> BODEGA | AB62: =VLOOKUP(Tabla1[[#This Row],[articulo]],'DT HUEVO'!$A:$F,6,0) -> AU/FS/GS
A63: 114268 | B63: HUEVO XL X 15 PET CAJA X 300 PV. | C63: UN | D63: 900 | F63: S | G63: IV82 | J63: HU | K63: HUEVO COMERCIAL | L63: 717.66 | M63: 46304 | O63: BARRANQUILLA CLASIFICACION | P63: 114268 | Q63: BQ | R63: 0 | T63: =+VLOOKUP(Tabla1[[#This Row],[id_bodega]],'CONVERSION DATOS'!B:D,2,0) -> TAT CE BARRANQUILLA | U63: =+VLOOKUP(Q63,'CONVERSION DATOS'!B:D,3,0) -> BODEGA | V63: =+VLOOKUP($A$1:$A$21747,'DT HUEVO'!$A:$E,3,0) -> XL | W63: =+VLOOKUP($A$1:$A$21587,'DT HUEVO'!$A:$E,4,0) -> EMPACADOS | X63: =+VLOOKUP(T$1:T$21747,'DT HUEVO'!$H:$K,2,0) -> CENTRO DE EMPAQUES | Y63: =+VLOOKUP(T$1:T$21747,'DT HUEVO'!$H:$K,3,0) -> SANTANDER | Z63: =+VLOOKUP(A$1:A$21747,'DT HUEVO'!$A:$E,5,0) -> 0 | AA63: =IF(Tabla1[[#This Row],[GRUPO]]="PLANTA CLASIFICACION","BODEGA",IF(Tabla1[[#This Row],[GRUPO]]="BODEGA","BODEGA",Tabla1[[#This Row],[GRUPO]])) -> BODEGA | AB63: =VLOOKUP(Tabla1[[#This Row],[articulo]],'DT HUEVO'!$A:$F,6,0) -> AU/FS/GS
A64: 114357 | B64: HUEVO L X 12 PET CAJA X 120 PV. | C64: UN | D64: 3240 | F64: S | G64: IV82 | J64: HU | K64: HUEVO COMERCIAL | L64: 639.68 | M64: 46304 | O64: BARRANQUILLA CLASIFICACION | P64: 114357 | Q64: BQ | R64: 0 | T64: =+VLOOKUP(Tabla1[[#This Row],[id_bodega]],'CONVERSION DATOS'!B:D,2,0) -> TAT CE BARRANQUILLA | U64: =+VLOOKUP(Q64,'CONVERSION DATOS'!B:D,3,0) -> BODEGA | V64: =+VLOOKUP($A$1:$A$21747,'DT HUEVO'!$A:$E,3,0) -> L | W64: =+VLOOKUP($A$1:$A$21587,'DT HUEVO'!$A:$E,4,0) -> EMPACADOS | X64: =+VLOOKUP(T$1:T$21747,'DT HUEVO'!$H:$K,2,0) -> CENTRO DE EMPAQUES | Y64: =+VLOOKUP(T$1:T$21747,'DT HUEVO'!$H:$K,3,0) -> SANTANDER | Z64: =+VLOOKUP(A$1:A$21747,'DT HUEVO'!$A:$E,5,0) -> 0 | AA64: =IF(Tabla1[[#This Row],[GRUPO]]="PLANTA CLASIFICACION","BODEGA",IF(Tabla1[[#This Row],[GRUPO]]="BODEGA","BODEGA",Tabla1[[#This Row],[GRUPO]])) -> BODEGA | AB64: =VLOOKUP(Tabla1[[#This Row],[articulo]],'DT HUEVO'!$A:$F,6,0) -> AU/FS/GS
A65: 114379 | B65: HUEVO L X 30 PET CAJA X 300 PV. | C65: UN | D65: 600 | F65: S | G65: IV82 | J65: HU | K65: HUEVO COMERCIAL | L65: 570.95 | M65: 46304 | O65: BARRANQUILLA CLASIFICACION | P65: 114379 | Q65: BQ | R65: 0 | T65: =+VLOOKUP(Tabla1[[#This Row],[id_bodega]],'CONVERSION DATOS'!B:D,2,0) -> TAT CE BARRANQUILLA | U65: =+VLOOKUP(Q65,'CONVERSION DATOS'!B:D,3,0) -> BODEGA | V65: =+VLOOKUP($A$1:$A$21747,'DT HUEVO'!$A:$E,3,0) -> L | W65: =+VLOOKUP($A$1:$A$21587,'DT HUEVO'!$A:$E,4,0) -> EMPACADOS | X65: =+VLOOKUP(T$1:T$21747,'DT HUEVO'!$H:$K,2,0) -> CENTRO DE EMPAQUES | Y65: =+VLOOKUP(T$1:T$21747,'DT HUEVO'!$H:$K,3,0) -> SANTANDER | Z65: =+VLOOKUP(A$1:A$21747,'DT HUEVO'!$A:$E,5,0) -> 0 | AA65: =IF(Tabla1[[#This Row],[GRUPO]]="PLANTA CLASIFICACION","BODEGA",IF(Tabla1[[#This Row],[GRUPO]]="BODEGA","BODEGA",Tabla1[[#This Row],[GRUPO]])) -> BODEGA | AB65: =VLOOKUP(Tabla1[[#This Row],[articulo]],'DT HUEVO'!$A:$F,6,0) -> AU/FS/GS
A66: 2010108 | B66: HUEVO YUMBO X 20 CARTON VERDE CANASTA - BARRANQUILLA | C66: UN | D66: 13 | F66: S | G66: IV82 | J66: HU | K66: HUEVO COMERCIAL | L66: 629.68 | M66: 46307 | N66: 10108 | O66: BARRANQUILLA CLASIFICACION | P66: 2010108 | Q66: BQ | R66: 0 | T66: =+VLOOKUP(Tabla1[[#This Row],[id_bodega]],'CONVERSION DATOS'!B:D,2,0) -> TAT CE BARRANQUILLA | U66: =+VLOOKUP(Q66,'CONVERSION DATOS'!B:D,3,0) -> BODEGA | V66: =+VLOOKUP($A$1:$A$21747,'DT HUEVO'!$A:$E,3,0) -> YUMBO | W66: =+VLOOKUP($A$1:$A$21587,'DT HUEVO'!$A:$E,4,0) -> VERDE | X66: =+VLOOKUP(T$1:T$21747,'DT HUEVO'!$H:$K,2,0) -> CENTRO DE EMPAQUES | Y66: =+VLOOKUP(T$1:T$21747,'DT HUEVO'!$H:$K,3,0) -> SANTANDER | Z66: =+VLOOKUP(A$1:A$21747,'DT HUEVO'!$A:$E,5,0) -> 0 | AA66: =IF(Tabla1[[#This Row],[GRUPO]]="PLANTA CLASIFICACION","BODEGA",IF(Tabla1[[#This Row],[GRUPO]]="BODEGA","BODEGA",Tabla1[[#This Row],[GRUPO]])) -> BODEGA | AB66: =VLOOKUP(Tabla1[[#This Row],[articulo]],'DT HUEVO'!$A:$F,6,0) -> TAT
A67: 2010301 | B67: HUEVO AA X30 CARTON GRIS CANASTA. | C67: UN | D67: 203100 | F67: S | G67: IV82 | J67: HU | K67: HUEVO COMERCIAL | L67: 376.81287 | M67: 46308 | O67: BARRANQUILLA CLASIFICACION | P67: 2010301 | Q67: BQ | R67: 0 | T67: =+VLOOKUP(Tabla1[[#This Row],[id_bodega]],'CONVERSION DATOS'!B:D,2,0) -> TAT CE BARRANQUILLA | U67: =+VLOOKUP(Q67,'CONVERSION DATOS'!B:D,3,0) -> BODEGA | V67: =+VLOOKUP($A$1:$A$21747,'DT HUEVO'!$A:$E,3,0) -> AA | W67: =+VLOOKUP($A$1:$A$21587,'DT HUEVO'!$A:$E,4,0) -> GRIS SUELTO | X67: =+VLOOKUP(T$1:T$21747,'DT HUEVO'!$H:$K,2,0) -> CENTRO DE EMPAQUES | Y67: =+VLOOKUP(T$1:T$21747,'DT HUEVO'!$H:$K,3,0) -> SANTANDER | Z67: =+VLOOKUP(A$1:A$21747,'DT HUEVO'!$A:$E,5,0) -> 0 | AA67: =IF(Tabla1[[#This Row],[GRUPO]]="PLANTA CLASIFICACION","BODEGA",IF(Tabla1[[#This Row],[GRUPO]]="BODEGA","BODEGA",Tabla1[[#This Row],[GRUPO]])) -> BODEGA | AB67: =VLOOKUP(Tabla1[[#This Row],[articulo]],'DT HUEVO'!$A:$F,6,0) -> HD
A68: 2010501 | B68: HUEVO B X30 CARTON GRIS CANASTA. | C68: UN | D68: 765147 | F68: S | G68: IV82 | J68: HU | K68: HUEVO COMERCIAL | L68: 319.65 | M68: 46308 | O68: BARRANQUILLA CLASIFICACION | P68: 2010501 | Q68: BQ | R68: 0 | T68: =+VLOOKUP(Tabla1[[#This Row],[id_bodega]],'CONVERSION DATOS'!B:D,2,0) -> TAT CE BARRANQUILLA | U68: =+VLOOKUP(Q68,'CONVERSION DATOS'!B:D,3,0) -> BODEGA | V68: =+VLOOKUP($A$1:$A$21766,'DT HUEVO'!$A:$E,3,0) -> B | W68: =+VLOOKUP($A$1:$A$21606,'DT HUEVO'!$A:$E,4,0) -> GRIS SUELTO | X68: =+VLOOKUP(T$1:T$21766,'DT HUEVO'!$H:$K,2,0) -> CENTRO DE EMPAQUES | Y68: =+VLOOKUP(T$1:T$21766,'DT HUEVO'!$H:$K,3,0) -> SANTANDER | Z68: =+VLOOKUP(A$1:A$21766,'DT HUEVO'!$A:$E,5,0) -> 0 | AA68: =IF(Tabla1[[#This Row],[GRUPO]]="PLANTA CLASIFICACION","BODEGA",IF(Tabla1[[#This Row],[GRUPO]]="BODEGA","BODEGA",Tabla1[[#This Row],[GRUPO]])) -> BODEGA | AB68: =VLOOKUP(Tabla1[[#This Row],[articulo]],'DT HUEVO'!$A:$F,6,0) -> hd
A69: 2410401 | B69: HUEVO CE X 30 CARTON GRIS CANASTA | C69: UN | D69: 197916 | F69: S | G69: IV82 | J69: HU | K69: HUEVO COMERCIAL | L69: 406.83 | M69: 46308 | N69: 0 | O69: BARRANQUILLA CLASIFICACION | P69: 2410401 | Q69: BQ | R69: 0 | T69: =+VLOOKUP(Tabla1[[#This Row],[id_bodega]],'CONVERSION DATOS'!B:D,2,0) -> TAT CE BARRANQUILLA | U69: =+VLOOKUP(Q69,'CONVERSION DATOS'!B:D,3,0) -> BODEGA | V69: =+VLOOKUP($A$1:$A$21766,'DT HUEVO'!$A:$E,3,0) -> A | W69: =+VLOOKUP($A$1:$A$21606,'DT HUEVO'!$A:$E,4,0) -> GRIS SUELTO | X69: =+VLOOKUP(T$1:T$21766,'DT HUEVO'!$H:$K,2,0) -> CENTRO DE EMPAQUES | Y69: =+VLOOKUP(T$1:T$21766,'DT HUEVO'!$H:$K,3,0) -> SANTANDER | Z69: =+VLOOKUP(A$1:A$21766,'DT HUEVO'!$A:$E,5,0) -> 0 | AA69: =IF(Tabla1[[#This Row],[GRUPO]]="PLANTA CLASIFICACION","BODEGA",IF(Tabla1[[#This Row],[GRUPO]]="BODEGA","BODEGA",Tabla1[[#This Row],[GRUPO]])) -> BODEGA | AB69: =VLOOKUP(Tabla1[[#This Row],[articulo]],'DT HUEVO'!$A:$F,6,0) -> HD
A70: 10401 | B70: HUEVO A X30 CARTON GRIS | C70: UN | D70: 1041 | F70: S | G70: IV82 | J70: HU | K70: HUEVO COMERCIAL | L70: 259.73 | M70: 46307 | N70: 10401 | O70: CENTRO DE EMPAQUES CALI | P70: 10401 | Q70: CA | R70: 0 | T70: =+VLOOKUP(Tabla1[[#This Row],[id_bodega]],'CONVERSION DATOS'!B:D,2,0) -> TAT CE CALI | U70: =+VLOOKUP(Q70,'CONVERSION DATOS'!B:D,3,0) -> BODEGA | V70: =+VLOOKUP($A$1:$A$21766,'DT HUEVO'!$A:$E,3,0) -> A | W70: =+VLOOKUP($A$1:$A$21606,'DT HUEVO'!$A:$E,4,0) -> GRIS SUELTO | X70: =+VLOOKUP(T$1:T$21766,'DT HUEVO'!$H:$K,2,0) -> OCCIDENTE | Y70: =+VLOOKUP(T$1:T$21766,'DT HUEVO'!$H:$K,3,0) -> CALOTO | Z70: =+VLOOKUP(A$1:A$21766,'DT HUEVO'!$A:$E,5,0) -> 0 | AA70: =IF(Tabla1[[#This Row],[GRUPO]]="PLANTA CLASIFICACION","BODEGA",IF(Tabla1[[#This Row],[GRUPO]]="BODEGA","BODEGA",Tabla1[[#This Row],[GRUPO]])) -> BODEGA | AB70: =VLOOKUP(Tabla1[[#This Row],[articulo]],'DT HUEVO'!$A:$F,6,0) -> MAY
A71: 13324 | B71: HUEVO AA X 30 BAND GRIS AMARRADO TAPA VERDE ALAT - ESTIBADO | C71: UN | D71: 1800 | F71: S | G71: IV82 | J71: HU | K71: HUEVO COMERCIAL | L71: 470.72 | M71: 46307 | N71: 0 | O71: CENTRO DE EMPAQUES CALI | P71: 13324 | Q71: CA | R71: 0 | T71: =+VLOOKUP(Tabla1[[#This Row],[id_bodega]],'CONVERSION DATOS'!B:D,2,0) -> TAT CE CALI | U71: =+VLOOKUP(Q71,'CONVERSION DATOS'!B:D,3,0) -> BODEGA | V71: =+VLOOKUP($A$1:$A$21766,'DT HUEVO'!$A:$E,3,0) -> AA | W71: =+VLOOKUP($A$1:$A$21606,'DT HUEVO'!$A:$E,4,0) -> EMPACADOS | X71: =+VLOOKUP(T$1:T$21766,'DT HUEVO'!$H:$K,2,0) -> OCCIDENTE | Y71: =+VLOOKUP(T$1:T$21766,'DT HUEVO'!$H:$K,3,0) -> CALOTO | Z71: =+VLOOKUP(A$1:A$21766,'DT HUEVO'!$A:$E,5,0) -> 0 | AA71: =IF(Tabla1[[#This Row],[GRUPO]]="PLANTA CLASIFICACION","BODEGA",IF(Tabla1[[#This Row],[GRUPO]]="BODEGA","BODEGA",Tabla1[[#This Row],[GRUPO]])) -> BODEGA | AB71: =VLOOKUP(Tabla1[[#This Row],[articulo]],'DT HUEVO'!$A:$F,6,0) -> HD
A72: 13420 | B72: HUEVO A X 30 BAND GRIS AMARRADO SOL NACIENTE - ESTIBADO | C72: UN | D72: 3600 | F72: S | G72: IV82 | J72: HU | K72: HUEVO COMERCIAL | L72: 404.41 | M72: 46307 | O72: CENTRO DE EMPAQUES CALI | P72: 13420 | Q72: CA | R72: 0 | T72: =+VLOOKUP(Tabla1[[#This Row],[id_bodega]],'CONVERSION DATOS'!B:D,2,0) -> TAT CE CALI | U72: =+VLOOKUP(Q72,'CONVERSION DATOS'!B:D,3,0) -> BODEGA | V72: =+VLOOKUP($A$1:$A$21766,'DT HUEVO'!$A:$E,3,0) -> A | W72: =+VLOOKUP($A$1:$A$21606,'DT HUEVO'!$A:$E,4,0) -> EMPACADOS | X72: =+VLOOKUP(T$1:T$21766,'DT HUEVO'!$H:$K,2,0) -> OCCIDENTE | Y72: =+VLOOKUP(T$1:T$21766,'DT HUEVO'!$H:$K,3,0) -> CALOTO | Z72: =+VLOOKUP(A$1:A$21766,'DT HUEVO'!$A:$E,5,0) -> 0 | AA72: =IF(Tabla1[[#This Row],[GRUPO]]="PLANTA CLASIFICACION","BODEGA",IF(Tabla1[[#This Row],[GRUPO]]="BODEGA","BODEGA",Tabla1[[#This Row],[GRUPO]])) -> BODEGA | AB72: =VLOOKUP(Tabla1[[#This Row],[articulo]],'DT HUEVO'!$A:$F,6,0) -> HD
A73: 100 | B73: HUEVO SIN CLASIFICAR ROJO | C73: UN | D73: 132400 | F73: S | G73: IV82 | J73: HU | K73: HUEVO COMERCIAL | L73: 376.83 | M73: 46307 | N73: 100 | O73: PLANTA CLASIFICADORA INTEGRADO JP | P73: 100 | Q73: CLAT1 | R73: 0 | T73: =+VLOOKUP(Tabla1[[#This Row],[id_bodega]],'CONVERSION DATOS'!B:D,2,0) -> PLANTA CLASIFICADORA INTEGRADO JP | U73: =+VLOOKUP(Q73,'CONVERSION DATOS'!B:D,3,0) -> HUEVO SIN CLASIFICAR | V73: =+VLOOKUP($A$1:$A$21766,'DT HUEVO'!$A:$E,3,0) -> HUEVO SIN CLASIFICAR | W73: =+VLOOKUP($A$1:$A$21606,'DT HUEVO'!$A:$E,4,0) -> HUEVO SIN CLASIFICAR | X73: =+VLOOKUP(T$1:T$21766,'DT HUEVO'!$H:$K,2,0) -> COSTA | Y73: =+VLOOKUP(T$1:T$21766,'DT HUEVO'!$H:$K,3,0) -> 0 | Z73: =+VLOOKUP(A$1:A$21766,'DT HUEVO'!$A:$E,5,0) -> HUEVO SIN CLASIFICAR | AA73: =IF(Tabla1[[#This Row],[GRUPO]]="PLANTA CLASIFICACION","BODEGA",IF(Tabla1[[#This Row],[GRUPO]]="BODEGA","BODEGA",Tabla1[[#This Row],[GRUPO]])) -> HUEVO SIN CLASIFICAR | AB73: =VLOOKUP(Tabla1[[#This Row],[articulo]],'DT HUEVO'!$A:$F,6,0) -> SIN CL
A74: 100 | B74: HUEVO SIN CLASIFICAR ROJO | C74: UN | D74: 639331 | F74: S | G74: IV82 | J74: HU | K74: HUEVO COMERCIAL | L74: 376.83 | M74: 46306 | N74: 100 | O74: CLASIFICADORA LANZA | P74: 100 | Q74: CLKI | R74: 0 | T74: =+VLOOKUP(Tabla1[[#This Row],[id_bodega]],'CONVERSION DATOS'!B:D,2,0) -> LANZA | U74: =+VLOOKUP(Q74,'CONVERSION DATOS'!B:D,3,0) -> HUEVO SIN CLASIFICAR | V74: =+VLOOKUP($A$1:$A$21766,'DT HUEVO'!$A:$E,3,0) -> HUEVO SIN CLASIFICAR | W74: =+VLOOKUP($A$1:$A$21606,'DT HUEVO'!$A:$E,4,0) -> HUEVO SIN CLASIFICAR | X74: =+VLOOKUP(T$1:T$21766,'DT HUEVO'!$H:$K,2,0) -> - | Y74: =+VLOOKUP(T$1:T$21766,'DT HUEVO'!$H:$K,3,0) -> SANTANDER | Z74: =+VLOOKUP(A$1:A$21766,'DT HUEVO'!$A:$E,5,0) -> HUEVO SIN CLASIFICAR | AA74: =IF(Tabla1[[#This Row],[GRUPO]]="PLANTA CLASIFICACION","BODEGA",IF(Tabla1[[#This Row],[GRUPO]]="BODEGA","BODEGA",Tabla1[[#This Row],[GRUPO]])) -> HUEVO SIN CLASIFICAR | AB74: =VLOOKUP(Tabla1[[#This Row],[articulo]],'DT HUEVO'!$A:$F,6,0) -> SIN CL
A75: 2013322 | B75: HUEVO AA X 30 BAND GRIS AMARRADO TAPA VERDE ALAT CANASTA | C75: UN | D75: 12960 | F75: S | G75: IV82 | J75: HU | K75: HUEVO COMERCIAL | L75: 478.25 | M75: 46307 | N75: 0 | O75: CENTRO DE EMPAQUES CUCUTA | P75: 2013322 | Q75: CU | R75: 0 | T75: =+VLOOKUP(Tabla1[[#This Row],[id_bodega]],'CONVERSION DATOS'!B:D,2,0) -> TAT CUCUTA | U75: =+VLOOKUP(Q75,'CONVERSION DATOS'!B:D,3,0) -> BODEGA | V75: =+VLOOKUP($A$1:$A$21802,'DT HUEVO'!$A:$E,3,0) -> AA | W75: =+VLOOKUP($A$1:$A$21642,'DT HUEVO'!$A:$E,4,0) -> EMPACADOS | X75: =+VLOOKUP(T$1:T$21802,'DT HUEVO'!$H:$K,2,0) -> COSTA | Y75: =+VLOOKUP(T$1:T$21802,'DT HUEVO'!$H:$K,3,0) -> SANTANDER | Z75: =+VLOOKUP(A$1:A$21802,'DT HUEVO'!$A:$E,5,0) -> 0 | AA75: =IF(Tabla1[[#This Row],[GRUPO]]="PLANTA CLASIFICACION","BODEGA",IF(Tabla1[[#This Row],[GRUPO]]="BODEGA","BODEGA",Tabla1[[#This Row],[GRUPO]])) -> BODEGA | AB75: =VLOOKUP(Tabla1[[#This Row],[articulo]],'DT HUEVO'!$A:$F,6,0) -> HD
A76: 2013419 | B76: HUEVO A X 30 CARTON GRIS AMARRADO SOL NACIENTE CANASTA. | C76: UN | D76: 101520 | F76: S | G76: IV82 | J76: HU | K76: HUEVO COMERCIAL | L76: 406.83 | M76: 46307 | N76: 0 | O76: CENTRO DE EMPAQUES CUCUTA | P76: 2013419 | Q76: CU | R76: 0 | T76: =+VLOOKUP(Tabla1[[#This Row],[id_bodega]],'CONVERSION DATOS'!B:D,2,0) -> TAT CUCUTA | U76: =+VLOOKUP(Q76,'CONVERSION DATOS'!B:D,3,0) -> BODEGA | V76: =+VLOOKUP($A$1:$A$21802,'DT HUEVO'!$A:$E,3,0) -> A | W76: =+VLOOKUP($A$1:$A$21642,'DT HUEVO'!$A:$E,4,0) -> EMPACADOS | X76: =+VLOOKUP(T$1:T$21802,'DT HUEVO'!$H:$K,2,0) -> COSTA | Y76: =+VLOOKUP(T$1:T$21802,'DT HUEVO'!$H:$K,3,0) -> SANTANDER | Z76: =+VLOOKUP(A$1:A$21802,'DT HUEVO'!$A:$E,5,0) -> 0 | AA76: =IF(Tabla1[[#This Row],[GRUPO]]="PLANTA CLASIFICACION","BODEGA",IF(Tabla1[[#This Row],[GRUPO]]="BODEGA","BODEGA",Tabla1[[#This Row],[GRUPO]])) -> BODEGA | AB76: =VLOOKUP(Tabla1[[#This Row],[articulo]],'DT HUEVO'!$A:$F,6,0) -> HD
A77: 272008 | B77: HUEVO SUCIO BASE LAVADO ZF X 30 BANDEJA GRIS CANASTA | C77: UN | D77: 5684 | F77: S | G77: IV82 | J77: HU | K77: HUEVO COMERCIAL | L77: 188.68 | M77: 46308 | O77: ELABORACION DE PRODUCTOS - KI | P77: 272008 | Q77: EPKI | R77: 0 | T77: =+VLOOKUP(Tabla1[[#This Row],[id_bodega]],'CONVERSION DATOS'!B:D,2,0) -> LANZA | U77: =+VLOOKUP(Q77,'CONVERSION DATOS'!B:D,3,0) -> PLANTA CLASIFICACION | V77: =+VLOOKUP($A$1:$A$21802,'DT HUEVO'!$A:$E,3,0) -> SEGUNDA | W77: =+VLOOKUP($A$1:$A$21642,'DT HUEVO'!$A:$E,4,0) -> SEGUNDA | X77: =+VLOOKUP(T$1:T$21802,'DT HUEVO'!$H:$K,2,0) -> - | Y77: =+VLOOKUP(T$1:T$21802,'DT HUEVO'!$H:$K,3,0) -> SANTANDER | Z77: =+VLOOKUP(A$1:A$21802,'DT HUEVO'!$A:$E,5,0) -> 0 | AA77: =IF(Tabla1[[#This Row],[GRUPO]]="PLANTA CLASIFICACION","BODEGA",IF(Tabla1[[#This Row],[GRUPO]]="BODEGA","BODEGA",Tabla1[[#This Row],[GRUPO]])) -> BODEGA | AB77: =VLOOKUP(Tabla1[[#This Row],[articulo]],'DT HUEVO'!$A:$F,6,0) -> SEGUNDA
A78: 110316 | B78: HUEVO L X30 CARTON VERDE CON ETIQUETA | C78: UN | D78: 3600 | E78: 0 | F78: S | G78: IV82 | H78: 0 | I78: 535 | J78: HU | K78: HUEVO COMERCIAL | L78: 474.15 | M78: 46307 | O78: TAT BUCARAMANGA - FOOD SERVICE | P78: 110316 | Q78: FS1 | R78: 0 | T78: =+VLOOKUP(Tabla1[[#This Row],[id_bodega]],'CONVERSION DATOS'!B:D,2,0) -> TAT BUCARAMANGA | U78: =+VLOOKUP(Q78,'CONVERSION DATOS'!B:D,3,0) -> VEHICULOS | V78: =+VLOOKUP($A$1:$A$21802,'DT HUEVO'!$A:$E,3,0) -> L | W78: =+VLOOKUP($A$1:$A$21642,'DT HUEVO'!$A:$E,4,0) -> ETIQUETA | X78: =+VLOOKUP(T$1:T$21802,'DT HUEVO'!$H:$K,2,0) -> COSTA | Y78: =+VLOOKUP(T$1:T$21802,'DT HUEVO'!$H:$K,3,0) -> SANTANDER | Z78: =+VLOOKUP(A$1:A$21802,'DT HUEVO'!$A:$E,5,0) -> 0 | AA78: =IF(Tabla1[[#This Row],[GRUPO]]="PLANTA CLASIFICACION","BODEGA",IF(Tabla1[[#This Row],[GRUPO]]="BODEGA","BODEGA",Tabla1[[#This Row],[GRUPO]])) -> VEHICULOS | AB78: =VLOOKUP(Tabla1[[#This Row],[articulo]],'DT HUEVO'!$A:$F,6,0) -> AU/FS/GS
A79: 110316 | B79: HUEVO L X30 CARTON VERDE CON ETIQUETA | C79: UN | D79: 1400 | E79: 0 | F79: S | G79: IV82 | H79: 0 | I79: 555 | J79: HU | K79: HUEVO COMERCIAL | L79: 474.15 | M79: 46308 | O79: FOOD SERVICE PEREIRA - OP | P79: 110316 | Q79: FS36 | R79: 0 | T79: =+VLOOKUP(Tabla1[[#This Row],[id_bodega]],'CONVERSION DATOS'!B:D,2,0) -> TAT PEREIRA | U79: =+VLOOKUP(Q79,'CONVERSION DATOS'!B:D,3,0) -> VEHICULOS | V79: =+VLOOKUP($A$1:$A$21802,'DT HUEVO'!$A:$E,3,0) -> L | W79: =+VLOOKUP($A$1:$A$21642,'DT HUEVO'!$A:$E,4,0) -> ETIQUETA | X79: =+VLOOKUP(T$1:T$21802,'DT HUEVO'!$H:$K,2,0) -> OCCIDENTE | Y79: =+VLOOKUP(T$1:T$21802,'DT HUEVO'!$H:$K,3,0) -> CALOTO | Z79: =+VLOOKUP(A$1:A$21802,'DT HUEVO'!$A:$E,5,0) -> 0 | AA79: =IF(Tabla1[[#This Row],[GRUPO]]="PLANTA CLASIFICACION","BODEGA",IF(Tabla1[[#This Row],[GRUPO]]="BODEGA","BODEGA",Tabla1[[#This Row],[GRUPO]])) -> VEHICULOS | AB79: =VLOOKUP(Tabla1[[#This Row],[articulo]],'DT HUEVO'!$A:$F,6,0) -> AU/FS/GS
A80: 110416 | B80: HUEVO M X 30 CARTON VERDE CON ETIQUETA | C80: UN | D80: 90 | E80: 0 | F80: S | G80: IV82 | H80: 0 | I80: 460 | J80: HU | K80: HUEVO COMERCIAL | L80: 450.22 | M80: 46308 | O80: TAT BARRANQUILLA - FOOD SERVICE | P80: 110416 | Q80: FS4 | R80: 0 | T80: =+VLOOKUP(Tabla1[[#This Row],[id_bodega]],'CONVERSION DATOS'!B:D,2,0) -> TAT BARRANQUILLA | U80: =+VLOOKUP(Q80,'CONVERSION DATOS'!B:D,3,0) -> VEHICULOS | V80: =+VLOOKUP($A$1:$A$21802,'DT HUEVO'!$A:$E,3,0) -> M | W80: =+VLOOKUP($A$1:$A$21642,'DT HUEVO'!$A:$E,4,0) -> ETIQUETA | X80: =+VLOOKUP(T$1:T$21802,'DT HUEVO'!$H:$K,2,0) -> COSTA | Y80: =+VLOOKUP(T$1:T$21802,'DT HUEVO'!$H:$K,3,0) -> CALOTO | Z80: =+VLOOKUP(A$1:A$21802,'DT HUEVO'!$A:$E,5,0) -> 0 | AA80: =IF(Tabla1[[#This Row],[GRUPO]]="PLANTA CLASIFICACION","BODEGA",IF(Tabla1[[#This Row],[GRUPO]]="BODEGA","BODEGA",Tabla1[[#This Row],[GRUPO]])) -> VEHICULOS | AB80: =VLOOKUP(Tabla1[[#This Row],[articulo]],'DT HUEVO'!$A:$F,6,0) -> AU/FS/GS
A81: 110316 | B81: HUEVO L X30 CARTON VERDE CON ETIQUETA | C81: UN | D81: 1200 | E81: 0 | F81: S | G81: IV82 | H81: 0 | I81: 500 | J81: HU | K81: HUEVO COMERCIAL | L81: 474.15 | M81: 46308 | O81: TAT CARTAGENA - FOOD SERVICE | P81: 110316 | Q81: FS41 | R81: 0 | T81: =+VLOOKUP(Tabla1[[#This Row],[id_bodega]],'CONVERSION DATOS'!B:D,2,0) -> TAT CARTAGENA | U81: =+VLOOKUP(Q81,'CONVERSION DATOS'!B:D,3,0) -> VEHICULOS | V81: =+VLOOKUP($A$1:$A$21802,'DT HUEVO'!$A:$E,3,0) -> L | W81: =+VLOOKUP($A$1:$A$21642,'DT HUEVO'!$A:$E,4,0) -> ETIQUETA | X81: =+VLOOKUP(T$1:T$21802,'DT HUEVO'!$H:$K,2,0) -> COSTA | Y81: =+VLOOKUP(T$1:T$21802,'DT HUEVO'!$H:$K,3,0) -> CALOTO | Z81: =+VLOOKUP(A$1:A$21802,'DT HUEVO'!$A:$E,5,0) -> 0 | AA81: =IF(Tabla1[[#This Row],[GRUPO]]="PLANTA CLASIFICACION","BODEGA",IF(Tabla1[[#This Row],[GRUPO]]="BODEGA","BODEGA",Tabla1[[#This Row],[GRUPO]])) -> VEHICULOS | AB81: =VLOOKUP(Tabla1[[#This Row],[articulo]],'DT HUEVO'!$A:$F,6,0) -> AU/FS/GS
A82: 110416 | B82: HUEVO M X 30 CARTON VERDE CON ETIQUETA | C82: UN | D82: 15000 | E82: 0 | F82: S | G82: IV82 | H82: 0 | I82: 460 | J82: HU | K82: HUEVO COMERCIAL | L82: 450.22 | M82: 46308 | O82: TAT CARTAGENA - FOOD SERVICE | P82: 110416 | Q82: FS41 | R82: 0 | T82: =+VLOOKUP(Tabla1[[#This Row],[id_bodega]],'CONVERSION DATOS'!B:D,2,0) -> TAT CARTAGENA | U82: =+VLOOKUP(Q82,'CONVERSION DATOS'!B:D,3,0) -> VEHICULOS | V82: =+VLOOKUP($A$1:$A$21802,'DT HUEVO'!$A:$E,3,0) -> M | W82: =+VLOOKUP($A$1:$A$21642,'DT HUEVO'!$A:$E,4,0) -> ETIQUETA | X82: =+VLOOKUP(T$1:T$21802,'DT HUEVO'!$H:$K,2,0) -> COSTA | Y82: =+VLOOKUP(T$1:T$21802,'DT HUEVO'!$H:$K,3,0) -> CALOTO | Z82: =+VLOOKUP(A$1:A$21802,'DT HUEVO'!$A:$E,5,0) -> 0 | AA82: =IF(Tabla1[[#This Row],[GRUPO]]="PLANTA CLASIFICACION","BODEGA",IF(Tabla1[[#This Row],[GRUPO]]="BODEGA","BODEGA",Tabla1[[#This Row],[GRUPO]])) -> VEHICULOS | AB82: =VLOOKUP(Tabla1[[#This Row],[articulo]],'DT HUEVO'!$A:$F,6,0) -> AU/FS/GS
A83: 2110202 | B83: HUEVO XL X 30 CARTON VERDE CANASTA | C83: UN | D83: 540 | E83: 0 | F83: S | G83: IV82 | H83: 0 | I83: 475 | J83: HU | K83: HUEVO COMERCIAL | L83: 394.25972 | M83: 46307 | O83: TAT - FOOD SERVICE BOGOTA - FS59 | P83: 2110202 | Q83: FS59 | R83: 0 | T83: =+VLOOKUP(Tabla1[[#This Row],[id_bodega]],'CONVERSION DATOS'!B:D,2,0) -> TAT BOGOTA SIBERIA | U83: =+VLOOKUP(Q83,'CONVERSION DATOS'!B:D,3,0) -> VEHICULOS | V83: =+VLOOKUP($A$1:$A$21802,'DT HUEVO'!$A:$E,3,0) -> XL | W83: =+VLOOKUP($A$1:$A$21642,'DT HUEVO'!$A:$E,4,0) -> VERDE | X83: =+VLOOKUP(T$1:T$21802,'DT HUEVO'!$H:$K,2,0) -> CENTRO ORIENTE | Y83: =+VLOOKUP(T$1:T$21802,'DT HUEVO'!$H:$K,3,0) -> CALOTO | Z83: =+VLOOKUP(A$1:A$21802,'DT HUEVO'!$A:$E,5,0) -> 0 | AA83: =IF(Tabla1[[#This Row],[GRUPO]]="PLANTA CLASIFICACION","BODEGA",IF(Tabla1[[#This Row],[GRUPO]]="BODEGA","BODEGA",Tabla1[[#This Row],[GRUPO]])) -> VEHICULOS | AB83: =VLOOKUP(Tabla1[[#This Row],[articulo]],'DT HUEVO'!$A:$F,6,0) -> TAT
A84: 2110302 | B84: HUEVO L X 30 CARTON VERDE CANASTA | C84: UN | D84: 1920 | E84: 0 | F84: S | G84: IV82 | H84: 0 | I84: 430 | J84: HU | K84: HUEVO COMERCIAL | L84: 363.24006 | M84: 46307 | O84: TAT - FOOD SERVICE BOGOTA - FS59 | P84: 2110302 | Q84: FS59 | R84: 0 | T84: =+VLOOKUP(Tabla1[[#This Row],[id_bodega]],'CONVERSION DATOS'!B:D,2,0) -> TAT BOGOTA SIBERIA | U84: =+VLOOKUP(Q84,'CONVERSION DATOS'!B:D,3,0) -> VEHICULOS | V84: =+VLOOKUP($A$1:$A$21802,'DT HUEVO'!$A:$E,3,0) -> L | W84: =+VLOOKUP($A$1:$A$21642,'DT HUEVO'!$A:$E,4,0) -> VERDE | X84: =+VLOOKUP(T$1:T$21802,'DT HUEVO'!$H:$K,2,0) -> CENTRO ORIENTE | Y84: =+VLOOKUP(T$1:T$21802,'DT HUEVO'!$H:$K,3,0) -> CALOTO | Z84: =+VLOOKUP(A$1:A$21802,'DT HUEVO'!$A:$E,5,0) -> 0 | AA84: =IF(Tabla1[[#This Row],[GRUPO]]="PLANTA CLASIFICACION","BODEGA",IF(Tabla1[[#This Row],[GRUPO]]="BODEGA","BODEGA",Tabla1[[#This Row],[GRUPO]])) -> VEHICULOS | AB84: =VLOOKUP(Tabla1[[#This Row],[articulo]],'DT HUEVO'!$A:$F,6,0) -> TAT
A85: 2110402 | B85: HUEVO M X 30 CARTON VERDE CANASTA | C85: UN | D85: 1680 | E85: 0 | F85: S | G85: IV82 | H85: 0 | I85: 425 | J85: HU | K85: HUEVO COMERCIAL | L85: 349.55 | M85: 46307 | O85: TAT - FOOD SERVICE BOGOTA - FS59 | P85: 2110402 | Q85: FS59 | R85: 0 | T85: =+VLOOKUP(Tabla1[[#This Row],[id_bodega]],'CONVERSION DATOS'!B:D,2,0) -> TAT BOGOTA SIBERIA | U85: =+VLOOKUP(Q85,'CONVERSION DATOS'!B:D,3,0) -> VEHICULOS | V85: =+VLOOKUP($A$1:$A$21802,'DT HUEVO'!$A:$E,3,0) -> M | W85: =+VLOOKUP($A$1:$A$21642,'DT HUEVO'!$A:$E,4,0) -> VERDE | X85: =+VLOOKUP(T$1:T$21802,'DT HUEVO'!$H:$K,2,0) -> CENTRO ORIENTE | Y85: =+VLOOKUP(T$1:T$21802,'DT HUEVO'!$H:$K,3,0) -> CALOTO | Z85: =+VLOOKUP(A$1:A$21802,'DT HUEVO'!$A:$E,5,0) -> 0 | AA85: =IF(Tabla1[[#This Row],[GRUPO]]="PLANTA CLASIFICACION","BODEGA",IF(Tabla1[[#This Row],[GRUPO]]="BODEGA","BODEGA",Tabla1[[#This Row],[GRUPO]])) -> VEHICULOS | AB85: =VLOOKUP(Tabla1[[#This Row],[articulo]],'DT HUEVO'!$A:$F,6,0) -> TAT
A86: 76402 | B86: REVOLTURA HUEVO GK | C86: UN | D86: 600 | E86: 0 | F86: S | G86: IV82 | H86: 0 | I86: 400 | J86: HU | K86: HUEVO COMERCIAL | L86: 166 | M86: 46305 | N86: 76402 | O86: BODEGA DE CONSERVACION Y DESPACHO PUERTO TEJADA | P86: 76402 | Q86: GC25 | R86: 0 | T86: =+VLOOKUP(Tabla1[[#This Row],[id_bodega]],'CONVERSION DATOS'!B:D,2,0) -> 0 | U86: =+VLOOKUP(Q86,'CONVERSION DATOS'!B:D,3,0) -> BODEGA | V86: =+VLOOKUP($A$1:$A$21802,'DT HUEVO'!$A:$E,3,0) -> SEGUNDA | W86: =+VLOOKUP($A$1:$A$21642,'DT HUEVO'!$A:$E,4,0) -> SEGUNDA | X86: =+VLOOKUP(T$1:T$21802,'DT HUEVO'!$H:$K,2,0) -> #N/A | Y86: =+VLOOKUP(T$1:T$21802,'DT HUEVO'!$H:$K,3,0) -> #N/A | Z86: =+VLOOKUP(A$1:A$21802,'DT HUEVO'!$A:$E,5,0) -> REVOLTURA | AA86: =IF(Tabla1[[#This Row],[GRUPO]]="PLANTA CLASIFICACION","BODEGA",IF(Tabla1[[#This Row],[GRUPO]]="BODEGA","BODEGA",Tabla1[[#This Row],[GRUPO]])) -> BODEGA | AB86: =VLOOKUP(Tabla1[[#This Row],[articulo]],'DT HUEVO'!$A:$F,6,0) -> SEGUNDA
A87: 100 | B87: HUEVO SIN CLASIFICAR ROJO | C87: UN | D87: 645986 | F87: S | G87: IV82 | J87: HU | K87: HUEVO COMERCIAL | L87: 376.83 | M87: 46295 | N87: 100 | O87: GRANJAS DE PISO | P87: 100 | Q87: GP | R87: 0 | T87: =+VLOOKUP(Tabla1[[#This Row],[id_bodega]],'CONVERSION DATOS'!B:D,2,0) -> GRANJAS DE PISO | U87: =+VLOOKUP(Q87,'CONVERSION DATOS'!B:D,3,0) -> HUEVO SIN CLASIFICAR | V87: =+VLOOKUP($A$1:$A$21802,'DT HUEVO'!$A:$E,3,0) -> HUEVO SIN CLASIFICAR | W87: =+VLOOKUP($A$1:$A$21642,'DT HUEVO'!$A:$E,4,0) -> HUEVO SIN CLASIFICAR | X87: =+VLOOKUP(T$1:T$21802,'DT HUEVO'!$H:$K,2,0) -> - | Y87: =+VLOOKUP(T$1:T$21802,'DT HUEVO'!$H:$K,3,0) -> - | Z87: =+VLOOKUP(A$1:A$21802,'DT HUEVO'!$A:$E,5,0) -> HUEVO SIN CLASIFICAR | AA87: =IF(Tabla1[[#This Row],[GRUPO]]="PLANTA CLASIFICACION","BODEGA",IF(Tabla1[[#This Row],[GRUPO]]="BODEGA","BODEGA",Tabla1[[#This Row],[GRUPO]])) -> HUEVO SIN CLASIFICAR | AB87: =VLOOKUP(Tabla1[[#This Row],[articulo]],'DT HUEVO'!$A:$F,6,0) -> SIN CL
A88: 90 | B88: HUEVO ROJO SIN CLASIFICAR GRANJAS | C88: UN | D88: 1328840 | F88: S | G88: IV82 | J88: HU | K88: HUEVO COMERCIAL | L88: 1 | M88: 46308 | O88: HUEVO SIN CLASIFICAR | P88: 90 | Q88: GR | R88: 0 | T88: =+VLOOKUP(Tabla1[[#This Row],[id_bodega]],'CONVERSION DATOS'!B:D,2,0) -> HUEVO SIN CLASIFICAR | U88: =+VLOOKUP(Q88,'CONVERSION DATOS'!B:D,3,0) -> HUEVO SIN CLASIFICAR | V88: =+VLOOKUP($A$1:$A$21802,'DT HUEVO'!$A:$E,3,0) -> HUEVO SIN CLASIFICAR | W88: =+VLOOKUP($A$1:$A$21642,'DT HUEVO'!$A:$E,4,0) -> HUEVO SIN CLASIFICAR | X88: =+VLOOKUP(T$1:T$21802,'DT HUEVO'!$H:$K,2,0) -> - | Y88: =+VLOOKUP(T$1:T$21802,'DT HUEVO'!$H:$K,3,0) -> - | Z88: =+VLOOKUP(A$1:A$21802,'DT HUEVO'!$A:$E,5,0) -> HUEVO SIN CLASIFICAR | AA88: =IF(Tabla1[[#This Row],[GRUPO]]="PLANTA CLASIFICACION","BODEGA",IF(Tabla1[[#This Row],[GRUPO]]="BODEGA","BODEGA",Tabla1[[#This Row],[GRUPO]])) -> HUEVO SIN CLASIFICAR | AB88: =VLOOKUP(Tabla1[[#This Row],[articulo]],'DT HUEVO'!$A:$F,6,0) -> SIN CL
A89: 2110327 | B89: HUEVO L X 30 CARTON VERDE CANASTA - BGA | C89: UN | D89: 1 | E89: 0 | F89: S | G89: IV82 | H89: 0 | I89: 480 | J89: HU | K89: HUEVO COMERCIAL | L89: 359.32 | M89: 46305 | N89: 0 | O89: TAT BUCARAMANGA H1004 | P89: 2110327 | Q89: H1004 | R89: 0 | T89: =+VLOOKUP(Tabla1[[#This Row],[id_bodega]],'CONVERSION DATOS'!B:D,2,0) -> TAT BUCARAMANGA | U89: =+VLOOKUP(Q89,'CONVERSION DATOS'!B:D,3,0) -> VEHICULOS | V89: =+VLOOKUP($A$1:$A$21802,'DT HUEVO'!$A:$E,3,0) -> L | W89: =+VLOOKUP($A$1:$A$21642,'DT HUEVO'!$A:$E,4,0) -> VERDE | X89: =+VLOOKUP(T$1:T$21802,'DT HUEVO'!$H:$K,2,0) -> COSTA | Y89: =+VLOOKUP(T$1:T$21802,'DT HUEVO'!$H:$K,3,0) -> SANTANDER | Z89: =+VLOOKUP(A$1:A$21802,'DT HUEVO'!$A:$E,5,0) -> 0 | AA89: =IF(Tabla1[[#This Row],[GRUPO]]="PLANTA CLASIFICACION","BODEGA",IF(Tabla1[[#This Row],[GRUPO]]="BODEGA","BODEGA",Tabla1[[#This Row],[GRUPO]])) -> VEHICULOS | AB89: =VLOOKUP(Tabla1[[#This Row],[articulo]],'DT HUEVO'!$A:$F,6,0) -> TAT
A90: 2110427 | B90: HUEVO M X 30 CARTON VERDE CANASTA - BGA | C90: UN | D90: 1376 | E90: 0 | F90: S | G90: IV82 | H90: 0 | I90: 450 | J90: HU | K90: HUEVO COMERCIAL | L90: 328.87 | M90: 46308 | N90: 0 | O90: TAT BUCARAMANGA H1004 | P90: 2110427 | Q90: H1004 | R90: 0 | T90: =+VLOOKUP(Tabla1[[#This Row],[id_bodega]],'CONVERSION DATOS'!B:D,2,0) -> TAT BUCARAMANGA | U90: =+VLOOKUP(Q90,'CONVERSION DATOS'!B:D,3,0) -> VEHICULOS | V90: =+VLOOKUP($A$1:$A$21802,'DT HUEVO'!$A:$E,3,0) -> M | W90: =+VLOOKUP($A$1:$A$21642,'DT HUEVO'!$A:$E,4,0) -> VERDE | X90: =+VLOOKUP(T$1:T$21802,'DT HUEVO'!$H:$K,2,0) -> COSTA | Y90: =+VLOOKUP(T$1:T$21802,'DT HUEVO'!$H:$K,3,0) -> SANTANDER | Z90: =+VLOOKUP(A$1:A$21802,'DT HUEVO'!$A:$E,5,0) -> 0 | AA90: =IF(Tabla1[[#This Row],[GRUPO]]="PLANTA CLASIFICACION","BODEGA",IF(Tabla1[[#This Row],[GRUPO]]="BODEGA","BODEGA",Tabla1[[#This Row],[GRUPO]])) -> VEHICULOS | AB90: =VLOOKUP(Tabla1[[#This Row],[articulo]],'DT HUEVO'!$A:$F,6,0) -> TAT
A91: 2110327 | B91: HUEVO L X 30 CARTON VERDE CANASTA - BGA | C91: UN | D91: 837 | E91: 0 | F91: S | G91: IV82 | H91: 0 | I91: 480 | J91: HU | K91: HUEVO COMERCIAL | L91: 359.32 | M91: 46305 | N91: 0 | O91: TAT BUCARAMANGA H1005 | P91: 2110327 | Q91: H1005 | R91: 0 | T91: =+VLOOKUP(Tabla1[[#This Row],[id_bodega]],'CONVERSION DATOS'!B:D,2,0) -> TAT BUCARAMANGA | U91: =+VLOOKUP(Q91,'CONVERSION DATOS'!B:D,3,0) -> VEHICULOS | V91: =+VLOOKUP($A$1:$A$21802,'DT HUEVO'!$A:$E,3,0) -> L | W91: =+VLOOKUP($A$1:$A$21642,'DT HUEVO'!$A:$E,4,0) -> VERDE | X91: =+VLOOKUP(T$1:T$21802,'DT HUEVO'!$H:$K,2,0) -> COSTA | Y91: =+VLOOKUP(T$1:T$21802,'DT HUEVO'!$H:$K,3,0) -> SANTANDER | Z91: =+VLOOKUP(A$1:A$21802,'DT HUEVO'!$A:$E,5,0) -> 0 | AA91: =IF(Tabla1[[#This Row],[GRUPO]]="PLANTA CLASIFICACION","BODEGA",IF(Tabla1[[#This Row],[GRUPO]]="BODEGA","BODEGA",Tabla1[[#This Row],[GRUPO]])) -> VEHICULOS | AB91: =VLOOKUP(Tabla1[[#This Row],[articulo]],'DT HUEVO'!$A:$F,6,0) -> TAT
A92: 2152388 | B92: HUEVO L X 15 PAGUE 14 PET EN CANASTA. | C92: UN | D92: 60 | E92: 0 | F92: S | G92: IV82 | H92: 0 | I92: 530 | J92: HU | K92: HUEVO COMERCIAL | L92: 538.38 | M92: 46305 | O92: TAT BUCARAMANGA H1005 | P92: 2152388 | Q92: H1005 | R92: 0 | T92: =+VLOOKUP(Tabla1[[#This Row],[id_bodega]],'CONVERSION DATOS'!B:D,2,0) -> TAT BUCARAMANGA | U92: =+VLOOKUP(Q92,'CONVERSION DATOS'!B:D,3,0) -> VEHICULOS | V92: =+VLOOKUP($A$1:$A$21802,'DT HUEVO'!$A:$E,3,0) -> L | W92: =+VLOOKUP($A$1:$A$21642,'DT HUEVO'!$A:$E,4,0) -> EMPACADOS | X92: =+VLOOKUP(T$1:T$21802,'DT HUEVO'!$H:$K,2,0) -> COSTA | Y92: =+VLOOKUP(T$1:T$21802,'DT HUEVO'!$H:$K,3,0) -> SANTANDER | Z92: =+VLOOKUP(A$1:A$21802,'DT HUEVO'!$A:$E,5,0) -> 0 | AA92: =IF(Tabla1[[#This Row],[GRUPO]]="PLANTA CLASIFICACION","BODEGA",IF(Tabla1[[#This Row],[GRUPO]]="BODEGA","BODEGA",Tabla1[[#This Row],[GRUPO]])) -> VEHICULOS | AB92: =VLOOKUP(Tabla1[[#This Row],[articulo]],'DT HUEVO'!$A:$F,6,0) -> TAT
A93: 2110327 | B93: HUEVO L X 30 CARTON VERDE CANASTA - BGA | C93: UN | D93: 1665 | E93: 0 | F93: S | G93: IV82 | H93: 0 | I93: 480 | J93: HU | K93: HUEVO COMERCIAL | L93: 359.32 | M93: 46305 | N93: 0 | O93: TAT BUCARAMANGA H1006 | P93: 2110327 | Q93: H1006 | R93: 0 | T93: =+VLOOKUP(Tabla1[[#This Row],[id_bodega]],'CONVERSION DATOS'!B:D,2,0) -> TAT BUCARAMANGA | U93: =+VLOOKUP(Q93,'CONVERSION DATOS'!B:D,3,0) -> VEHICULOS | V93: =+VLOOKUP($A$1:$A$21802,'DT HUEVO'!$A:$E,3,0) -> L | W93: =+VLOOKUP($A$1:$A$21642,'DT HUEVO'!$A:$E,4,0) -> VERDE | X93: =+VLOOKUP(T$1:T$21802,'DT HUEVO'!$H:$K,2,0) -> COSTA | Y93: =+VLOOKUP(T$1:T$21802,'DT HUEVO'!$H:$K,3,0) -> SANTANDER | Z93: =+VLOOKUP(A$1:A$21802,'DT HUEVO'!$A:$E,5,0) -> 0 | AA93: =IF(Tabla1[[#This Row],[GRUPO]]="PLANTA CLASIFICACION","BODEGA",IF(Tabla1[[#This Row],[GRUPO]]="BODEGA","BODEGA",Tabla1[[#This Row],[GRUPO]])) -> VEHICULOS | AB93: =VLOOKUP(Tabla1[[#This Row],[articulo]],'DT HUEVO'!$A:$F,6,0) -> TAT
A94: 2110427 | B94: HUEVO M X 30 CARTON VERDE CANASTA - BGA | C94: UN | D94: 855 | E94: 0 | F94: S | G94: IV82 | H94: 0 | I94: 450 | J94: HU | K94: HUEVO COMERCIAL | L94: 328.87 | M94: 46305 | N94: 0 | O94: TAT BUCARAMANGA H1006 | P94: 2110427 | Q94: H1006 | R94: 0 | T94: =+VLOOKUP(Tabla1[[#This Row],[id_bodega]],'CONVERSION DATOS'!B:D,2,0) -> TAT BUCARAMANGA | U94: =+VLOOKUP(Q94,'CONVERSION DATOS'!B:D,3,0) -> VEHICULOS | V94: =+VLOOKUP($A$1:$A$21802,'DT HUEVO'!$A:$E,3,0) -> M | W94: =+VLOOKUP($A$1:$A$21642,'DT HUEVO'!$A:$E,4,0) -> VERDE | X94: =+VLOOKUP(T$1:T$21802,'DT HUEVO'!$H:$K,2,0) -> COSTA | Y94: =+VLOOKUP(T$1:T$21802,'DT HUEVO'!$H:$K,3,0) -> SANTANDER | Z94: =+VLOOKUP(A$1:A$21802,'DT HUEVO'!$A:$E,5,0) -> 0 | AA94: =IF(Tabla1[[#This Row],[GRUPO]]="PLANTA CLASIFICACION","BODEGA",IF(Tabla1[[#This Row],[GRUPO]]="BODEGA","BODEGA",Tabla1[[#This Row],[GRUPO]])) -> VEHICULOS | AB94: =VLOOKUP(Tabla1[[#This Row],[articulo]],'DT HUEVO'!$A:$F,6,0) -> TAT
A95: 2112207 | B95: HUEVO XL X 15 PET CANASTA | C95: UN | D95: 150 | E95: 0 | F95: S | G95: IV82 | H95: 0 | I95: 640 | J95: HU | K95: HUEVO COMERCIAL | L95: 599.68 | M95: 46305 | O95: TAT BUCARAMANGA H1006 | P95: 2112207 | Q95: H1006 | R95: 0 | T95: =+VLOOKUP(Tabla1[[#This Row],[id_bodega]],'CONVERSION DATOS'!B:D,2,0) -> TAT BUCARAMANGA | U95: =+VLOOKUP(Q95,'CONVERSION DATOS'!B:D,3,0) -> VEHICULOS | V95: =+VLOOKUP($A$1:$A$21824,'DT HUEVO'!$A:$E,3,0) -> XL | W95: =+VLOOKUP($A$1:$A$21664,'DT HUEVO'!$A:$E,4,0) -> EMPACADOS | X95: =+VLOOKUP(T$1:T$21824,'DT HUEVO'!$H:$K,2,0) -> COSTA | Y95: =+VLOOKUP(T$1:T$21824,'DT HUEVO'!$H:$K,3,0) -> SANTANDER | Z95: =+VLOOKUP(A$1:A$21824,'DT HUEVO'!$A:$E,5,0) -> TAT | AA95: =IF(Tabla1[[#This Row],[GRUPO]]="PLANTA CLASIFICACION","BODEGA",IF(Tabla1[[#This Row],[GRUPO]]="BODEGA","BODEGA",Tabla1[[#This Row],[GRUPO]])) -> VEHICULOS | AB95: =VLOOKUP(Tabla1[[#This Row],[articulo]],'DT HUEVO'!$A:$F,6,0) -> TAT
A96: 2152388 | B96: HUEVO L X 15 PAGUE 14 PET EN CANASTA. | C96: UN | D96: 120 | E96: 0 | F96: S | G96: IV82 | H96: 0 | I96: 530 | J96: HU | K96: HUEVO COMERCIAL | L96: 538.38 | M96: 46305 | O96: TAT BUCARAMANGA H1006 | P96: 2152388 | Q96: H1006 | R96: 0 | T96: =+VLOOKUP(Tabla1[[#This Row],[id_bodega]],'CONVERSION DATOS'!B:D,2,0) -> TAT BUCARAMANGA | U96: =+VLOOKUP(Q96,'CONVERSION DATOS'!B:D,3,0) -> VEHICULOS | V96: =+VLOOKUP($A$1:$A$21824,'DT HUEVO'!$A:$E,3,0) -> L | W96: =+VLOOKUP($A$1:$A$21664,'DT HUEVO'!$A:$E,4,0) -> EMPACADOS | X96: =+VLOOKUP(T$1:T$21824,'DT HUEVO'!$H:$K,2,0) -> COSTA | Y96: =+VLOOKUP(T$1:T$21824,'DT HUEVO'!$H:$K,3,0) -> SANTANDER | Z96: =+VLOOKUP(A$1:A$21824,'DT HUEVO'!$A:$E,5,0) -> 0 | AA96: =IF(Tabla1[[#This Row],[GRUPO]]="PLANTA CLASIFICACION","BODEGA",IF(Tabla1[[#This Row],[GRUPO]]="BODEGA","BODEGA",Tabla1[[#This Row],[GRUPO]])) -> VEHICULOS | AB96: =VLOOKUP(Tabla1[[#This Row],[articulo]],'DT HUEVO'!$A:$F,6,0) -> TAT
